Workbook
Name _1: #REF!
Name M: #REF!

Sheet Info
A3: Client : | C3: Forest Car Company Ltd
A4: Year-end : | E4: PYE :
A5: From : | C5: 44783 | E5: NA
A6: To : | C6: 45260 | E6: NA
A8: Prepared By : | C8: Aratee
A9: Date : | C9: 45343
A11: Reviewed By : | C11: Mitesh
A12: Date : | C12: 45352
A14: Nature of business : | C14: Sale of used cars and light motor vehicles

Sheet Notes
B2: Client : | C2: =Info!C3 -> Forest Car Company Ltd | D2: Prepared by : | E2: =Info!C8 -> Aratee
B3: Year end : | C3: =Info!C6 -> 45260 | D3: Reviewed by : | E3: =Info!C11 -> Mitesh
B5: Notes and observations
B7: Sr. No | C7: Particulars | D7: Hyperlink | E7: Your remarks
B8: [A] | C8: GENERAL
B10: 1 | C10: Approach
C11: Accounts have been prepared based on VAT return record which includes sales, purchase and expense. We have matched bank with trade creditors and trade debtors and booked additional purchase, expense and sales from bank. We have passed necessary journal entries to prepare draft account. Please confirm.
C13: Current year is first year of business organisation, Paid up capital of 100 No. of shares price of £1 each introduce through DCA.
C15: Current year we have estimate expense Telephone £900. Please confirm.
B17: [B] | C17: BALANCE SHEET ITEMS
B19: =+B10+1 -> 2 | C19: Fixed Assets
B21: a) | C21: Intangible
D22: Fixed Assets - Intangible
B24: b) | C24: Tangible
C26: Fixtures & Fittings | D26: F2 - Tangible FA
C27: Current year there is addition of £599. We have calculated depreciation at 20% RBM. Please Confirm. | D27: F4 - FAR
C29: Computer Equipment | D29: Reallocations
C30: Current year there is addition of £1,653. We have calculated depreciation at 20% RBM. Please Confirm.
B32: =+B19+1 -> 3 | C32: Stock
C33: We have booked closing stock of £44,938 as per stock sheet. | D33: C1 - Stock
B35: =+B32+1 -> 4 | C35: Debtors
C36: At the end of the year, balance is £5,200. | D36: C2-1 - Trade debtors
B38: 5 | C38: Other debtors- (TAXcal code -4420)
D39: C2-2 - Other debtors
B42: =B38+1 -> 6 | C42: Other debtors- inter co. (TAXcal code -4423)
D43: Other Debtors - Inter company
B49: =B42+1 -> 7 | C49: Other debtors- CIS. (TAXcal code -4424)
D50: C2-6 - CIS
B51: =+B35+1 -> 5 | C51: Bank and cash
C52: Barclays Bank A/c. No.: 30470120
C53: At the end of the year, balance is £44,032. It matches with the closing bank statement.
C55: Barclays Bank A/c. No.: 50237620
C56: At the end of the year, balance is £50,000. It matches with the closing bank statement.
C58: Cash
C59: At the end of the year, balance is £1,022. | D59: C3 - Bank & Cash
C60: We have adjusted following through cash :- -Trade Creditors £68,455 adjusted. -Trade Debtors £71,072 adjusted. - Wages £630 paid through cash. - Cash £13,784 introduce through DCA.
C61: Please confirm.
B63: =+B51+1 -> 6 | C63: VAT | D63: C4-2 - VAT
C64: At the end of the year there is VAT payable of £2,862. Please confirm. | D64: VAT Rec
B66: =+B63+1 -> 7 | C66: Prepayments
D68: C2-3 - Prepayments
B70: =+B66+1 -> 8 | C70: Bank and cash
D75: C3 - Bank & Cash
B79: =+B63+1 -> 7 | C79: Trade Creditors
C80: At the end of the year, £677 outstanding balance . | D80: C4-1 - Trade creditors
B82: =+B79+1 -> 8 | C82: Other creditors
D84: C4-5 - Other creditors
B86: =+B79+1 -> 8 | C86: PAYE/NIC
C87: At the end of the year, PAYE/NIC liability is Nil. Please confirm. | D87: C4-4 - PAYE/NIC
B89: =B86+1 -> 9 | C89: Accruals
D91: C4-6 - Accruals
B92: =+B86+1 -> 9 | C92: Net wages
C93: At the end of the year, balance is £1,040 for the month of Nov 23. Please confirm. | D93: C4-10 - Net wages'!
B95: =+B92+1 -> 10 | C95: Corporation tax
C96: Corporation tax provision for current year is £913. Please confirm. | D96: C4-3 - CT
B98: =+B95+1 -> 11 | C98: Directors current account
C99: At the end of the year, balance is £135,708 Please confirm.
C100: Adjustment as per below : - - Share capital £100 introduce through DCA. - Director's Remuneration £11,440 booked. - Trade creditors £257,100 adjusted. - Trade debtors £1,300 adjusted. - Estimate expenses £1,940 booked. - Expense £13,204 move to DCA. (Refreshment £6,896, Clothing £1,143 and Cleaning £5,165) - Estimate income of £105,000 booked. | D100: C4-7 - DCA
B102: =+B98+1 -> 12 | C102: Hire purchase
D103: C4-9 - HP < 1
B109: =B102+1 -> 13 | C109: Loan
D110: L1 - Loan > 1
B112: =B109+1 -> 14 | C112: Deferred Tax
D113: D - Deferred tax
B115: [C] | C115: PROFIT & LOSS ACCOUNT ITEMS
B117: =B112+1 -> 15
B121: =B117+1 -> 16
B124: =B121+1 -> 17
B128: =B124+1 -> 18
B131: =B128+1 -> 19
D132: Reallocations
B134: =B131+1 -> 20
B137: =B134+1 -> 21
B141: =B137+1 -> 22

Sheet Input Summary
A1: Client: | B1: =Info!C3 -> Forest Car Company Ltd | F1: Prepared by: | G1: =+Info!C8 -> Aratee
A2: File No: | B2: 7033 | F2: Date : | G2: =+Info!C9 -> 45343
A3: Accounting Period: | C3: =Info!C5 -> 44783
A4: Trading Period: | C4: =Info!C6 -> 45260 | F4: Reviewed by: | G4: =+Info!C11 -> Mitesh
F5: Date : | G5: =+Info!C12 -> 45352
B7: EXPENSE SUMMARY
A9: Sr No | B9: VAT Ref | C9: Date | D9: Particulars | E9: IRIS | F9: Net | G9: Vat | H9: Gross
A11: 19 | B11: VP FEB 23-34 | C11: 44901 | D11: A BAUID | E11: 27 | F11: 2000 | G11: 0 | H11: 2000 | I11: =VLOOKUP($E11,ETB!$B$66:$C$674,2,0) -> Purchases
A12: 74 | B12: VP QE MAY 23/22 | C12: 44994 | D12: A CARPENTER | E12: 27 | F12: 2500 | G12: 0 | H12: 2500 | I12: =VLOOKUP($E12,ETB!$B$66:$C$674,2,0) -> Purchases
A13: 187 | B13: VP QE NOV 23/21 | C13: 45170 | D13: A NORTON | E13: 27 | F13: 900 | G13: 0 | H13: 900 | I13: =VLOOKUP($E13,ETB!$B$66:$C$674,2,0) -> Purchases
A14: 3 | B14: VP FEB 23-23 | C14: 44872 | D14: ABDUL ALI | E14: 27 | F14: 3500 | G14: 0 | H14: 3500 | I14: =VLOOKUP($E14,ETB!$B$66:$C$674,2,0) -> Purchases
A15: 40 | B15: STOCK SHEET FEB 23 | C15: 44942 | D15: ADS | E15: 27 | F15: 3500 | G15: 0 | H15: 3500 | I15: =VLOOKUP($E15,ETB!$B$66:$C$674,2,0) -> Purchases
A16: 43 | B16: STOCK SHEET FEB 23 | C16: 44943 | D16: ADS | E16: 27 | F16: 1700 | G16: 0 | H16: 1700 | I16: =VLOOKUP($E16,ETB!$B$66:$C$674,2,0) -> Purchases
A17: 56 | B17: STOCK SHEET FEB 23 | C17: 44969 | D17: ADS | E17: 27 | F17: 300 | G17: 0 | H17: 300 | I17: =VLOOKUP($E17,ETB!$B$66:$C$674,2,0) -> Purchases
A18: 231 | B18: VP QE NOV 23/74 | C18: 45170 | D18: ADS | E18: 27 | F18: 1600 | G18: 0 | H18: 1600 | I18: =VLOOKUP($E18,ETB!$B$66:$C$674,2,0) -> Purchases
A19: 215 | B19: VP QE NOV 23/56 | C19: 45183 | D19: AGNES WALSH | E19: 27 | F19: 2350 | G19: 0 | H19: 2350 | I19: =VLOOKUP($E19,ETB!$B$66:$C$674,2,0) -> Purchases
A20: 144 | B20: VP QE AUG 23/41 | C20: 45079 | D20: ALAN DAVIS | E20: 27 | F20: 800 | G20: 0 | H20: 800 | I20: =VLOOKUP($E20,ETB!$B$66:$C$674,2,0) -> Purchases
A21: 217 | B21: VP QE NOV 23/59 | C21: 45177 | D21: ANDREW COOKE | E21: 27 | F21: 3900 | G21: 0 | H21: 3900 | I21: =VLOOKUP($E21,ETB!$B$66:$C$674,2,0) -> Purchases
A22: 1 | B22: VP FEB 23-11 | C22: 44870 | D22: B BROWN | E22: 27 | F22: 1500 | G22: 0 | H22: 1500 | I22: =VLOOKUP($E22,ETB!$B$66:$C$674,2,0) -> Purchases
... A254: 204 | B254: VP QE NOV 23/40 | C254: 45174 | D254: ZORAN REPAS | E254: 27 | F254: 2400 | G254: 0 | H254: 2400 | I254: =VLOOKUP($E254,ETB!$B$66:$C$674,2,0) -> Purchases
E256: 27 Total | F256: =SUBTOTAL(9,F11:F254) -> 532927.8 | G256: =SUBTOTAL(9,G11:G254) -> 0 | H256: =SUBTOTAL(9,H11:H254) -> 532927.8
A258: 1406 | B258: 1218 | C258: 45226 | D258: AGS WINDSCREEN | E258: 54 | F258: 630 | G258: 126 | H258: 756 | I258: =VLOOKUP($E258,ETB!$B$66:$C$674,2,0) -> Direct cost
A259: 1041 | B259: 834 | C259: 45110 | D259: AMAZON | E259: 54 | F259: 2.78 | G259: 0.55 | H259: 3.33 | I259: =VLOOKUP($E259,ETB!$B$66:$C$674,2,0) -> Direct cost
A260: 1042 | B260: 835 | C260: 45084 | D260: AMAZON | E260: 54 | F260: 15.53 | G260: 3.1 | H260: 18.63 | I260: =VLOOKUP($E260,ETB!$B$66:$C$674,2,0) -> Direct cost
A261: 1043 | B261: 836 | C261: 45104 | D261: AMAZON | E261: 54 | F261: 18.95 | G261: 3.79 | H261: 22.74 | I261: =VLOOKUP($E261,ETB!$B$66:$C$674,2,0) -> Direct cost
A262: 1044 | B262: 837 | C262: 45093 | D262: AMAZON | E262: 54 | F262: 26.63 | G262: 5.32 | H262: 31.95 | I262: =VLOOKUP($E262,ETB!$B$66:$C$674,2,0) -> Direct cost
A263: 1045 | B263: 838 | C263: 45096 | D263: AMAZON | E263: 54 | F263: 2.74 | G263: 0.55 | H263: 3.29 | I263: =VLOOKUP($E263,ETB!$B$66:$C$674,2,0) -> Direct cost
A264: 1046 | B264: 839 | C264: 45118 | D264: AMAZON | E264: 54 | F264: 12.49 | G264: 2.5 | H264: 14.99 | I264: =VLOOKUP($E264,ETB!$B$66:$C$674,2,0) -> Direct cost
A265: 1047 | B265: 840 | C265: 45093 | D265: AMAZON | E265: 54 | F265: 23.28 | G265: 4.66 | H265: 27.94 | I265: =VLOOKUP($E265,ETB!$B$66:$C$674,2,0) -> Direct cost
A266: 1048 | B266: 841 | C266: 45125 | D266: AMAZON | E266: 54 | F266: 13.33 | G266: 2.66 | H266: 15.99 | I266: =VLOOKUP($E266,ETB!$B$66:$C$674,2,0) -> Direct cost
A267: 1049 | B267: 842 | C267: 45125 | D267: AMAZON | E267: 54 | F267: 7.79 | G267: 1.56 | H267: 9.35 | I267: =VLOOKUP($E267,ETB!$B$66:$C$674,2,0) -> Direct cost
A268: 1050 | B268: 843 | C268: 45125 | D268: AMAZON | E268: 54 | F268: 5.58 | G268: 1.11 | H268: 6.69 | I268: =VLOOKUP($E268,ETB!$B$66:$C$674,2,0) -> Direct cost
A269: 1051 | B269: 844 | C269: 45159 | D269: AMAZON | E269: 54 | F269: 65.38 | G269: 13.07 | H269: 78.45 | I269: =VLOOKUP($E269,ETB!$B$66:$C$674,2,0) -> Direct cost
... A376: 1467 | B376: 1280 | C376: 45236 | D376: DVLA | E376: 54 | F376: 25.37 | G376: 0 | H376: 25.37 | I376: =VLOOKUP($E376,ETB!$B$66:$C$674,2,0) -> Direct cost
A377: 689 | B377: x` | C377: 45019 | D377: DVLA | E377: 54 | F377: 25.37 | G377: 0 | H377: 25.37 | I377: =VLOOKUP($E377,ETB!$B$66:$C$674,2,0) -> Direct cost
A378: 310 | B378: 67 | C378: 44945 | D378: EBAY | E378: 54 | F378: 112.92 | G378: 22.58 | H378: 135.5 | I378: =VLOOKUP($E378,ETB!$B$66:$C$674,2,0) -> Direct cost
A379: 311 | B379: 70 | C379: 44927 | D379: EBAY | E379: 54 | F379: 13.9 | G379: 0 | H379: 13.9 | I379: =VLOOKUP($E379,ETB!$B$66:$C$674,2,0) -> Direct cost
A380: 312 | B380: 71 | C380: 44927 | D380: EBAY | E380: 54 | F380: 39.95 | G380: 0 | H380: 39.95 | I380: =VLOOKUP($E380,ETB!$B$66:$C$674,2,0) -> Direct cost
A381: 313 | B381: 72 | C381: 44972 | D381: EBAY | E381: 54 | F381: 40.62 | G381: 8.12 | H381: 48.74 | I381: =VLOOKUP($E381,ETB!$B$66:$C$674,2,0) -> Direct cost
A382: 314 | B382: 74 | C382: 44966 | D382: EBAY | E382: 54 | F382: 26.83 | G382: 5.36 | H382: 32.19 | I382: =VLOOKUP($E382,ETB!$B$66:$C$674,2,0) -> Direct cost
A383: 328 | B383: 96 | C383: 44981 | D383: EBAY | E383: 54 | F383: 29.92 | G383: 5.98 | H383: 35.9 | I383: =VLOOKUP($E383,ETB!$B$66:$C$674,2,0) -> Direct cost
A384: 349 | B384: 123 | C384: 44972 | D384: EBAY | E384: 54 | F384: 21.46 | G384: 4.29 | H384: 25.75 | I384: =VLOOKUP($E384,ETB!$B$66:$C$674,2,0) -> Direct cost
A385: 350 | B385: 124 | C385: 44972 | D385: EBAY | E385: 54 | F385: 19.16 | G385: 3.83 | H385: 22.99 | I385: =VLOOKUP($E385,ETB!$B$66:$C$674,2,0) -> Direct cost
A386: 351 | B386: 125 | C386: 44971 | D386: EBAY | E386: 54 | F386: 73.33 | G386: 14.66 | H386: 87.99 | I386: =VLOOKUP($E386,ETB!$B$66:$C$674,2,0) -> Direct cost
A387: 352 | B387: 126 | C387: 44948 | D387: EBAY | E387: 54 | F387: 83.33 | G387: 16.67 | H387: 100 | I387: =VLOOKUP($E387,ETB!$B$66:$C$674,2,0) -> Direct cost
A388: 353 | B388: 127 | C388: 44945 | D388: EBAY | E388: 54 | F388: 13.33 | G388: 2.66 | H388: 15.99 | I388: =VLOOKUP($E388,ETB!$B$66:$C$674,2,0) -> Direct cost
A389: 354 | B389: 128 | C389: 44945 | D389: EBAY | E389: 54 | F389: 32.45 | G389: 6.49 | H389: 38.94 | I389: =VLOOKUP($E389,ETB!$B$66:$C$674,2,0) -> Direct cost
... A1040: 401 | B1040: 179 | C1040: 44965 | D1040: YSS TYRES LTD | E1040: 54 | F1040: 60 | G1040: 0 | H1040: 60 | I1040: =VLOOKUP($E1040,ETB!$B$66:$C$674,2,0) -> Direct cost
E1042: 54 Total | F1042: =SUBTOTAL(9,F258:F1040) -> 121276.15 | G1042: =SUBTOTAL(9,G258:G1040) -> 12006.7 | H1042: =SUBTOTAL(9,H258:H1040) -> 133282.85
A1044: 277 | B1044: 33 | C1044: 44971 | D1044: COSTCO WHOLESALE | E1044: 261 | F1044: 227.94 | G1044: 45.59 | H1044: 273.53 | I1044: =VLOOKUP($E1044,ETB!$B$66:$C$674,2,0) -> Refreshments
A1045: 337 | B1045: 107 | C1045: 44927 | D1045: COSTCO WHOLESALE | E1045: 261 | F1045: 472.69 | G1045: 84.92 | H1045: 557.61 | I1045: =VLOOKUP($E1045,ETB!$B$66:$C$674,2,0) -> Refreshments
A1046: 666 | B1046: 451 | C1046: 44994 | D1046: COSTCO WHOLESALE | E1046: 261 | F1046: 301.31 | G1046: 53.93 | H1046: 355.24 | I1046: =VLOOKUP($E1046,ETB!$B$66:$C$674,2,0) -> Refreshments
A1047: 667 | B1047: 452 | C1047: 45048 | D1047: COSTCO WHOLESALE | E1047: 261 | F1047: 512.72 | G1047: 98.08 | H1047: 610.8 | I1047: =VLOOKUP($E1047,ETB!$B$66:$C$674,2,0) -> Refreshments
A1048: 681 | B1048: 468 | C1048: 45027 | D1048: COSTCO WHOLESALE | E1048: 261 | F1048: 331.88 | G1048: 66.38 | H1048: 398.26 | I1048: =VLOOKUP($E1048,ETB!$B$66:$C$674,2,0) -> Refreshments
A1049: 260 | B1049: 16 | C1049: 44945 | D1049: REFRESHMENT | E1049: 261 | F1049: 57 | G1049: 0 | H1049: 57 | I1049: =VLOOKUP($E1049,ETB!$B$66:$C$674,2,0) -> Refreshments
A1050: 261 | B1050: 17 | C1050: 44945 | D1050: REFRESHMENT | E1050: 261 | F1050: 38 | G1050: 0 | H1050: 38 | I1050: =VLOOKUP($E1050,ETB!$B$66:$C$674,2,0) -> Refreshments
A1051: 263 | B1051: 19 | C1051: 44951 | D1051: REFRESHMENT | E1051: 261 | F1051: 85.12 | G1051: 17.03 | H1051: 102.15 | I1051: =VLOOKUP($E1051,ETB!$B$66:$C$674,2,0) -> Refreshments
A1052: 268 | B1052: 24 | C1052: 44962 | D1052: REFRESHMENT | E1052: 261 | F1052: 291.66 | G1052: 0 | H1052: 291.66 | I1052: =VLOOKUP($E1052,ETB!$B$66:$C$674,2,0) -> Refreshments
A1053: 269 | B1053: 25 | C1053: 44953 | D1053: REFRESHMENT | E1053: 261 | F1053: 30.04 | G1053: 6.01 | H1053: 36.05 | I1053: =VLOOKUP($E1053,ETB!$B$66:$C$674,2,0) -> Refreshments
A1054: 271 | B1054: 27 | C1054: 44971 | D1054: REFRESHMENT | E1054: 261 | F1054: 96.58 | G1054: 0 | H1054: 96.58 | I1054: =VLOOKUP($E1054,ETB!$B$66:$C$674,2,0) -> Refreshments
A1055: 272 | B1055: 28 | C1055: 44927 | D1055: REFRESHMENT | E1055: 261 | F1055: 7.69 | G1055: 0 | H1055: 7.69 | I1055: =VLOOKUP($E1055,ETB!$B$66:$C$674,2,0) -> Refreshments
... A1097: 1491 | B1097: 1304 | C1097: 45250 | D1097: SUNDRY EXPENSE | E1097: 261 | F1097: 35.94 | G1097: 0 | H1097: 35.94 | I1097: =VLOOKUP($E1097,ETB!$B$66:$C$674,2,0) -> Refreshments
E1099: 261 Total | F1099: =SUBTOTAL(9,F1044:F1097) -> 6559.63 | G1099: =SUBTOTAL(9,G1044:G1097) -> 833.35 | H1099: =SUBTOTAL(9,H1044:H1097) -> 7392.98
A1101: 266 | B1101: 22 | C1101: 44978 | D1101: POST OFFICE LTD | E1101: 264 | F1101: 5.55 | G1101: 0 | H1101: 5.55 | I1101: =VLOOKUP($E1101,ETB!$B$66:$C$674,2,0) -> Printing, Post and Stationery
A1102: 1487 | B1102: 1300 | C1102: 45236 | D1102: SUNDRY EXPENSE | E1102: 264 | F1102: 166.67 | G1102: 33.33 | H1102: 200 | I1102: =VLOOKUP($E1102,ETB!$B$66:$C$674,2,0) -> Printing, Post and Stationery
A1103: 1544 | B1103: 1413 | C1103: 45182 | D1103: SUNDRY EXPENSE | E1103: 264 | F1103: 720 | G1103: 0 | H1103: 720 | I1103: =VLOOKUP($E1103,ETB!$B$66:$C$674,2,0) -> Printing, Post and Stationery
E1105: 264 Total | F1105: =SUBTOTAL(9,F1101:F1103) -> 892.22 | G1105: =SUBTOTAL(9,G1101:G1103) -> 33.33 | H1105: =SUBTOTAL(9,H1101:H1103) -> 925.55
A1107: 279 | B1107: 35 | C1107: 44962 | D1107: AUTO TRADER LIMITED | E1107: 265 | F1107: 28.5 | G1107: 5.7 | H1107: 34.2 | I1107: =VLOOKUP($E1107,ETB!$B$66:$C$674,2,0) -> Advertising
A1108: 280 | B1108: 36 | C1108: 44963 | D1108: AUTO TRADER LIMITED | E1108: 265 | F1108: 28.5 | G1108: 5.7 | H1108: 34.2 | I1108: =VLOOKUP($E1108,ETB!$B$66:$C$674,2,0) -> Advertising
A1109: 281 | B1109: 37 | C1109: 44964 | D1109: AUTO TRADER LIMITED | E1109: 265 | F1109: 17.25 | G1109: 3.45 | H1109: 20.7 | I1109: =VLOOKUP($E1109,ETB!$B$66:$C$674,2,0) -> Advertising
A1110: 282 | B1110: 38 | C1110: 44966 | D1110: AUTO TRADER LIMITED | E1110: 265 | F1110: 17.25 | G1110: 3.45 | H1110: 20.7 | I1110: =VLOOKUP($E1110,ETB!$B$66:$C$674,2,0) -> Advertising
A1111: 283 | B1111: 39 | C1111: 44971 | D1111: AUTO TRADER LIMITED | E1111: 265 | F1111: 17.25 | G1111: 3.45 | H1111: 20.7 | I1111: =VLOOKUP($E1111,ETB!$B$66:$C$674,2,0) -> Advertising
A1112: 284 | B1112: 40 | C1112: 44941 | D1112: AUTO TRADER LIMITED | E1112: 265 | F1112: 22.5 | G1112: 4.5 | H1112: 27 | I1112: =VLOOKUP($E1112,ETB!$B$66:$C$674,2,0) -> Advertising
A1113: 285 | B1113: 41 | C1113: 44945 | D1113: AUTO TRADER LIMITED | E1113: 265 | F1113: 17.25 | G1113: 3.45 | H1113: 20.7 | I1113: =VLOOKUP($E1113,ETB!$B$66:$C$674,2,0) -> Advertising
A1114: 286 | B1114: 42 | C1114: 44945 | D1114: AUTO TRADER LIMITED | E1114: 265 | F1114: 29.95 | G1114: 5.99 | H1114: 35.94 | I1114: =VLOOKUP($E1114,ETB!$B$66:$C$674,2,0) -> Advertising
A1115: 287 | B1115: 43 | C1115: 44950 | D1115: AUTO TRADER LIMITED | E1115: 265 | F1115: 17.25 | G1115: 3.45 | H1115: 20.7 | I1115: =VLOOKUP($E1115,ETB!$B$66:$C$674,2,0) -> Advertising
A1116: 288 | B1116: 44 | C1116: 44952 | D1116: AUTO TRADER LIMITED | E1116: 265 | F1116: 22.5 | G1116: 4.5 | H1116: 27 | I1116: =VLOOKUP($E1116,ETB!$B$66:$C$674,2,0) -> Advertising
A1117: 289 | B1117: 45 | C1117: 44962 | D1117: AUTO TRADER LIMITED | E1117: 265 | F1117: 28.5 | G1117: 5.7 | H1117: 34.2 | I1117: =VLOOKUP($E1117,ETB!$B$66:$C$674,2,0) -> Advertising
A1118: 290 | B1118: 46 | C1118: 44963 | D1118: AUTO TRADER LIMITED | E1118: 265 | F1118: 22.5 | G1118: 4.5 | H1118: 27 | I1118: =VLOOKUP($E1118,ETB!$B$66:$C$674,2,0) -> Advertising
... A1449: 1192 | B1449: 1000 | C1449: 45255 | D1449: AUTO TRADER LIMITED | E1449: 265 | F1449: 37.5 | G1449: 7.5 | H1449: 45 | I1449: =VLOOKUP($E1449,ETB!$B$66:$C$674,2,0) -> Advertising
E1451: 265 Total | F1451: =SUBTOTAL(9,F1107:F1449) -> 8425.9 | G1451: =SUBTOTAL(9,G1107:G1449) -> 1685.18 | H1451: =SUBTOTAL(9,H1107:H1449) -> 10111.08
A1453: 991 | B1453: 782 | C1453: 45092 | D1453: HOTELS | E1453: 266 | F1453: 199.17 | G1453: 39.83 | H1453: 239 | I1453: =VLOOKUP($E1453,ETB!$B$66:$C$674,2,0) -> Travelling
A1454: 992 | B1454: 783 | C1454: 45093 | D1454: HOTELS | E1454: 266 | F1454: 156.19 | G1454: 31.24 | H1454: 187.43 | I1454: =VLOOKUP($E1454,ETB!$B$66:$C$674,2,0) -> Travelling
A1455: 1501 | B1455: 1314 | C1455: 45218 | D1455: SUNDRY EXPENSE | E1455: 266 | F1455: 37.93 | G1455: 0 | H1455: 37.93 | I1455: =VLOOKUP($E1455,ETB!$B$66:$C$674,2,0) -> Travelling
A1456: 1502 | B1456: 1315 | C1456: 45217 | D1456: SUNDRY EXPENSE | E1456: 266 | F1456: 31.61 | G1456: 6.32 | H1456: 37.93 | I1456: =VLOOKUP($E1456,ETB!$B$66:$C$674,2,0) -> Travelling
A1457: 1503 | B1457: 1316 | C1457: 45224 | D1457: SUNDRY EXPENSE | E1457: 266 | F1457: 17.93 | G1457: 3.58 | H1457: 21.51 | I1457: =VLOOKUP($E1457,ETB!$B$66:$C$674,2,0) -> Travelling
A1458: 253 | B1458: 9 | C1458: 44927 | D1458: THE LOWERY HOTEL | E1458: 266 | F1458: 300.92 | G1458: 0 | H1458: 300.92 | I1458: =VLOOKUP($E1458,ETB!$B$66:$C$674,2,0) -> Travelling
E1460: 266 Total | F1460: =SUBTOTAL(9,F1453:F1458) -> 743.75 | G1460: =SUBTOTAL(9,G1453:G1458) -> 80.97 | H1460: =SUBTOTAL(9,H1453:H1458) -> 824.72
A1462: 262 | B1462: 18 | C1462: 44952 | D1462: PETROL EXPENSE | E1462: 267 | F1462: 41.67 | G1462: 8.33 | H1462: 50 | I1462: =VLOOKUP($E1462,ETB!$B$66:$C$674,2,0) -> Motor Expenses
A1463: 264 | B1463: 20 | C1463: 44927 | D1463: PETROL EXPENSE | E1463: 267 | F1463: 81.85 | G1463: 16.37 | H1463: 98.22 | I1463: =VLOOKUP($E1463,ETB!$B$66:$C$674,2,0) -> Motor Expenses
A1464: 265 | B1464: 21 | C1464: 44967 | D1464: PETROL EXPENSE | E1464: 267 | F1464: 28.84 | G1464: 5.77 | H1464: 34.61 | I1464: =VLOOKUP($E1464,ETB!$B$66:$C$674,2,0) -> Motor Expenses
A1465: 270 | B1465: 26 | C1465: 44943 | D1465: PETROL EXPENSE | E1465: 267 | F1465: 120.72 | G1465: 24.14 | H1465: 144.86 | I1465: =VLOOKUP($E1465,ETB!$B$66:$C$674,2,0) -> Motor Expenses
A1466: 274 | B1466: 30 | C1466: 44966 | D1466: PETROL EXPENSE | E1466: 267 | F1466: 9.69 | G1466: 1.94 | H1466: 11.63 | I1466: =VLOOKUP($E1466,ETB!$B$66:$C$674,2,0) -> Motor Expenses
A1467: 276 | B1467: 32 | C1467: 44971 | D1467: PETROL EXPENSE | E1467: 267 | F1467: 95.63 | G1467: 19.13 | H1467: 114.76 | I1467: =VLOOKUP($E1467,ETB!$B$66:$C$674,2,0) -> Motor Expenses
A1468: 278 | B1468: 34 | C1468: 44968 | D1468: PETROL EXPENSE | E1468: 267 | F1468: 99.12 | G1468: 19.82 | H1468: 118.94 | I1468: =VLOOKUP($E1468,ETB!$B$66:$C$674,2,0) -> Motor Expenses
A1469: 644 | B1469: 429 | C1469: 45048 | D1469: PETROL EXPENSE | E1469: 267 | F1469: 41.91 | G1469: 8.38 | H1469: 50.29 | I1469: =VLOOKUP($E1469,ETB!$B$66:$C$674,2,0) -> Motor Expenses
A1470: 645 | B1470: 430 | C1470: 45037 | D1470: PETROL EXPENSE | E1470: 267 | F1470: 112.42 | G1470: 22.48 | H1470: 134.9 | I1470: =VLOOKUP($E1470,ETB!$B$66:$C$674,2,0) -> Motor Expenses
A1471: 654 | B1471: 439 | C1471: 45050 | D1471: PETROL EXPENSE | E1471: 267 | F1471: 10 | G1471: 2 | H1471: 12 | I1471: =VLOOKUP($E1471,ETB!$B$66:$C$674,2,0) -> Motor Expenses
A1472: 656 | B1472: 441 | C1472: 44986 | D1472: PETROL EXPENSE | E1472: 267 | F1472: 112.96 | G1472: 22.59 | H1472: 135.55 | I1472: =VLOOKUP($E1472,ETB!$B$66:$C$674,2,0) -> Motor Expenses
A1473: 657 | B1473: 442 | C1473: 44999 | D1473: PETROL EXPENSE | E1473: 267 | F1473: 118.37 | G1473: 23.67 | H1473: 142.04 | I1473: =VLOOKUP($E1473,ETB!$B$66:$C$674,2,0) -> Motor Expenses
...

Sheet BRS Barclays Bank Ac -30470120
A1: Client Name : | C1: =Info!C3 -> Forest Car Company Ltd | E1: Prepared by : | G1: =+Info!C8 -> Aratee
A2: File No : | C2: 7033 | D2: =+E8&"R" -> 692R | E2: Date : | G2: =+Info!C9 -> 45343
A4: A/C Holder Name: | C4: =C1 -> Forest Car Company Ltd | E4: Reviewed by : | G4: =+Info!C11 -> Mitesh
A5: Bank Name : | C5: Barclays Bank | E5: Date : | G5: =+Info!C12 -> 45352
A6: Account No. : | C6: 30470120
A7: =C5& " A/c # "&C6 -> Barclays Bank A/c # 30470120
A8: Year End : | E8: 692
A9: Start : | B9: =Info!C5 -> 44783
A10: End : | B10: =Info!C6 -> 45260
B13: BANK RECONCILIATION | E13: =B10 -> 45260
D15: Page No. | E15: Date | F15: Amount | G15: Ref
B16: Closing Balance as per Bank Statement No | E16: =B10 -> 45260 | F16: ='C3-1 - Bank 1'!G18 -> 44032.43 | G16: H / 3 / 2
B18: DETAILS OF OUTSTANDING CHEQUES | F18: =E26 -> 0
B20: Date | C20: Particulars | D20: Cheque No. | E20: Amount (£) | G20: IRIS CODE
C26: TOTAL | E26: =SUBTOTAL(9,E21:E24) -> 0
B28: Closing Balance as per Accounts | E28: =E13 -> 45260 | F28: =F16-F18 -> 44032.43
B35: Bank Book Details
B37: Opening Balance as per Accounts | E37: =B9 -> 44783 | F37: ='Barclays Bank Ac -30470120'!H13 -> 0 | G37: H / 3 / 3
B38: ADJUSTMENTS IF ANY
A40: ADD: | B40: RECEIPTS | F40: ='Barclays Bank Ac -30470120'!G1708 -> 598113.09
A42: LESS: | B42: PAYMENTS | F42: ='Barclays Bank Ac -30470120'!F1708 -> 554080.66
B45: CLOSING BALANCE AS PER ACCOUNTS | E45: =B10 -> 45260 | F45: =F37+F40-F42 -> 44032.43 | G45: H / 3 / 2
D47: Difference | F47: =F28-F45 -> 1.1641532e-10

Sheet Barclays Bank Ac -30470120
A1: Client Name : | C1: =Info!C3 -> Forest Car Company Ltd | E1: Prepared by: | G1: =+Info!C8 -> Aratee
A2: File No. : | C2: =+'BRS Barclays Bank Ac -30470120'!C2 -> 7033 | D2: =+E8 -> 692 | E2: Date: | G2: =+Info!C9 -> 45343
A4: A/C Holder Name: | C4: =+'BRS Barclays Bank Ac -30470120'!C4 -> Forest Car Company Ltd | E4: Reviewed by: | G4: =+Info!C11 -> Mitesh
A5: Bank Name : | C5: =+'BRS Barclays Bank Ac -30470120'!C5 -> Barclays Bank | E5: Date: | G5: =+Info!C12 -> 45352
A6: Account No. : | C6: =+'BRS Barclays Bank Ac -30470120'!C6 -> 30470120
A7: =C5& " A/c # "&C6 -> Barclays Bank A/c # 30470120
A8: Period Start : | C8: =Info!C5 -> 44783 | E8: =+'BRS Barclays Bank Ac -30470120'!E8 -> 692
A9: Period End : | C9: =Info!C6 -> 45260
A11: Sr No | B11: Date | D11: Particulars | E11: IRIS | F11: Payments | G11: Receipts | H11: Balance
B13: =+C8 -> 44783 | D13: OPENING BALANCE | H13: 0
A14: 1 | B14: 44882 | C14: Credit | D14: Account Fee Refund Gadbrook Park | E14: 378 | G14: 8 | H14: =+H13+G14-F14 -> 8
A15: 2 | B15: 44890 | C15: Funds Transfer | D15: 203698 93272893 Dl Ft | E15: 727 | G15: 7000 | H15: =+H14+G15-F15 -> 7008
A16: 3 | B16: 44894 | C16: Debit | D16: Ebay O*11-09399-09 On 28 Nov Bdc | E16: 54 | F16: 10.95 | H16: =+H15+G16-F16 -> 6997.05
A17: 4 | B17: 44900 | C17: Counter Credit | D17: M Stacey Cream Mini Deposit Bg | E17: 586.1 | G17: 250 | H17: =+H16+G17-F17 -> 7247.05
A18: 5 | B18: 44900 | C18: Counter Credit | D18: Marquel Edwards Car Vauxhall Adam Bgc Lm63RTu | E18: 586 | G18: 1400 | H18: =+H17+G18-F18 -> 8647.05
A19: 6 | B19: 44900 | C19: Counter Credit | D19: Marquel Edwards Lm63Rtu Bgc | E19: 586 | G19: 2500 | H19: =+H18+G19-F19 -> 11147.05
A20: 7 | B20: 44901 | C20: Counter Credit | D20: Misha Haycock Mt10Fnf Bgc | E20: 586 | G20: 1989 | H20: =+H19+G20-F20 -> 13136.05
A21: 8 | B21: 44901 | C21: Counter Credit | D21: Rutter Paul Chloe Car Bgc | E21: 586 | G21: 1500 | H21: =+H20+G21-F21 -> 14636.05
A22: 9 | B22: 44901 | C22: Funds Transfer | D22: Custom Cars Ltd Ag08Gzm Ft | E22: 737 | F22: 148 | H22: =+H21+G22-F22 -> 14488.05
A23: 10 | B23: 44901 | C23: Funds Transfer | D23: Redcorn Ltd Car Ft | E23: 737 | F23: 1000 | H23: =+H22+G23-F23 -> 13488.05
A24: 11 | B24: 44901 | C24: Funds Transfer | D24: Redcorn Ltd Car Ft | E24: 737 | F24: 800 | H24: =+H23+G24-F24 -> 12688.05
A25: 12 | B25: 44902 | C25: Counter Credit | D25: Charlie Loughbridg Mk58 Pke Bgc | E25: 586 | G25: 3700 | H25: =+H24+G25-F25 -> 16388.05
A26: 13 | B26: 44902 | C26: Funds Transfer | D26: Urban Auto Invoice December Ft | E26: 737.2 | F26: 3000 | H26: =+H25+G26-F26 -> 13388.05
A27: 14 | B27: 44904 | C27: Funds Transfer | D27: Custom Cars Ltd Ibiza Ft | E27: 737 | F27: 156 | H27: =+H26+G27-F27 -> 13232.05
A28: 15 | B28: 44904 | C28: Debit | D28: Equita Ltd On 08 Dec Bdc | E28: 280 | F28: 189 | H28: =+H27+G28-F28 -> 13043.05
A29: 16 | B29: 44908 | C29: Counter Credit | D29: Barnes Helen Jimmy Bgc | E29: 586 | G29: 250 | H29: =+H28+G29-F29 -> 13293.05
A30: 17 | B30: 44908 | C30: Debit | D30: The Lowry Hotel On 12 Dec Bdc | E30: 737 | F30: 300 | H30: =+H29+G30-F30 -> 12993.05
A31: 18 | B31: 44908 | C31: Debit | D31: Zettle_*Ali Cab On 12 Dec Bdc | E31: 266 | F31: 41.2 | H31: =+H30+G31-F31 -> 12951.85
A32: 19 | B32: 44909 | C32: Counter Credit | D32: Barnes Helen Jimmy Bgc | E32: 586 | G32: 3859 | H32: =+H31+G32-F32 -> 16810.85
A33: 20 | B33: 44909 | C33: Debit | D33: Paypal *Trainline On 12 Dec Bdc | E33: 266 | F33: 139.19 | H33: =+H32+G33-F33 -> 16671.66
A34: 21 | B34: 44911 | C34: Debit | D34: Auto Trader On 15 Dec Bdc | E34: 737 | F34: 20.7 | H34: =+H33+G34-F34 -> 16650.96
A35: 22 | B35: 44911 | C35: Debit | D35: Auto Trader On 15 Dec Bdc | E35: 737 | F35: 20.7 | H35: =+H34+G35-F35 -> 16630.26
A36: 23 | B36: 44911 | C36: Debit | D36: Auto Trader On 15 Dec Bdc | E36: 737 | F36: 34.2 | H36: =+H35+G36-F36 -> 16596.06
A37: 24 | B37: 44911 | C37: Debit | D37: Auto Trader On 15 Dec Bdc | E37: 737 | F37: 35.94 | H37: =+H36+G37-F37 -> 16560.12
A38: 25 | B38: 44911 | C38: Funds Transfer | D38: Crown Cars Invoice Ft | E38: 737 | F38: 280 | H38: =+H37+G38-F38 -> 16280.12
A39: 26 | B39: 44914 | C39: Counter Credit | D39: Jasper Ka Delivery Norfolk Bgc | E39: 668 | G39: 240 | H39: =+H38+G39-F39 -> 16520.12
A40: 27 | B40: 44914 | C40: Funds Transfer | D40: Henningsen Trading Invoice Ft | E40: 27 | F40: 2935 | H40: =+H39+G40-F40 -> 13585.12
A41: 28 | B41: 44914 | C41: Debit | D41: Land Registry Ecom On 16 Dec Bdc | E41: 290 | F41: 6 | H41: =+H40+G41-F41 -> 13579.12
A42: 29 | B42: 44914 | C42: Funds Transfer | D42: Redcorn Ltd Car Ft | E42: 737 | F42: 700 | H42: =+H41+G42-F42 -> 12879.12
A43: 30 | B43: 44915 | C43: Counter Credit | D43: Wisdom James Car Bgc Cx62Ysh | E43: 586 | G43: 550 | H43: =+H42+G43-F43 -> 13429.12
A44: 31 | B44: 44916 | C44: Credit | D44: Total Waste Manage On 20 Dec Bdc | E44: 586 | G44: 300 | H44: =+H43+G44-F44 -> 13729.12
A45: 32 | B45: 44916 | C45: Credit | D45: Total Waste Manage On 20 Dec Bdc | E45: 586 | G45: 400 | H45: =+H44+G45-F45 -> 14129.12
A46: 33 | B46: 44916 | C46: Debit | D46: Ebay O*17-09490-43 On 20 Dec Bdc | E46: 54 | F46: 1.5 | H46: =+H45+G46-F46 -> 14127.62
A47: 34 | B47: 44917 | C47: Debit | D47: Ebay O*17-09493-91 On 21 Dec Bdc | E47: 54 | F47: 49.99 | H47: =+H46+G47-F47 -> 14077.63
A48: 35 | B48: 44923 | C48: Debit | D48: Paypal *Louiseholt On 22 Dec Bdc | E48: 280 | F48: 25 | H48: =+H47+G48-F48 -> 14052.63
A49: 36 | B49: 44923 | C49: Funds Transfer | D49: Vgates Ltd Gates So-000260 Ft | E49: 737 | F49: 750 | H49: =+H48+G49-F49 -> 13302.63
A50: 37 | B50: 44925 | C50: Debit | D50: Bassett Filling St On 29 Dec Bdc | E50: 267 | F50: 122.39 | H50: =+H49+G50-F50 -> 13180.24
A51: 38 | B51: 44925 | C51: Contactless Card Purchase | D51: Toby Carvery On 29 Dec Clp | E51: 261 | F51: 40 | H51: =+H50+G51-F51 -> 13140.24
A52: 39 | B52: 44929 | C52: Funds Transfer | D52: 203698 93272893 Mobile-Channel Ft | E52: 737.2 | F52: 3000 | H52: =+H51+G52-F52 -> 10140.24
A53: 40 | B53: 44929 | C53: Debit | D53: Alecs Restaurant On 30 Dec Bdc | E53: 737 | F53: 230 | H53: =+H52+G53-F53 -> 9910.24
A54: 41 | B54: 44930 | C54: Counter Credit | D54: A Smith Pj07Lbf Bgc | E54: 586 | G54: 250 | H54: =+H53+G54-F54 -> 10160.24
A55: 42 | B55: 44930 | C55: Debit | D55: Auto Trader On 03 Jan Bdc | E55: 737 | F55: 20.7 | H55: =+H54+G55-F55 -> 10139.54
A56: 43 | B56: 44930 | C56: Debit | D56: Auto Trader On 03 Jan Bdc | E56: 737 | F56: 20.7 | H56: =+H55+G56-F56 -> 10118.84
A57: 44 | B57: 44930 | C57: Debit | D57: Auto Trader On 03 Jan Bdc | E57: 737 | F57: 20.7 | H57: =+H56+G57-F57 -> 10098.14
A58: 45 | B58: 44930 | C58: Debit | D58: Auto Trader On 03 Jan Bdc | E58: 737 | F58: 20.7 | H58: =+H57+G58-F58 -> 10077.44
A59: 46 | B59: 44930 | C59: Debit | D59: Auto Trader On 03 Jan Bdc | E59: 737 | F59: 27 | H59: =+H58+G59-F59 -> 10050.44
A60: 47 | B60: 44930 | C60: Debit | D60: Auto Trader On 03 Jan Bdc | E60: 737 | F60: 27 | H60: =+H59+G60-F60 -> 10023.44
A61: 48 | B61: 44930 | C61: Debit | D61: Auto Trader On 03 Jan Bdc | E61: 737 | F61: 34.2 | H61: =+H60+G61-F61 -> 9989.24
A62: 49 | B62: 44930 | C62: Debit | D62: Ebay O*10-09537-16 On 03 Jan Bdc | E62: 54 | F62: 20 | H62: =+H61+G62-F62 -> 9969.24
A63: 50 | B63: 44930 | C63: Debit | D63: Ebay O*10-09537-16 On 03 Jan Bdc | E63: 54 | F63: 101.29 | H63: =+H62+G63-F63 -> 9867.95
A64: 51 | B64: 44930 | C64: Funds Transfer | D64: Mallard Leasing Li Bv13Rvj-358717 Ft | E64: 737 | F64: 450 | H64: =+H63+G64-F64 -> 9417.95
A65: 52 | B65: 44930 | C65: Funds Transfer | D65: Mallard Leasing Li Kr58Vjc-359500 Ft | E65: 737 | F65: 370 | H65: =+H64+G65-F65 -> 9047.95
A66: 53 | B66: 44930 | C66: Funds Transfer | D66: Urban Auto Invoice December Ft | E66: 737 | F66: 5162.37 | H66: =+H65+G66-F66 -> 3885.58
A67: 54 | B67: 44931 | C67: Counter Credit | D67: A Smith Pj07Lbf Bgc | E67: 586 | G67: 1739 | H67: =+H66+G67-F67 -> 5624.58
A68: 55 | B68: 44931 | C68: Counter Credit | D68: Terry R Caa Wf56Udo Bgc | E68: 586 | G68: 2489 | H68: =+H67+G68-F68 -> 8113.58
A69: 56 | B69: 44932 | C69: Counter Credit | D69: Koji-Paton N Seat Leon Bgc KW59JYD | E69: 586 | G69: 250 | H69: =+H68+G69-F69 -> 8363.58
A70: 57 | B70: 44932 | C70: Debit | D70: Auto Trader On 05 Jan Bdc | E70: 737 | F70: 20.7 | H70: =+H69+G70-F70 -> 8342.88
A71: 58 | B71: 44932 | C71: Debit | D71: Auto Trader On 05 Jan Bdc | E71: 737 | F71: 27 | H71: =+H70+G71-F71 -> 8315.88
A72: 59 | B72: 44932 | C72: Debit | D72: Auto Trader On 05 Jan Bdc | E72: 737 | F72: 34.2 | H72: =+H71+G72-F72 -> 8281.68
A73: 60 | B73: 44932 | C73: Debit | D73: Auto Trader On 05 Jan Bdc | E73: 737 | F73: 35.94 | H73: =+H72+G73-F73 -> 8245.74
A74: 61 | B74: 44935 | C74: Credit | D74: Total Waste Manage On 06 Jan Bdc | E74: 92 | G74: 112 | H74: =+H73+G74-F74 -> 8357.74
A75: 62 | B75: 44935 | C75: Counter Credit | D75: J Valentine Kn58Kya Bgc | E75: 586 | G75: 1300 | H75: =+H74+G75-F75 -> 9657.74
A76: 63 | B76: 44935 | C76: Credit Payment | D76: Loyalty Reward 17 Nov - 12 Dec | E76: 92 | G76: 0.23 | H76: =+H75+G76-F76 -> 9657.97
A77: 64 | B77: 44935 | C77: Debit | D77: Auto Trader On 09 Jan Bdc | E77: 737 | F77: 27 | H77: =+H76+G77-F77 -> 9630.97
A78: 65 | B78: 44935 | C78: Debit | D78: Auto Trader On 09 Jan Bdc | E78: 737 | F78: 34.2 | H78: =+H77+G78-F78 -> 9596.77
A79: 66 | B79: 44935 | C79: Credit Payment | D79: Charges Commission For Period | E79: 737 | F79: 12.55 | H79: =+H78+G79-F79 -> 9584.22
A80: 67 | B80: 44935 | C80: Funds Transfer | D80: Mallard Leasing Li Fy11Hcx 358960 Ft | E80: 737 | F80: 500 | H80: =+H79+G80-F80 -> 9084.22
A81: 68 | B81: 44936 | C81: Debit | D81: Auto Trader On 09 Jan Bdc | E81: 737 | F81: 27 | H81: =+H80+G81-F81 -> 9057.22
A82: 69 | B82: 44936 | C82: Debit | D82: Auto Trader On 09 Jan Bdc | E82: 737 | F82: 27 | H82: =+H81+G82-F82 -> 9030.22
A83: 70 | B83: 44936 | C83: Debit | D83: Ebay O*04-09565-33 On 09 Jan Bdc | E83: 54 | F83: 25.19 | H83: =+H82+G83-F83 -> 9005.03
A84: 71 | B84: 44936 | C84: Debit | D84: Ebay O*05-09565-42 On 09 Jan Bdc | E84: 235 | F84: 33 | H84: =+H83+G84-F84 -> 8972.03
A85: 72 | B85: 44936 | C85: Debit | D85: Ebay O*16-09560-57 On 09 Jan Bdc | E85: 54 | F85: 21.12 | H85: =+H84+G85-F85 -> 8950.91
A86: 73 | B86: 44936 | C86: Debit | D86: Ebay O*16-09560-57 On 09 Jan Bdc | E86: 54 | F86: 24 | H86: =+H85+G86-F86 -> 8926.91
A87: 74 | B87: 44936 | C87: Debit | D87: Ebay O*16-09560-57 On 09 Jan Bdc | E87: 54 | F87: 28 | H87: =+H86+G87-F87 -> 8898.91
A88: 75 | B88: 44936 | C88: Debit | D88: Ebay O*18-09560-20 On 09 Jan Bdc | E88: 54 | F88: 70 | H88: =+H87+G88-F88 -> 8828.91
... A91: 78 | B91: 44936 | C91: Funds Transfer | D91: Redcorn Ltd Car Ft | E91: 737 | F91: 800 | H91: =+H90+G91-F91 -> 6528.91
A92: 79 | B92: 44937 | C92: Counter Credit | D92: D Hayes En63 Rzu- Dawn Bgc | E92: 586 | G92: 150 | H92: =+H91+G92-F92 -> 6678.91
A93: 80 | B93: 44937 | C93: Counter Credit | D93: Rowley Ma Ka Bgc CK59KKO | E93: 586 | G93: 250 | H93: =+H92+G93-F93 -> 6928.91
A94: 81 | B94: 44937 | C94: Credit | D94: Ebay O*05-09565-42 On 10 Jan Bdc | E94: 235 | G94: 33 | H94: =+H93+G94-F94 -> 6961.91
A95: 82 | B95: 44937 | C95: Debit | D95: Ebay O*01-09568-85 On 10 Jan Bdc | E95: 54 | F95: 35 | H95: =+H94+G95-F95 -> 6926.91
A96: 83 | B96: 44938 | C96: Debit | D96: Auto Trader On 11 Jan Bdc | E96: 737 | F96: 20.7 | H96: =+H95+G96-F96 -> 6906.21
A97: 84 | B97: 44938 | C97: Debit | D97: Auto Trader On 11 Jan Bdc | E97: 737 | F97: 34.2 | H97: =+H96+G97-F97 -> 6872.01
A98: 85 | B98: 44938 | C98: Debit | D98: Tfl Business Bops On 10 Jan Bdc | E98: 267 | F98: 12.5 | H98: =+H97+G98-F98 -> 6859.51
A99: 86 | B99: 44939 | C99: Counter Credit | D99: M Dumitru Mariana Toyota Ayg Bg LT60GNU | E99: 586 | G99: 489 | H99: =+H98+G99-F99 -> 7348.51
A100: 87 | B100: 44939 | C100: Credit | D100: Total Waste Manage On 12 Jan Bdc | E100: 586 | G100: 400 | H100: =+H99+G100-F100 -> 7748.51
A101: 88 | B101: 44939 | C101: Debit | D101: Auto Trader On 13 Jan Bdc | E101: 737 | F101: 34.2 | H101: =+H100+G101-F101 -> 7714.31
A102: 89 | B102: 44942 | C102: Counter Credit | D102: D Hayes En63 Rzu- Dawn Bgc | E102: 586 | G102: 4800 | H102: =+H101+G102-F102 -> 12514.31
A103: 90 | B103: 44942 | C103: Debit | D103: Auto Trader On 14 Jan Bdc | E103: 737 | F103: 27 | H103: =+H102+G103-F103 -> 12487.31
A104: 91 | B104: 44942 | C104: Debit | D104: Auto Trader On 14 Jan Bdc | E104: 737 | F104: 42.6 | H104: =+H103+G104-F104 -> 12444.71
A105: 92 | B105: 44942 | C105: Debit | D105: Auto Trader On 15 Jan Bdc | E105: 737 | F105: 27 | H105: =+H104+G105-F105 -> 12417.71
...

Sheet Index
B2: Client : | C2: =Info!C3 -> Forest Car Company Ltd | G2: Prepared by : | H2: =Info!C8 -> Aratee | I2: Date : | J2: =Info!C9 -> 45343
B3: Year end : | C3: =Info!C6 -> 45260 | G3: Reviewed by : | H3: =Info!C11 -> Mitesh | I3: Date : | J3: =Info!C12 -> 45352
B5: Index of working papers
B8: Sr. No | C8: Particulars | G8: Hyperlink
B10: 1 | C10: =+Notes!B5 -> Notes and observations | E10: a | G10: =+C10 -> Notes and observations
B12: =+B10+1 -> 2 | C12: =+'Job plan'!B5 -> Job plan | E12: a | G12: =+C12 -> Job plan | K12: r
B14: =+B12+1 -> 3 | C14: =+Queries!B5 -> Queries | E14: a | G14: =+C14 -> Queries
B16: =+B14+1 -> 4 | C16: =+'Profit & Loss'!B5 -> Profit and loss account | E16: a | G16: =+C16 -> Profit and loss account
B18: =+B16+1 -> 5 | C18: =+'Balance Sheet'!B5 -> Balance Sheet | E18: a | G18: =+C18 -> Balance Sheet
B20: =+B18+1 -> 6 | C20: =+ETB!B5 -> Extended Trial Balance (ETB) | E20: a | G20: =+C20 -> Extended Trial Balance (ETB)
B22: =+B20+1 -> 7 | C22: =+Journal!B5 -> Journals | E22: a | G22: =+C22 -> Journals
B24: =+B22+1 -> 8 | C24: =+TB!B5 -> Trial Balance | E24: a | G24: =+C24 -> Trial Balance
B26: =+B24+1 -> 9 | C26: =+'F - Fixed Assets'!B5 -> Lead Schedule - Fixed Assets | E26: r | G26: =+C26 -> Lead Schedule - Fixed Assets
B28: =+B26+1 -> 10 | C28: =+'F1 - Intangible FA'!B5 -> Fixed Assets - Intangible | E28: r | G28: =+C28 -> Fixed Assets - Intangible
B30: =+B28+1 -> 11 | C30: =+'F2 - Tangible FA'!B5 -> Fixed Assets - Tangible | E30: r | G30: =+C30 -> Fixed Assets - Tangible
B32: =+B30+1 -> 12 | C32: =+'F4 - FAR'!B5 -> Fixed asset register | E32: r | G32: =+C32 -> Fixed asset register
B34: =+B32+1 -> 13 | C34: =+'F5 - Investments'!B5 -> Investments | E34: a | G34: =+C34 -> Investments
B36: =+B34+1 -> 14 | C36: =+'C1 - Stock'!B5 -> Lead Schedule - Stock | E36: r | G36: =+C36 -> Lead Schedule - Stock
B38: =+B36+1 -> 15 | C38: =+'C2 - Debtors'!B5 -> Lead Schedule - Debtors | E38: a | G38: =+C38 -> Lead Schedule - Debtors
B40: =+B38+1 -> 16 | C40: =+'C2-1 - Trade debtors'!B5 -> Trade debtors | E40: a | G40: =+C40 -> Trade debtors
B42: =+B40+1 -> 17 | C42: =+'C2-2-1 - Other Debtors'!B5 -> Other Debtors | E42: a | G42: =+C42 -> Other Debtors
B44: =+B42+1 -> 18 | C44: =+'C2-3 - Prepayments'!B5 -> Prepayments | E44: a | G44: =+C44 -> Prepayments
B46: =+B44+1 -> 19 | C46: =+'C2-4 - Accrued Income'!B5 -> Other Debtors | E46: a | G46: =+C46 -> Other Debtors
B48: =+B46+1 -> 20 | C48: =+'C2-5 - Other debtors-Inter co.'!B5 -> Other Debtors - Inter company | E48: a | G48: =+C48 -> Other Debtors - Inter company
B50: =+B48+1 -> 21 | C50: =+'C2-6 - CIS'!B5 -> Other Debtors - CIS | E50: a | G50: =+C50 -> Other Debtors - CIS
B52: =+B50+1 -> 22 | C52: =+'C2-7 - Other debtors (3)'!B5 -> Other Debtors - 3 | E52: a | G52: =+C52 -> Other Debtors - 3
B54: =+B52+1 -> 23 | C54: =+'C3 - Bank & Cash'!B5 -> Lead Schedule - Bank and Cash in hand | E54: a | G54: =+C54 -> Lead Schedule - Bank and Cash in hand
B56: =+B54+1 -> 24 | C56: =+'C3-1 - Bank 1'!B5 -> Bank account - 1 | E56: a | G56: =+C56 -> Bank account - 1
B58: =+B56+1 -> 25 | C58: =+'C3-4 - Bank-2'!B5 -> Bank account - 2 | E58: a | G58: =+C58 -> Bank account - 2
B60: =+B58+1 -> 26 | C60: =+'C5 - Cash'!B5 -> Cash | E60: a | G60: =+C60 -> Cash
B62: =+B60+1 -> 27 | C62: =+'C4 - Creditors'!B5 -> Lead Schedule - Creditors < 1 Year | E62: a | G62: =+C62 -> Lead Schedule - Creditors < 1 Year
B64: =+B62+1 -> 28 | C64: =+'C4-1 - Trade creditors'!B5 -> Trade creditors | E64: a | G64: =+C64 -> Trade creditors
B66: =+B64+1 -> 29 | C66: =+'C2-2 - Other debtors'!B5 -> Other creditors | E66: a | G66: =+C66 -> Other creditors
B68: =+B66+1 -> 30 | C68: =+'C4-3 - CT'!B5 -> Corporation tax | E68: a | G68: =+C68 -> Corporation tax
B70: =+B68+1 -> 31 | C70: =+'C4-2 - VAT'!B5 -> VAT Liability | E70: a | G70: =+C70 -> VAT Liability
B72: =+B70+1 -> 32 | C72: =+'VAT Rec'!B5 -> VAT Reconciliation | E72: a | G72: =+C72 -> VAT Reconciliation
B74: =+B72+1 -> 33 | C74: =+'C4-4 - PAYE-NI'!B5 -> PAYE/NI Liability | E74: a | G74: =+C74 -> PAYE/NI Liability
B76: =+B74+1 -> 34 | C76: =+'C4-10 - Net wages'!B5 -> Net wages | E76: a | G76: =+C76 -> Net wages
B78: =+B76+1 -> 35 | C78: =+'C4-5 - Other creditors'!B5 -> Other creditors | E78: a | G78: =+C78 -> Other creditors
B80: =+B78+1 -> 36 | C80: =+'C4-6 - Accruals'!B5 -> Accruals | E80: a | G80: =+C80 -> Accruals
B82: =+B80+1 -> 37 | C82: =+'C4-7 - DCA'!B5 -> Director's current account | E82: a | G82: =+C82 -> Director's current account
B84: =+B82+1 -> 38 | C84: =+'C4-8 - Loan < 1'!B5 -> Loan Account | E84: a | G84: =+C84 -> Loan Account
B86: =+B84+1 -> 39 | C86: =+'C4-9 - HP < 1'!B5 -> Hire purchase payable < 1 Year | E86: a | G86: =+C86 -> Hire purchase payable < 1 Year
B88: =+B86+1 -> 40 | C88: =+'C4-10 - Pension'!B5 -> Pension | E88: a | G88: =+C88 -> Pension
B90: =+B88+1 -> 41 | C90: =+'C4-11 - Other Creditors (3)'!B5 -> Other Creditors - 3 | E90: a | G90: =+C90 -> Other Creditors - 3
B92: =+B90+1 -> 42 | C92: =+'C4-12 - Other Crediotrs (4)'!B5 -> Other Creditors - 4 | E92: a | G92: =+C92 -> Other Creditors - 4
B94: =+B92+1 -> 43 | C94: =+'L - Long Term Loans'!B5 -> Lead Schedule - Creditors > 1 Year | E94: r | G94: =+C94 -> Lead Schedule - Creditors > 1 Year
B96: =+B94+1 -> 44 | C96: =+'L1 - Loan > 1'!B5 -> Loans payable > 1 Year | E96: a | G96: =+C96 -> Loans payable > 1 Year
B98: =+B96+1 -> 45 | C98: =+'L2 - HP > 1'!B5 -> Hire purchase payable > 1 Year | E98: a | G98: =+C98 -> Hire purchase payable > 1 Year
B100: =+B98+1 -> 46 | C100: =+'D - Deferred tax'!B5 -> Lead Schedule - Provision for Liabilities | E100: a | G100: =+C100 -> Lead Schedule - Provision for Liabilities
B102: =+B100+1 -> 47 | C102: =+'E - Share capital'!B5 -> Lead Schedule - Share capital | E102: a | G102: =+C102 -> Lead Schedule - Share capital
B104: =+B102+1 -> 48 | C104: =+'P - Reserves'!B5 -> Lead Schedule - Profit and loss account | E104: a | G104: =+C104 -> Lead Schedule - Profit and loss account

Sheet Barclays Bank Ac -30470120 (C)
A1: Client Name : | C1: =Info!C3 -> Forest Car Company Ltd | E1: Prepared by: | G1: =+Info!C8 -> Aratee
A2: File No. : | C2: =+'BRS Barclays Bank Ac -30470120'!C2 -> 7033 | D2: =+E8 -> 692 | E2: Date: | G2: =+Info!C9 -> 45343
A4: A/C Holder Name: | C4: =+'BRS Barclays Bank Ac -30470120'!C4 -> Forest Car Company Ltd | E4: Reviewed by: | G4: =+Info!C11 -> Mitesh
A5: Bank Name : | C5: =+'BRS Barclays Bank Ac -30470120'!C5 -> Barclays Bank | E5: Date: | G5: =+Info!C12 -> 45352
A6: Account No. : | C6: =+'BRS Barclays Bank Ac -30470120'!C6 -> 30470120
A7: =C5& " A/c # "&C6 -> Barclays Bank A/c # 30470120
A8: Period Start : | C8: =Info!C5 -> 44783 | E8: =+'BRS Barclays Bank Ac -30470120'!E8 -> 692
A9: Period End : | C9: =Info!C6 -> 45260
A11: Sr No | B11: Date | D11: Particulars | E11: IRIS | F11: Payments | G11: Receipts
A13: 421 | B13: 45041 | C13: Funds Transfer | D13: A Kalafatis Warranty 107 Red09 Ft | E13: 1 | F13: 134 | H13: =VLOOKUP($E13,ETB!$B$66:$C$674,2,0) -> Sales
A14: 428 | B14: 44949 | C14: Funds Transfer | D14: A Smith Partial Refund Min Ft | E14: 1 | F14: 160 | H14: =VLOOKUP($E14,ETB!$B$66:$C$674,2,0) -> Sales
E16: 1 Total | F16: =SUBTOTAL(9,F13:F14) -> 0 | G16: =SUBTOTAL(9,G13:G14) -> 0
A18: 1247 | B18: 45091 | C18: Funds Transfer | D18: Essex Trader Uk Lt Green C3 Ft | E18: 27 | F18: 1100 | H18: =VLOOKUP($E18,ETB!$B$66:$C$674,2,0) -> Purchases
A19: 1266 | B19: 44914 | C19: Funds Transfer | D19: Henningsen Trading Invoice Ft | E19: 27 | F19: 2935 | H19: =VLOOKUP($E19,ETB!$B$66:$C$674,2,0) -> Purchases
A20: 1439 | B20: 45187 | C20: Funds Transfer | D20: Redcorn Ltd Car B Ft | E20: 27 | F20: 3180 | H20: =VLOOKUP($E20,ETB!$B$66:$C$674,2,0) -> Purchases
A21: 1460 | B21: 45131 | C21: Funds Transfer | D21: Redcorn Ltd Car Ft | E21: 27 | F21: 700 | H21: =VLOOKUP($E21,ETB!$B$66:$C$674,2,0) -> Purchases
A22: 1473 | B22: 45111 | C22: Funds Transfer | D22: Redcorn Ltd Car J Ft | E22: 27 | F22: 2800 | H22: =VLOOKUP($E22,ETB!$B$66:$C$674,2,0) -> Purchases
A23: 1478 | B23: 45250 | C23: Funds Transfer | D23: Redcorn Ltd Car J Ft | E23: 27 | F23: 5074 | H23: =VLOOKUP($E23,ETB!$B$66:$C$674,2,0) -> Purchases
A24: 1479 | B24: 45254 | C24: Funds Transfer | D24: Redcorn Ltd Car J Ft | E24: 27 | F24: 3308 | H24: =VLOOKUP($E24,ETB!$B$66:$C$674,2,0) -> Purchases
A25: 1496 | B25: 45208 | C25: Funds Transfer | D25: Redcorn Ltd Car P Ft | E25: 27 | F25: 2680 | H25: =VLOOKUP($E25,ETB!$B$66:$C$674,2,0) -> Purchases
A26: 1497 | B26: 45113 | C26: Funds Transfer | D26: Redcorn Ltd Car R Ft | E26: 27 | F26: 1800 | H26: =VLOOKUP($E26,ETB!$B$66:$C$674,2,0) -> Purchases
A27: 1509 | B27: 45258 | C27: Funds Transfer | D27: Redcorn Ltd Car U Ft | E27: 27 | F27: 660 | H27: =VLOOKUP($E27,ETB!$B$66:$C$674,2,0) -> Purchases
A28: 1511 | B28: 45233 | C28: Funds Transfer | D28: Redcorn Ltd Car W Ft | E28: 27 | F28: 600 | H28: =VLOOKUP($E28,ETB!$B$66:$C$674,2,0) -> Purchases
A29: 1519 | B29: 45251 | C29: Funds Transfer | D29: Redcorn Ltd Car Y Ft | E29: 27 | F29: 3080 | H29: =VLOOKUP($E29,ETB!$B$66:$C$674,2,0) -> Purchases
A30: 1520 | B30: 45244 | C30: Funds Transfer | D30: Redcorn Ltd Car Z Ft | E30: 27 | F30: 2410 | H30: =VLOOKUP($E30,ETB!$B$66:$C$674,2,0) -> Purchases
E32: 27 Total | F32: =SUBTOTAL(9,F18:F30) -> 0 | G32: =SUBTOTAL(9,G18:G30) -> 0
A34: 422 | B34: 45194 | C34: Funds Transfer | D34: A Nazir 0012 Ft | E34: 54 | F34: 140 | H34: =VLOOKUP($E34,ETB!$B$66:$C$674,2,0) -> Direct cost
A35: 423 | B35: 45222 | C35: Funds Transfer | D35: A Nazir Ecu Fix Ft | E35: 54 | F35: 120 | H35: =VLOOKUP($E35,ETB!$B$66:$C$674,2,0) -> Direct cost
A36: 424 | B36: 45257 | C36: Funds Transfer | D36: A Nazir Electronics Ft | E36: 54 | F36: 390 | H36: =VLOOKUP($E36,ETB!$B$66:$C$674,2,0) -> Direct cost
A37: 427 | B37: 45222 | C37: Funds Transfer | D37: A Pilgrim C3 58 Scrap Ft | E37: 54 | F37: 200 | H37: =VLOOKUP($E37,ETB!$B$66:$C$674,2,0) -> Direct cost
A38: 446 | B38: 45002 | C38: Debit | D38: Allen Briggs Motor On 16 Mar Bdc | E38: 54 | F38: 133.87 | H38: =VLOOKUP($E38,ETB!$B$66:$C$674,2,0) -> Direct cost
A39: 447 | B39: 45082 | C39: Funds Transfer | D39: Altaf Nazir Map Ft | E39: 54 | F39: 400 | H39: =VLOOKUP($E39,ETB!$B$66:$C$674,2,0) -> Direct cost
A40: 448 | B40: 45184 | C40: Funds Transfer | D40: Altaf Nazir Map Ft | E40: 54 | F40: 240 | H40: =VLOOKUP($E40,ETB!$B$66:$C$674,2,0) -> Direct cost
A41: 449 | B41: 45252 | C41: Funds Transfer | D41: Altaf Nazir Map Ft | E41: 54 | F41: 280 | H41: =VLOOKUP($E41,ETB!$B$66:$C$674,2,0) -> Direct cost
A42: 457 | B42: 45051 | C42: Debit | D42: Amazon.Co.Uk*Ew8Ez On 04 May Bdc | E42: 54 | F42: 49 | H42: =VLOOKUP($E42,ETB!$B$66:$C$674,2,0) -> Direct cost
A43: 468 | B43: 45049 | C43: Debit | D43: Amznmktplace On 02 May Bdc | E43: 54 | F43: 27.95 | H43: =VLOOKUP($E43,ETB!$B$66:$C$674,2,0) -> Direct cost
A44: 469 | B44: 45049 | C44: Debit | D44: Amznmktplace On 02 May Bdc | E44: 54 | F44: 14.99 | H44: =VLOOKUP($E44,ETB!$B$66:$C$674,2,0) -> Direct cost
A45: 501 | B45: 45191 | C45: Debit | D45: Amznmktplace On 21 Sep Bdc | E45: 54 | F45: 19.99 | H45: =VLOOKUP($E45,ETB!$B$66:$C$674,2,0) -> Direct cost
... A64: 1018 | B64: 45258 | C64: Debit | D64: Ebay C 15441851672 On 28 Nov Bdc | E64: 54 | F64: 14.99 | H64: =VLOOKUP($E64,ETB!$B$66:$C$674,2,0) -> Direct cost
A65: 59 | B65: 45118 | C65: Counter Credit | D65: Ebay Commerce Uk L Ebay Microdeposit Bg | E65: 54 | G65: 0.05 | H65: =VLOOKUP($E65,ETB!$B$66:$C$674,2,0) -> Direct cost
A66: 65 | B66: 45118 | C66: Counter Credit | D66: Ebay Commerce Uk L Ebay Microdeposit Bg | E66: 54 | G66: 0.03 | H66: =VLOOKUP($E66,ETB!$B$66:$C$674,2,0) -> Direct cost
A67: 70 | B67: 45126 | C67: Unpaid | D67: Ebay Commerce Uk L Mrn22318562092 Unp | E67: 54 | G67: 0.08 | H67: =VLOOKUP($E67,ETB!$B$66:$C$674,2,0) -> Direct cost
A68: 1024 | B68: 45182 | C68: Debit | D68: Ebay Commerce Uk L On 12 Sep Bdc | E68: 54 | F68: 30.33 | H68: =VLOOKUP($E68,ETB!$B$66:$C$674,2,0) -> Direct cost
A69: 1026 | B69: 45187 | C69: Debit | D69: Ebay Commerce Uk L On 15 Sep Bdc | E69: 54 | F69: 14.99 | H69: =VLOOKUP($E69,ETB!$B$66:$C$674,2,0) -> Direct cost
A70: 1032 | B70: 45196 | C70: Debit | D70: Ebay Commerce Uk L On 26 Sep Bdc | E70: 54 | F70: 146 | H70: =VLOOKUP($E70,ETB!$B$66:$C$674,2,0) -> Direct cost
A71: 82 | B71: 45117 | C71: Counter Credit | D71: Ebay Commerce Uk L P*5947112312 Bgc | E71: 54 | G71: 190.66 | H71: =VLOOKUP($E71,ETB!$B$66:$C$674,2,0) -> Direct cost
A72: 86 | B72: 45201 | C72: Counter Credit | D72: Ebay Commerce Uk L P*6050347040 Bgc | E72: 54 | G72: 178.46 | H72: =VLOOKUP($E72,ETB!$B$66:$C$674,2,0) -> Direct cost
A73: 87 | B73: 45210 | C73: Counter Credit | D73: Ebay Commerce Uk L P*6064159016 Bgc | E73: 54 | G73: 44.97 | H73: =VLOOKUP($E73,ETB!$B$66:$C$674,2,0) -> Direct cost
A74: 1034 | B74: 44937 | C74: Debit | D74: Ebay O*01-09568-85 On 10 Jan Bdc | E74: 54 | F74: 35 | H74: =VLOOKUP($E74,ETB!$B$66:$C$674,2,0) -> Direct cost
A75: 91 | B75: 44950 | C75: Credit | D75: Ebay O*01-09619-18 On 23 Jan Bdc | E75: 54 | G75: 199 | H75: =VLOOKUP($E75,ETB!$B$66:$C$674,2,0) -> Direct cost
A76: 1044 | B76: 45210 | C76: Debit | D76: Ebay O*011064760 On 10 Oct Bdc | E76: 54 | F76: 31.79 | H76: =VLOOKUP($E76,ETB!$B$66:$C$674,2,0) -> Direct cost
A77: 1045 | B77: 45210 | C77: Debit | D77: Ebay O*011064760 On 10 Oct Bdc | E77: 54 | F77: 32.25 | H77: =VLOOKUP($E77,ETB!$B$66:$C$674,2,0) -> Direct cost
A78: 1048 | B78: 45245 | C78: Debit | D78: Ebay O*011079530 On 14 Nov Bdc | E78: 54 | F78: 71.32 | H78: =VLOOKUP($E78,ETB!$B$66:$C$674,2,0) -> Direct cost
A79: 92 | B79: 44950 | C79: Credit | D79: Ebay O*02-09604-37 On 23 Jan Bdc | E79: 54 | G79: 6.03 | H79: =VLOOKUP($E79,ETB!$B$66:$C$674,2,0) -> Direct cost
A80: 1068 | B80: 45184 | C80: Debit | D80: Ebay O*031054123 On 14 Sep Bdc | E80: 54 | F80: 24.99 | H80: =VLOOKUP($E80,ETB!$B$66:$C$674,2,0) -> Direct cost
A81: 1070 | B81: 44936 | C81: Debit | D81: Ebay O*04-09565-33 On 09 Jan Bdc | E81: 54 | F81: 25.19 | H81: =VLOOKUP($E81,ETB!$B$66:$C$674,2,0) -> Direct cost
A82: 1080 | B82: 45056 | C82: Debit | D82: Ebay O*05-10041-71 On 09 May Bdc | E82: 54 | F82: 28.39 | H82: =VLOOKUP($E82,ETB!$B$66:$C$674,2,0) -> Direct cost
A83: 98 | B83: 45189 | C83: Credit | D83: Ebay O*051045202 On 23 Aug Bdc | E83: 54 | G83: 115 | H83: =VLOOKUP($E83,ETB!$B$66:$C$674,2,0) -> Direct cost
A84: 1086 | B84: 45198 | C84: Debit | D84: Ebay O*051059802 On 28 Sep Bdc | E84: 54 | F84: 17.24 | H84: =VLOOKUP($E84,ETB!$B$66:$C$674,2,0) -> Direct cost
A85: 311 | B85: 45222 | C85: Credit | D85: Ebay O*061068408 On 19 Oct Bdc | E85: 54 | G85: 20 | H85: =VLOOKUP($E85,ETB!$B$66:$C$674,2,0) -> Direct cost
A86: 1098 | B86: 45254 | C86: Debit | D86: Ebay O*061083101 On 23 Nov Bdc | E86: 54 | F86: 21.59 | H86: =VLOOKUP($E86,ETB!$B$66:$C$674,2,0) -> Direct cost
A87: 1100 | B87: 45062 | C87: Debit | D87: Ebay O*07-10062-88 On 15 May Bdc | E87: 54 | F87: 99.9 | H87: =VLOOKUP($E87,ETB!$B$66:$C$674,2,0) -> Direct cost
A88: 1117 | B88: 44930 | C88: Debit | D88: Ebay O*10-09537-16 On 03 Jan Bdc | E88: 54 | F88: 20 | H88: =VLOOKUP($E88,ETB!$B$66:$C$674,2,0) -> Direct cost
A89: 1118 | B89: 44930 | C89: Debit | D89: Ebay O*10-09537-16 On 03 Jan Bdc | E89: 54 | F89: 101.29 | H89: =VLOOKUP($E89,ETB!$B$66:$C$674,2,0) -> Direct cost
A90: 1121 | B90: 45056 | C90: Debit | D90: Ebay O*10-10038-86 On 09 May Bdc | E90: 54 | F90: 119 | H90: =VLOOKUP($E90,ETB!$B$66:$C$674,2,0) -> Direct cost
A91: 100 | B91: 45184 | C91: Credit | D91: Ebay O*101042524 On 17 Aug Bdc | E91: 54 | G91: 160 | H91: =VLOOKUP($E91,ETB!$B$66:$C$674,2,0) -> Direct cost
A92: 1126 | B92: 44894 | C92: Debit | D92: Ebay O*11-09399-09 On 28 Nov Bdc | E92: 54 | F92: 10.95 | H92: =VLOOKUP($E92,ETB!$B$66:$C$674,2,0) -> Direct cost
A93: 1135 | B93: 45210 | C93: Debit | D93: Ebay O*131064046 On 10 Oct Bdc | E93: 54 | F93: 22.49 | H93: =VLOOKUP($E93,ETB!$B$66:$C$674,2,0) -> Direct cost
A94: 1145 | B94: 44936 | C94: Debit | D94: Ebay O*16-09560-57 On 09 Jan Bdc | E94: 54 | F94: 21.12 | H94: =VLOOKUP($E94,ETB!$B$66:$C$674,2,0) -> Direct cost
A95: 1146 | B95: 44936 | C95: Debit | D95: Ebay O*16-09560-57 On 09 Jan Bdc | E95: 54 | F95: 24 | H95: =VLOOKUP($E95,ETB!$B$66:$C$674,2,0) -> Direct cost
A96: 1147 | B96: 44936 | C96: Debit | D96: Ebay O*16-09560-57 On 09 Jan Bdc | E96: 54 | F96: 28 | H96: =VLOOKUP($E96,ETB!$B$66:$C$674,2,0) -> Direct cost
A97: 1153 | B97: 44916 | C97: Debit | D97: Ebay O*17-09490-43 On 20 Dec Bdc | E97: 54 | F97: 1.5 | H97: =VLOOKUP($E97,ETB!$B$66:$C$674,2,0) -> Direct cost
A98: 1154 | B98: 44917 | C98: Debit | D98: Ebay O*17-09493-91 On 21 Dec Bdc | E98: 54 | F98: 49.99 | H98: =VLOOKUP($E98,ETB!$B$66:$C$674,2,0) -> Direct cost
A99: 1158 | B99: 45245 | C99: Debit | D99: Ebay O*171078484 On 14 Nov Bdc | E99: 54 | F99: 22.98 | H99: =VLOOKUP($E99,ETB!$B$66:$C$674,2,0) -> Direct cost
A100: 1160 | B100: 44936 | C100: Debit | D100: Ebay O*18-09560-20 On 09 Jan Bdc | E100: 54 | F100: 70 | H100: =VLOOKUP($E100,ETB!$B$66:$C$674,2,0) -> Direct cost
A101: 1163 | B101: 45071 | C101: Debit | D101: Ebay O*18-10091-18 On 24 May Bdc | E101: 54 | F101: 22 | H101: =VLOOKUP($E101,ETB!$B$66:$C$674,2,0) -> Direct cost
A102: 1169 | B102: 44942 | C102: Debit | D102: Ebay O*19-09578-99 On 14 Jan Bdc | E102: 54 | F102: 14.99 | H102: =VLOOKUP($E102,ETB!$B$66:$C$674,2,0) -> Direct cost
A103: 1173 | B103: 45202 | C103: Debit | D103: Ebay O*191060502 On 02 Oct Bdc | E103: 54 | F103: 21.99 | H103: =VLOOKUP($E103,ETB!$B$66:$C$674,2,0) -> Direct cost
... A137: 1434 | B137: 45135 | C137: Debit | D137: Redcorn Limited On 27 Jul Bdc | E137: 54 | F137: 50 | H137: =VLOOKUP($E137,ETB!$B$66:$C$674,2,0) -> Direct cost
A138: 350 | B138: 44979 | C138: Credit | D138: S W Motor Factors On 21 Feb Bdc | E138: 54 | G138: 90.9 | H138: =VLOOKUP($E138,ETB!$B$66:$C$674,2,0) -> Direct cost
A139: 1551 | B139: 45040 | C139: Contactless Card Purchase | D139: Shell Epping 21 On 21 Apr Clp | E139: 54 | F139: 3.78 | H139: =VLOOKUP($E139,ETB!$B$66:$C$674,2,0) -> Direct cost
A140: 1567 | B140: 44970 | C140: Debit | D140: Sq *Completely Ken On 10 Feb Bdc | E140: 54 | F140: 20 | H140: =VLOOKUP($E140,ETB!$B$66:$C$674,2,0) -> Direct cost
A141: 1568 | B141: 45223 | C141: Contactless Card Purchase | D141: Sq *Completely Ken On 23 Oct Clp | E141: 54 | F141: 20.81 | H141: =VLOOKUP($E141,ETB!$B$66:$C$674,2,0) -> Direct cost
A142: 1570 | B142: 45042 | C142: Funds Transfer | D142: Stuart Colin Middl Renault Tipper Ft | E142: 54 | F142: 700 | H142: =VLOOKUP($E142,ETB!$B$66:$C$674,2,0) -> Direct cost
A143: 1578 | B143: 45237 | C143: Debit | D143: Sw Motor Factors On 06 Nov Bdc | E143: 54 | F143: 456.75 | H143: =VLOOKUP($E143,ETB!$B$66:$C$674,2,0) -> Direct cost
A144: 1591 | B144: 45139 | C144: Debit | D144: Sw Motor Factors On 31 Jul Bdc | E144: 54 | F144: 40.56 | H144: =VLOOKUP($E144,ETB!$B$66:$C$674,2,0) -> Direct cost
A145: 1609 | B145: 45048 | C145: Debit | D145: Thompsonsofcrewshi On 29 Apr Bdc | E145: 54 | F145: 193.2 | H145: =VLOOKUP($E145,ETB!$B$66:$C$674,2,0) -> Direct cost
A146: 1614 | B146: 45182 | C146: Funds Transfer | D146: Urban Auto Invoice 35 Ft | E146: 54 | F146: 1043.4 | H146: =VLOOKUP($E146,ETB!$B$66:$C$674,2,0) -> Direct cost
A147: 1619 | B147: 45224 | C147: Funds Transfer | D147: Urban Auto Invoice 41 Ft | E147: 54 | F147: 1109.3 | H147: =VLOOKUP($E147,ETB!$B$66:$C$674,2,0) -> Direct cost
A148: 1640 | B148: 44952 | C148: Funds Transfer | D148: Vaidas Sungaila Ga Ft | E148: 54 | F148: 350 | H148: =VLOOKUP($E148,ETB!$B$66:$C$674,2,0) -> Direct cost
A149: 375 | B149: 44960 | C149: Cash Withdrawal | D149: Volksbank Tirol Ag Austria Amount In Eur | E149: 54 | F149: 368.67 | H149: =VLOOKUP($E149,ETB!$B$66:$C$674,2,0) -> Direct cost
A150: 1660 | B150: 45034 | C150: Funds Transfer | D150: Warranty Solutions 2Nd Invoice Ft | E150: 54 | F150: 648 | H150: =VLOOKUP($E150,ETB!$B$66:$C$674,2,0) -> Direct cost
... A156: 1684 | B156: 45002 | C156: Debit | D156: Www.Lsengineers.Co On 16 Mar Bdc | E156: 54 | F156: 17.94 | H156: =VLOOKUP($E156,ETB!$B$66:$C$674,2,0) -> Direct cost
E158: 54 Total | F158: =SUBTOTAL(9,F34:F156) -> 0 | G158: =SUBTOTAL(9,G34:G156) -> 1005.18
A160: 115 | B160: 45131 | C160: Counter Credit | D160: Evans N R N Evans Tax Bgc | E160: 92 | G160: 176 | H160: =VLOOKUP($E160,ETB!$B$66:$C$674,2,0) -> Other income
A161: 124 | B161: 44963 | C161: Credit Payment | D161: Loyalty Reward 13 Dec - 12 Jan | E161: 92 | G161: 1.09 | H161: =VLOOKUP($E161,ETB!$B$66:$C$674,2,0) -> Other income
A162: 81 | B162: 45019 | C162: Credit Payment | D162: Loyalty Reward 13 Feb - 12 Mar | E162: 92 | G162: 1.95 | H162: =VLOOKUP($E162,ETB!$B$66:$C$674,2,0) -> Other income
A163: 164 | B163: 44991 | C163: Credit Payment | D163: Loyalty Reward 13 Jan - 12 Feb | E163: 92 | G163: 1.51 | H163: =VLOOKUP($E163,ETB!$B$66:$C$674,2,0) -> Other income
A164: 180 | B164: 45055 | C164: Credit Payment | D164: Loyalty Reward 13 Mar - 12 Apr | E164: 92 | G164: 4.97 | H164: =VLOOKUP($E164,ETB!$B$66:$C$674,2,0) -> Other income
A165: 185 | B165: 44935 | C165: Credit Payment | D165: Loyalty Reward 17 Nov - 12 Dec | E165: 92 | G165: 0.23 | H165: =VLOOKUP($E165,ETB!$B$66:$C$674,2,0) -> Other income
...

Sheet Queries
B2: Client : | C2: =Info!C3 -> Forest Car Company Ltd | F2: Prepared by : | G2: =Info!C8 -> Aratee | H2: Date : | I2: =Info!C9 -> 45343
B3: Year end : | C3: =Info!C6 -> 45260 | F3: Reviewed by : | G3: =Info!C11 -> Mitesh | H3: Date : | I3: =Info!C12 -> 45352
B5: Queries
C7: 1 | D7: Need Invoice copy for booking
K14: Mitesh review pont
J16: 1 | K16: Sales sheet- always use formula/ margin/VAT | Q16: Done - VAT as it is
J17: 2 | K17: Refreshment- Where VAT consider / remoev from personal/ keep around 2400 | Q17: Done
J18: 3 | K18: DCA- BP/ BR | Q18: Done
J19: 4 | K19: Old format/ IRIS

Sheet Reallocations
B2: Client : | C2: =Info!C3 -> Forest Car Company Ltd | F2: Prepared by : | G2: =Info!C8 -> Aratee | H2: Date : | I2: =Info!C9 -> 45343
B3: Year end : | C3: =Info!C6 -> 45260 | F3: Reviewed by : | G3: =Info!C11 -> Mitesh | H3: Date : | I3: =Info!C12 -> 45352
B5: Reallocations

Sheet Job plan
B2: Client : | C2: =Info!C3 -> Forest Car Company Ltd | F2: Prepared by : | G2: =Info!C8 -> Aratee | H2: Date : | I2: =Info!C9 -> 45343
B3: Year end : | C3: =Info!C6 -> 45260 | F3: Reviewed by : | G3: =Info!C11 -> Mitesh | H3: Date : | I3: =Info!C12 -> 45352
B5: Job plan
C6: Particulars | G6: Hours

Sheet Communication
B2: Client : | C2: =Info!C3 -> Forest Car Company Ltd | F2: Prepared by : | G2: =Info!C8 -> Aratee | H2: Date : | I2: =Info!C9 -> 45343
B3: Year end : | C3: =Info!C6 -> 45260 | F3: Reviewed by : | G3: =Info!C11 -> Mitesh | H3: Date : | I3: =Info!C12 -> 45352
B5: Communication trail

Sheet Opening Bal Adj
B2: =CONCATENATE(Info!A3," ",Info!C3) -> Client : Forest Car Company Ltd | E2: Prepared by : | F2: =Info!C8 -> Aratee | H2: Date : | I2: =Info!C9 -> 45343
B3: =Info!A4 -> Year-end : | E3: Reviewed by : | F3: =Info!C11 -> Mitesh | H3: Date : | I3: =Info!C12 -> 45352
B4: =Info!C6 -> 45260
B6: Opening Balance Adjustments
E8: As per XERO | H8: As per Final Accounts | K8: Difference in opening entries | N8: Opening Balance Diifference already adjusted | Q8: Opening balance difference
B9: Details | C9: TaxCalc Code | E9: Dr £ | F9: Cr £ | H9: Dr £ | I9: Cr £ | K9: Dr £ | L9: Cr £ | N9: Dr £ | O9: Cr £ | Q9: Dr £ | R9: Cr £
K11: =MAX(((H11-E11)-(I11-F11)),0) -> 0 | L11: =MAX(((I11-F11)-(H11-E11)),0) -> 0 | N11: 0 | O11: 0 | Q11: =MAX(((K11-L11)-(N11-O11)),0) -> 0 | R11: =MAX(((L11-K11)-(O11-N11)),0) -> 0
K12: =MAX(((H12-E12)-(I12-F12)),0) -> 0 | L12: =MAX(((I12-F12)-(H12-E12)),0) -> 0 | N12: 0 | O12: 0 | Q12: =MAX(((K12-L12)-(N12-O12)),0) -> 0 | R12: =MAX(((L12-K12)-(O12-N12)),0) -> 0
K13: =MAX(((H13-E13)-(I13-F13)),0) -> 0 | L13: =MAX(((I13-F13)-(H13-E13)),0) -> 0 | N13: 0 | O13: 0 | Q13: =MAX(((K13-L13)-(N13-O13)),0) -> 0 | R13: =MAX(((L13-K13)-(O13-N13)),0) -> 0
K14: =MAX(((H14-E14)-(I14-F14)),0) -> 0 | L14: =MAX(((I14-F14)-(H14-E14)),0) -> 0 | N14: 0 | O14: 0 | Q14: =MAX(((K14-L14)-(N14-O14)),0) -> 0 | R14: =MAX(((L14-K14)-(O14-N14)),0) -> 0
K15: =MAX(((H15-E15)-(I15-F15)),0) -> 0 | L15: =MAX(((I15-F15)-(H15-E15)),0) -> 0 | N15: 0 | O15: 0 | Q15: =MAX(((K15-L15)-(N15-O15)),0) -> 0 | R15: =MAX(((L15-K15)-(O15-N15)),0) -> 0
K16: =MAX(((H16-E16)-(I16-F16)),0) -> 0 | L16: =MAX(((I16-F16)-(H16-E16)),0) -> 0 | N16: 0 | O16: 0 | Q16: =MAX(((K16-L16)-(N16-O16)),0) -> 0 | R16: =MAX(((L16-K16)-(O16-N16)),0) -> 0
K17: =MAX(((H17-E17)-(I17-F17)),0) -> 0 | L17: =MAX(((I17-F17)-(H17-E17)),0) -> 0 | N17: 0 | O17: 0 | Q17: =MAX(((K17-L17)-(N17-O17)),0) -> 0 | R17: =MAX(((L17-K17)-(O17-N17)),0) -> 0
K18: =MAX(((H18-E18)-(I18-F18)),0) -> 0 | L18: =MAX(((I18-F18)-(H18-E18)),0) -> 0 | N18: 0 | O18: 0 | Q18: =MAX(((K18-L18)-(N18-O18)),0) -> 0 | R18: =MAX(((L18-K18)-(O18-N18)),0) -> 0
K19: =MAX(((H19-E19)-(I19-F19)),0) -> 0 | L19: =MAX(((I19-F19)-(H19-E19)),0) -> 0 | N19: 0 | O19: 0 | Q19: =MAX(((K19-L19)-(N19-O19)),0) -> 0 | R19: =MAX(((L19-K19)-(O19-N19)),0) -> 0
K20: =MAX(((H20-E20)-(I20-F20)),0) -> 0 | L20: =MAX(((I20-F20)-(H20-E20)),0) -> 0 | N20: 0 | O20: 0 | Q20: =MAX(((K20-L20)-(N20-O20)),0) -> 0 | R20: =MAX(((L20-K20)-(O20-N20)),0) -> 0
K21: =MAX(((H21-E21)-(I21-F21)),0) -> 0 | L21: =MAX(((I21-F21)-(H21-E21)),0) -> 0 | N21: 0 | O21: 0 | Q21: =MAX(((K21-L21)-(N21-O21)),0) -> 0 | R21: =MAX(((L21-K21)-(O21-N21)),0) -> 0
K22: =MAX(((H22-E22)-(I22-F22)),0) -> 0 | L22: =MAX(((I22-F22)-(H22-E22)),0) -> 0 | N22: 0 | O22: 0 | Q22: =MAX(((K22-L22)-(N22-O22)),0) -> 0 | R22: =MAX(((L22-K22)-(O22-N22)),0) -> 0
... K24: =MAX(((H24-E24)-(I24-F24)),0) -> 0 | L24: =MAX(((I24-F24)-(H24-E24)),0) -> 0 | N24: 0 | O24: 0 | Q24: =MAX(((K24-L24)-(N24-O24)),0) -> 0 | R24: =MAX(((L24-K24)-(O24-N24)),0) -> 0
K25: =MAX(((H25-E25)-(I25-F25)),0) -> 0 | L25: =MAX(((I25-F25)-(H25-E25)),0) -> 0 | N25: 0 | O25: 0 | Q25: =MAX(((K25-L25)-(N25-O25)),0) -> 0 | R25: =MAX(((L25-K25)-(O25-N25)),0) -> 0 | S25: 24200.93
K26: =MAX(((H26-E26)-(I26-F26)),0) -> 0 | L26: =MAX(((I26-F26)-(H26-E26)),0) -> 0 | N26: 0 | O26: 0 | Q26: =MAX(((K26-L26)-(N26-O26)),0) -> 0 | R26: =MAX(((L26-K26)-(O26-N26)),0) -> 0 | S26: 20169.76
L27: =E28+E29+E30+E31-H27 -> 0 | N27: 0 | O27: 0 | Q27: =MAX(((K27-L27)-(N27-O27)),0) -> 0 | R27: =MAX(((L27-K27)-(O27-N27)),0) -> 0
K28: =MAX(((H28-E28)-(I28-F28)),0) -> 0 | N28: 0 | O28: 0 | Q28: =MAX(((K28-L28)-(N28-O28)),0) -> 0 | R28: =MAX(((L28-K28)-(O28-N28)),0) -> 0
K29: =MAX(((H29-E29)-(I29-F29)),0) -> 0 | N29: 0 | O29: 0 | Q29: =MAX(((K29-L29)-(N29-O29)),0) -> 0 | R29: =MAX(((L29-K29)-(O29-N29)),0) -> 0
K30: =MAX(((H30-E30)-(I30-F30)),0) -> 0 | N30: 0 | O30: 0 | Q30: =MAX(((K30-L30)-(N30-O30)),0) -> 0 | R30: =MAX(((L30-K30)-(O30-N30)),0) -> 0
K31: =MAX(((H31-E31)-(I31-F31)),0) -> 0 | N31: 0 | O31: 0 | Q31: =MAX(((K31-L31)-(N31-O31)),0) -> 0 | R31: =MAX(((L31-K31)-(O31-N31)),0) -> 0
K32: =MAX(((H32-E32)-(I32-F32)),0) -> 0 | L32: =MAX(((I32-F32)-(H32-E32)),0) -> 0 | N32: 0 | O32: 0 | Q32: =MAX(((K32-L32)-(N32-O32)),0) -> 0 | R32: =MAX(((L32-K32)-(O32-N32)),0) -> 0
K33: =MAX(((H33-E33)-(I33-F33)),0) -> 0 | L33: =MAX(((I33-F33)-(H33-E33)),0) -> 0 | N33: 0 | O33: 0 | Q33: =MAX(((K33-L33)-(N33-O33)),0) -> 0 | R33: =MAX(((L33-K33)-(O33-N33)),0) -> 0
K34: =MAX(((H34-E34)-(I34-F34)),0) -> 0 | L34: =MAX(((I34-F34)-(H34-E34)),0) -> 0 | N34: 0 | O34: 0 | Q34: =MAX(((K34-L34)-(N34-O34)),0) -> 0 | R34: =MAX(((L34-K34)-(O34-N34)),0) -> 0
K35: =MAX(((H35-E35)-(I35-F35)),0) -> 0 | L35: =MAX(((I35-F35)-(H35-E35)),0) -> 0 | N35: 0 | O35: 0 | Q35: =MAX(((K35-L35)-(N35-O35)),0) -> 0 | R35: =MAX(((L35-K35)-(O35-N35)),0) -> 0
K36: =MAX(((H36-E36)-(I36-F36)),0) -> 0 | L36: =MAX(((I36-F36)-(H36-E36)),0) -> 0 | N36: 0 | O36: 0 | Q36: =MAX(((K36-L36)-(N36-O36)),0) -> 0 | R36: =MAX(((L36-K36)-(O36-N36)),0) -> 0
K37: =MAX(((H37-E37)-(I37-F37)),0) -> 0 | L37: =MAX(((I37-F37)-(H37-E37)),0) -> 0 | N37: 0 | O37: 0 | Q37: =MAX(((K37-L37)-(N37-O37)),0) -> 0 | R37: =MAX(((L37-K37)-(O37-N37)),0) -> 0
K38: =MAX(((H38-E38)-(I38-F38)),0) -> 0 | L38: =MAX(((I38-F38)-(H38-E38)),0) -> 0 | N38: 0 | O38: 0 | Q38: =MAX(((K38-L38)-(N38-O38)),0) -> 0 | R38: =MAX(((L38-K38)-(O38-N38)),0) -> 0
K39: =MAX(((H39-E39)-(I39-F39)),0) -> 0 | L39: =MAX(((I39-F39)-(H39-E39)),0) -> 0 | N39: 0 | O39: 0 | Q39: =MAX(((K39-L39)-(N39-O39)),0) -> 0 | R39: =MAX(((L39-K39)-(O39-N39)),0) -> 0
K40: =MAX(((H40-E40)-(I40-F40)),0) -> 0 | L40: =MAX(((I40-F40)-(H40-E40)),0) -> 0 | N40: 0 | O40: 0 | Q40: =MAX(((K40-L40)-(N40-O40)),0) -> 0 | R40: =MAX(((L40-K40)-(O40-N40)),0) -> 0
K41: =MAX(((H41-E41)-(I41-F41)),0) -> 0 | L41: =MAX(((I41-F41)-(H41-E41)),0) -> 0 | N41: 0 | O41: 0 | Q41: =MAX(((K41-L41)-(N41-O41)),0) -> 0 | R41: =MAX(((L41-K41)-(O41-N41)),0) -> 0
K42: =MAX(((H42-E42)-(I42-F42)),0) -> 0 | L42: =MAX(((I42-F42)-(H42-E42)),0) -> 0 | N42: 0 | O42: 0 | Q42: =MAX(((K42-L42)-(N42-O42)),0) -> 0 | R42: =MAX(((L42-K42)-(O42-N42)),0) -> 0
K43: =MAX(((H43-E43)-(I43-F43)),0) -> 0 | L43: =MAX(((I43-F43)-(H43-E43)),0) -> 0 | N43: 0 | O43: 0 | Q43: =MAX(((K43-L43)-(N43-O43)),0) -> 0 | R43: =MAX(((L43-K43)-(O43-N43)),0) -> 0
... K48: =MAX(((H48-E48)-(I48-F48)),0) -> 0 | L48: =MAX(((I48-F48)-(H48-E48)),0) -> 0 | N48: 0 | O48: 0 | Q48: =MAX(((K48-L48)-(N48-O48)),0) -> 0 | R48: =MAX(((L48-K48)-(O48-N48)),0) -> 0
E50: =SUM(E11:E49) -> 0 | F50: =SUM(F11:F49) -> 0 | H50: =SUM(H11:H49) -> 0 | I50: =SUM(I11:I49) -> 0 | K50: =SUM(K11:K49) -> 0 | L50: =SUM(L11:L49) -> 0 | N50: =SUM(N11:N49) -> 0 | O50: =SUM(O11:O49) -> 0 | Q50: =SUM(Q11:Q49) -> 0 | R50: =SUM(R11:R49) -> 0
F51: =+F50-E50 -> 0 | I51: =+I50-H50 -> 0 | L51: =+L50-K50 -> 0 | O51: =+O50-N50 -> 0 | R51: =+R50-Q50 -> 0

Sheet Barclays Bank Ac 50237620
A1: Client Name : | C1: =Info!C3 -> Forest Car Company Ltd | E1: Prepared by: | G1: =+Info!C8 -> Aratee
A2: File No. : | C2: =+'BRS Barclays Bank Ac -30470120'!C2 -> 7033 | D2: =+E8 -> 692 | E2: Date: | G2: =+Info!C9 -> 45343
A4: A/C Holder Name: | C4: =+'BRS Barclays Bank Ac -30470120'!C4 -> Forest Car Company Ltd | E4: Reviewed by: | G4: =+Info!C11 -> Mitesh
A5: Bank Name : | C5: =+'BRS Barclays Bank Ac -30470120'!C5 -> Barclays Bank | E5: Date: | G5: =+Info!C12 -> 45352
A6: Account No. : | C6: =+'BRS Barclays Bank Ac -30470120'!C6 -> 30470120
A7: =C5& " A/c # "&C6 -> Barclays Bank A/c # 30470120
A8: Period Start : | C8: =Info!C5 -> 44783 | E8: =+'BRS Barclays Bank Ac -30470120'!E8 -> 692
A9: Period End : | C9: =Info!C6 -> 45260
A11: Sr No | B11: Date | D11: Particulars | E11: IRIS | F11: Payments | G11: Receipts | H11: Balance
B13: =+C8 -> 44783 | D13: OPENING BALANCE | H13: 0
A14: 1 | B14: 45232 | C14: Fund transfer | D14: 202519 30470120 MOBILE-CHANNEL FT | E14: 692 | G14: 50000 | H14: =H13-F14+G14 -> 50000
A17: Total£ | B17: 45187 | F17: =SUM(F14:F16) -> 0 | G17: =SUM(G14:G16) -> 50000 | H17: =H13+G17-F17 -> 50000

Sheet BRS Barclays Bank Ac 50237620
A1: Client Name : | C1: =Info!C3 -> Forest Car Company Ltd | E1: Prepared by : | G1: =+Info!C8 -> Aratee
A2: File No : | C2: 7033 | D2: =+E8&"R" -> 693R | E2: Date : | G2: =+Info!C9 -> 45343
A4: A/C Holder Name: | C4: =C1 -> Forest Car Company Ltd | E4: Reviewed by : | G4: =+Info!C11 -> Mitesh
A5: Bank Name : | C5: Barclays Bank | E5: Date : | G5: =+Info!C12 -> 45352
A6: Account No. : | C6: 50237620
A7: =C5& " A/c # "&C6 -> Barclays Bank A/c # 50237620
A8: Year End : | E8: 693
A9: Start : | B9: =Info!C5 -> 44783
A10: End : | B10: =Info!C6 -> 45260
B13: BANK RECONCILIATION | E13: =B10 -> 45260
D15: Page No. | E15: Date | F15: Amount | G15: Ref
B16: Closing Balance as per Bank Statement No | E16: =B10 -> 45260 | F16: ='C3-4 - Bank-2'!G17 -> 50000 | G16: H / 3 / 2
B18: DETAILS OF OUTSTANDING CHEQUES | F18: =E26 -> 0
B20: Date | C20: Particulars | D20: Cheque No. | E20: Amount (£) | G20: IRIS CODE
C26: TOTAL | E26: =SUBTOTAL(9,E21:E24) -> 0
B28: Closing Balance as per Accounts | E28: =E13 -> 45260 | F28: =F16-F18 -> 50000
B35: Bank Book Details
B37: Opening Balance as per Accounts | E37: =B9 -> 44783 | F37: 0 | G37: H / 3 / 3
B38: ADJUSTMENTS IF ANY
A40: ADD: | B40: RECEIPTS | F40: ='Barclays Bank Ac -30470120'!G1708 -> 598113.09
A42: LESS: | B42: PAYMENTS | F42: ='Barclays Bank Ac -30470120'!F1708 -> 554080.66
B45: CLOSING BALANCE AS PER ACCOUNTS | E45: =B10 -> 45260 | F45: =F37+F40-F42 -> 44032.43 | G45: H / 3 / 2
D47: Difference | F47: =F28-F45 -> 5967.57

Sheet Barclays Bank Ac 50237620 (C)
A1: Client Name : | C1: =Info!C3 -> Forest Car Company Ltd | E1: Prepared by: | G1: =+Info!C8 -> Aratee
A2: File No. : | C2: =+'BRS Barclays Bank Ac -30470120'!C2 -> 7033 | D2: =+E8 -> 692 | E2: Date: | G2: =+Info!C9 -> 45343
A4: A/C Holder Name: | C4: =+'BRS Barclays Bank Ac -30470120'!C4 -> Forest Car Company Ltd | E4: Reviewed by: | G4: =+Info!C11 -> Mitesh
A5: Bank Name : | C5: =+'BRS Barclays Bank Ac -30470120'!C5 -> Barclays Bank | E5: Date: | G5: =+Info!C12 -> 45352
A6: Account No. : | C6: =+'BRS Barclays Bank Ac -30470120'!C6 -> 30470120
A7: =C5& " A/c # "&C6 -> Barclays Bank A/c # 30470120
A8: Period Start : | C8: =Info!C5 -> 44783 | E8: =+'BRS Barclays Bank Ac -30470120'!E8 -> 692
A9: Period End : | C9: =Info!C6 -> 45260
A11: Sr No | B11: Date | D11: Particulars | E11: IRIS | F11: Payments | G11: Receipts
A13: 1 | B13: 45232 | C13: Fund transfer | D13: 202519 30470120 MOBILE-CHANNEL FT | E13: 692 | G13: 50000 | H13: Barclays BankA/c. No.: 30470120
E15: 692 Total | G15: =SUBTOTAL(9,G13:G13) -> 50000
E17: Grand Total | G17: =SUBTOTAL(9,G12:G13) -> 50000

Sheet Journal
B2: Client : | C2: =Info!C3 -> Forest Car Company Ltd | E2: Prepared by : | F2: =Info!C8 -> Aratee | G2: Date : | H2: =Info!C9 -> 45343
B3: Y/E : | C3: =Info!C6 -> 45260 | E3: Reviewed by : | F3: =Info!C11 -> Mitesh | G3: Date : | H3: =Info!C12 -> 45352
B5: Journals
B7: Sr. No. | C7: AP code | D7: Particulars | E7: Debit (£) | F7: Credit (£)
B9: PROFIT/(Loss) as per Books Profit and loss account :
B11: 1 | C11: 727 | D11: =IF(F11<>""," To "&IF(C11="","",VLOOKUP(C11,ETB!$B$10:$C$678,2,0)),IF(C11="","",VLOOKUP(C11,ETB!$B$10:$C$678,2,0))) -> Director's current account | E11: 100
C12: 966 | D12: =IF(F12<>""," To "&IF(C12="","",VLOOKUP(C12,ETB!$B$10:$C$678,2,0)),IF(C12="","",VLOOKUP(C12,ETB!$B$10:$C$678,2,0))) -> To Called up share capital | F12: 100
D13: =IF(F13<>""," To "&IF(C13="","",VLOOKUP(C13,ETB!$B$10:$C$678,2,0)),IF(C13="","",VLOOKUP(C13,ETB!$B$10:$C$678,2,0)))
D14: (Being : Share capital introduce through DCA.)
B16: =+B11+1 -> 2 | C16: 586 | D16: =IF(F16<>""," To "&IF(C16="","",VLOOKUP(C16,ETB!$B$10:$C$678,2,0)),IF(C16="","",VLOOKUP(C16,ETB!$B$10:$C$678,2,0))) -> Trade debtors | E16: =Sales!N253 -> 640214
C17: 1 | D17: =IF(F17<>""," To "&IF(C17="","",VLOOKUP(C17,ETB!$B$10:$C$678,2,0)),IF(C17="","",VLOOKUP(C17,ETB!$B$10:$C$678,2,0))) -> To Sales | F17: =Sales!P253 -> 615407.63
C18: 735 | D18: =IF(F18<>""," To "&IF(C18="","",VLOOKUP(C18,ETB!$B$10:$C$678,2,0)),IF(C18="","",VLOOKUP(C18,ETB!$B$10:$C$678,2,0))) -> To VAT | F18: =Sales!O253 -> 24806.37
D20: (Being : Current year sales booked.)
B22: =+B16+1 -> 3 | C22: 390/13 | D22: =IF(F22<>""," To "&IF(C22="","",VLOOKUP(C22,ETB!$B$10:$C$678,2,0)),IF(C22="","",VLOOKUP(C22,ETB!$B$10:$C$678,2,0))) -> Depreciation of fixtures and fittings | E22: ='F4 - FAR'!J30 -> 89.85
C23: 390/15 | D23: =IF(F23<>""," To "&IF(C23="","",VLOOKUP(C23,ETB!$B$10:$C$678,2,0)),IF(C23="","",VLOOKUP(C23,ETB!$B$10:$C$678,2,0))) -> Depreciation of computer equipment | E23: ='F4 - FAR'!J54 -> 82.6665
C24: 524/22 | D24: =IF(F24<>""," To "&IF(C24="","",VLOOKUP(C24,ETB!$B$10:$C$678,2,0)),IF(C24="","",VLOOKUP(C24,ETB!$B$10:$C$678,2,0))) -> To Fixtures & fittings - Charge for year | F24: =E22 -> 89.85
C25: 526/22 | D25: =IF(F25<>""," To "&IF(C25="","",VLOOKUP(C25,ETB!$B$10:$C$678,2,0)),IF(C25="","",VLOOKUP(C25,ETB!$B$10:$C$678,2,0))) -> To Computer equipment - Charge for year | F25: =E23 -> 82.6665
D27: (Being : Depreciation @20% RBM booked for current year.)
B29: =+B22+1 -> 4 | C29: 254 | D29: =IF(F29<>""," To "&IF(C29="","",VLOOKUP(C29,ETB!$B$10:$C$678,2,0)),IF(C29="","",VLOOKUP(C29,ETB!$B$10:$C$678,2,0))) -> Director's remuneration | E29: =Payroll!C38 -> 11440
C30: 254 | D30: =IF(F30<>""," To "&IF(C30="","",VLOOKUP(C30,ETB!$B$10:$C$678,2,0)),IF(C30="","",VLOOKUP(C30,ETB!$B$10:$C$678,2,0))) -> Director's remuneration | E30: =Payroll!K38 -> 97.35 | G30: ER NI
C31: 755 | D31: =IF(F31<>""," To "&IF(C31="","",VLOOKUP(C31,ETB!$B$10:$C$678,2,0)),IF(C31="","",VLOOKUP(C31,ETB!$B$10:$C$678,2,0))) -> To Social Security and other tax | F31: =E30 -> 97.35 | G31: ER NI
C32: 727 | D32: =IF(F32<>""," To "&IF(C32="","",VLOOKUP(C32,ETB!$B$10:$C$678,2,0)),IF(C32="","",VLOOKUP(C32,ETB!$B$10:$C$678,2,0))) -> To Director's current account | F32: =Payroll!J38 -> 11440
D33: =IF(F33<>""," To "&IF(C33="","",VLOOKUP(C33,ETB!$B$10:$C$678,2,0)),IF(C33="","",VLOOKUP(C33,ETB!$B$10:$C$678,2,0)))
D34: (Being : Director's remuneration booked for current year.)
B36: =+B29+1 -> 5 | C36: 255 | D36: =IF(F36<>""," To "&IF(C36="","",VLOOKUP(C36,ETB!$B$10:$C$678,2,0)),IF(C36="","",VLOOKUP(C36,ETB!$B$10:$C$678,2,0))) -> Wages | E36: =Payroll!C70 -> 11440
C37: 738 | D37: =IF(F37<>""," To "&IF(C37="","",VLOOKUP(C37,ETB!$B$10:$C$678,2,0)),IF(C37="","",VLOOKUP(C37,ETB!$B$10:$C$678,2,0))) -> To Net Wages | F37: =E36 -> 11440
D38: =IF(F38<>""," To "&IF(C38="","",VLOOKUP(C38,ETB!$B$10:$C$678,2,0)),IF(C38="","",VLOOKUP(C38,ETB!$B$10:$C$678,2,0)))
D39: (Being : Wages booked for current year.)
B41: =B36+1 -> 6 | C41: 668 | D41: =IF(F41<>""," To "&IF(C41="","",VLOOKUP(C41,ETB!$B$10:$C$678,2,0)),IF(C41="","",VLOOKUP(C41,ETB!$B$10:$C$678,2,0))) -> Cash in hand | E41: =Sales!AE240 -> 71072.2
C42: 727 | D42: =IF(F42<>""," To "&IF(C42="","",VLOOKUP(C42,ETB!$B$10:$C$678,2,0)),IF(C42="","",VLOOKUP(C42,ETB!$B$10:$C$678,2,0))) -> Director's current account | E42: =Sales!AD240 -> 1300
C43: 586 | D43: =IF(F43<>""," To "&IF(C43="","",VLOOKUP(C43,ETB!$B$10:$C$678,2,0)),IF(C43="","",VLOOKUP(C43,ETB!$B$10:$C$678,2,0))) -> To Trade debtors | F43: =Sales!AD240+Sales!AE240 -> 72372.2
D45: (Being : Trade debtors adjusted through cash and DCA.)
B47: =B41+1 -> 7 | C47: 1 | D47: =IF(F47<>""," To "&IF(C47="","",VLOOKUP(C47,ETB!$B$10:$C$678,2,0)),IF(C47="","",VLOOKUP(C47,ETB!$B$10:$C$678,2,0))) -> Sales | E47: =Sales!Y264 -> 12906
C48: 586 | D48: =IF(F48<>""," To "&IF(C48="","",VLOOKUP(C48,ETB!$B$10:$C$678,2,0)),IF(C48="","",VLOOKUP(C48,ETB!$B$10:$C$678,2,0))) -> To Trade debtors | F48: =E47 -> 12906
D50: (Being : Reversal of sales booked.)
B52: =+B47+1 -> 8 | C52: 586 | D52: =IF(F52<>""," To "&IF(C52="","",VLOOKUP(C52,ETB!$B$10:$C$678,2,0)),IF(C52="","",VLOOKUP(C52,ETB!$B$10:$C$678,2,0))) -> Trade debtors | E52: =Sales!Y240 -> 300
C53: 92 | D53: =IF(F53<>""," To "&IF(C53="","",VLOOKUP(C53,ETB!$B$10:$C$678,2,0)),IF(C53="","",VLOOKUP(C53,ETB!$B$10:$C$678,2,0))) -> To Other income | F53: =E52 -> 300
D55: (Being : Additional income booked which is incurred during sales.)
B57: =+B52+1 -> 9 | C57: 755 | D57: =IF(F57<>""," To "&IF(C57="","",VLOOKUP(C57,ETB!$B$10:$C$678,2,0)),IF(C57="","",VLOOKUP(C57,ETB!$B$10:$C$678,2,0))) -> Social Security and other tax | E57: =-'C4-4 - PAYE-NI'!H45 -> 97.35
C58: 254 | D58: =IF(F58<>""," To "&IF(C58="","",VLOOKUP(C58,ETB!$B$10:$C$678,2,0)),IF(C58="","",VLOOKUP(C58,ETB!$B$10:$C$678,2,0))) -> To Director's remuneration | F58: =E57 -> 97.35
D59: =IF(F59<>""," To "&IF(C59="","",VLOOKUP(C59,ETB!$B$10:$C$678,2,0)),IF(C59="","",VLOOKUP(C59,ETB!$B$10:$C$678,2,0)))
D60: (Being : Employer allowance received.)
B62: =+B57+1 -> 10 | C62: 569 | D62: =IF(F62<>""," To "&IF(C62="","",VLOOKUP(C62,ETB!$B$10:$C$678,2,0)),IF(C62="","",VLOOKUP(C62,ETB!$B$10:$C$678,2,0))) -> Stocks | E62: ='C1 - Stock'!H38 -> 44938
C63: 74 | D63: =IF(F63<>""," To "&IF(C63="","",VLOOKUP(C63,ETB!$B$10:$C$678,2,0)),IF(C63="","",VLOOKUP(C63,ETB!$B$10:$C$678,2,0))) -> To Closing stock | F63: =E62 -> 44938
D64: =IF(F64<>""," To "&IF(C64="","",VLOOKUP(C64,ETB!$B$10:$C$678,2,0)),IF(C64="","",VLOOKUP(C64,ETB!$B$10:$C$678,2,0)))
D65: (Being : Stock book for current year as per stock sheet.)
B67: =B62+1 -> 11 | C67: 263 | D67: =IF(F67<>""," To "&IF(C67="","",VLOOKUP(C67,ETB!$B$10:$C$678,2,0)),IF(C67="","",VLOOKUP(C67,ETB!$B$10:$C$678,2,0))) -> Telephone | E67: 900
C68: 727 | D68: =IF(F68<>""," To "&IF(C68="","",VLOOKUP(C68,ETB!$B$10:$C$678,2,0)),IF(C68="","",VLOOKUP(C68,ETB!$B$10:$C$678,2,0))) -> To Director's current account | F68: =E67 -> 900
D69: =IF(F69<>""," To "&IF(C69="","",VLOOKUP(C69,ETB!$B$10:$C$678,2,0)),IF(C69="","",VLOOKUP(C69,ETB!$B$10:$C$678,2,0)))
D70: (Being : Estimate expense booked for current year.)
B72: =+B67+1 -> 12 | C72: 737 | D72: =IF(F72<>""," To "&IF(C72="","",VLOOKUP(C72,ETB!$B$10:$C$678,2,0)),IF(C72="","",VLOOKUP(C72,ETB!$B$10:$C$678,2,0))) -> Trade creditors | E72: ='Reversal-Addition Expense '!Q39 -> 7776.03
C73: 54 | D73: =IF(F73<>""," To "&IF(C73="","",VLOOKUP(C73,ETB!$B$10:$C$678,2,0)),IF(C73="","",VLOOKUP(C73,ETB!$B$10:$C$678,2,0))) -> To Direct cost | F73: =SUMIF('Reversal-Addition Expense '!$K$8:$N$27,$C73,'Reversal-Addition Expense '!$S$8:$S$27) -> 972.76
C74: 54 | D74: =IF(F74<>""," To "&IF(C74="","",VLOOKUP(C74,ETB!$B$10:$C$678,2,0)),IF(C74="","",VLOOKUP(C74,ETB!$B$10:$C$678,2,0))) -> To Direct cost | F74: =SUMIF('Reversal-Addition Expense '!$K$8:$N$27,$C74,'Reversal-Addition Expense '!$T$8:$T$27) -> 38.97 | G74: VAT
C75: 274 | D75: =IF(F75<>""," To "&IF(C75="","",VLOOKUP(C75,ETB!$B$10:$C$678,2,0)),IF(C75="","",VLOOKUP(C75,ETB!$B$10:$C$678,2,0))) -> To Household and cleaning | F75: =SUMIF('Reversal-Addition Expense '!$K$8:$N$27,$C75,'Reversal-Addition Expense '!$S$8:$S$27) -> 4764.3
C76: 27 | D76: =IF(F76<>""," To "&IF(C76="","",VLOOKUP(C76,ETB!$B$10:$C$678,2,0)),IF(C76="","",VLOOKUP(C76,ETB!$B$10:$C$678,2,0))) -> To Purchases | F76: ='Reversal-Addition Expense '!S36 -> 2000
D78: (Being : Reversal of expense.)
B80: =+B72+1 -> 13 | C80: 737 | D80: =IF(F80<>""," To "&IF(C80="","",VLOOKUP(C80,ETB!$B$10:$C$678,2,0)),IF(C80="","",VLOOKUP(C80,ETB!$B$10:$C$678,2,0))) -> Trade creditors | E80: =Duplicate!O150 -> 4347.11
C81: 54 | D81: =IF(F81<>""," To "&IF(C81="","",VLOOKUP(C81,ETB!$B$10:$C$678,2,0)),IF(C81="","",VLOOKUP(C81,ETB!$B$10:$C$678,2,0))) -> To Direct cost | F81: =SUMIF(Duplicate!$I$8:$L$148,$C81,Duplicate!$R$8:$R$148) -> 2499.97
C82: 54 | D82: =IF(F82<>""," To "&IF(C82="","",VLOOKUP(C82,ETB!$B$10:$C$678,2,0)),IF(C82="","",VLOOKUP(C82,ETB!$B$10:$C$678,2,0))) -> To Direct cost | F82: =SUMIF(Duplicate!$I$8:$L$148,$C82,Duplicate!$S$8:$S$148) -> 217.44 | G82: VAT
C83: 261 | D83: =IF(F83<>""," To "&IF(C83="","",VLOOKUP(C83,ETB!$B$10:$C$678,2,0)),IF(C83="","",VLOOKUP(C83,ETB!$B$10:$C$678,2,0))) -> To Refreshments | F83: =SUMIF(Duplicate!$I$8:$L$148,$C83,Duplicate!$R$8:$R$148) -> 100
C84: 265 | D84: =IF(F84<>""," To "&IF(C84="","",VLOOKUP(C84,ETB!$B$10:$C$678,2,0)),IF(C84="","",VLOOKUP(C84,ETB!$B$10:$C$678,2,0))) -> To Advertising | F84: =SUMIF(Duplicate!$I$8:$L$148,$C84,Duplicate!$R$8:$R$148) -> 696.2
C85: 265 | D85: =IF(F85<>""," To "&IF(C85="","",VLOOKUP(C85,ETB!$B$10:$C$678,2,0)),IF(C85="","",VLOOKUP(C85,ETB!$B$10:$C$678,2,0))) -> To Advertising | F85: =SUMIF(Duplicate!$I$8:$L$148,$C85,Duplicate!$S$8:$S$148) -> 139.24 | G85: VAT
C86: 266 | D86: =IF(F86<>""," To "&IF(C86="","",VLOOKUP(C86,ETB!$B$10:$C$678,2,0)),IF(C86="","",VLOOKUP(C86,ETB!$B$10:$C$678,2,0))) -> To Travelling | F86: =SUMIF(Duplicate!$I$8:$L$148,$C86,Duplicate!$R$8:$R$148) -> 37.93
C87: 271 | D87: =IF(F87<>""," To "&IF(C87="","",VLOOKUP(C87,ETB!$B$10:$C$678,2,0)),IF(C87="","",VLOOKUP(C87,ETB!$B$10:$C$678,2,0))) -> To Clothing | F87: =SUMIF(Duplicate!$I$8:$L$148,$C87,Duplicate!$R$8:$R$148) -> 546.94
C88: 271 | D88: =IF(F88<>""," To "&IF(C88="","",VLOOKUP(C88,ETB!$B$10:$C$678,2,0)),IF(C88="","",VLOOKUP(C88,ETB!$B$10:$C$678,2,0))) -> To Clothing | F88: =SUMIF(Duplicate!$I$8:$L$148,$C88,Duplicate!$S$8:$S$148) -> 109.39 | G88: VAT
D90: (Being : Duplicate expense reversed.)
B92: =+B80+1 -> 14 | C92: 727 | D92: =IF(F92<>""," To "&IF(C92="","",VLOOKUP(C92,ETB!$B$10:$C$678,2,0)),IF(C92="","",VLOOKUP(C92,ETB!$B$10:$C$678,2,0))) -> Director's current account | E92: =F93+F94+F95 -> 13203.68
C93: 261 | D93: =IF(F93<>""," To "&IF(C93="","",VLOOKUP(C93,ETB!$B$10:$C$678,2,0)),IF(C93="","",VLOOKUP(C93,ETB!$B$10:$C$678,2,0))) -> To Refreshments | F93: =4496+2399.99 -> 6895.99
C94: 271 | D94: =IF(F94<>""," To "&IF(C94="","",VLOOKUP(C94,ETB!$B$10:$C$678,2,0)),IF(C94="","",VLOOKUP(C94,ETB!$B$10:$C$678,2,0))) -> To Clothing | F94: 1142.69
C95: 274 | D95: =IF(F95<>""," To "&IF(C95="","",VLOOKUP(C95,ETB!$B$10:$C$678,2,0)),IF(C95="","",VLOOKUP(C95,ETB!$B$10:$C$678,2,0))) -> To Household and cleaning | F95: 5165
D97: (Being : Expense move to DCA.)
B99: =+B92+1 -> 15 | C99: 737 | D99: =IF(F99<>""," To "&IF(C99="","",VLOOKUP(C99,ETB!$B$10:$C$678,2,0)),IF(C99="","",VLOOKUP(C99,ETB!$B$10:$C$678,2,0))) -> Trade creditors | E99: ='PDB Expense'!Y1316+'PDB Expense'!X1316 -> 325554.79
C100: 668 | D100: =IF(F100<>""," To "&IF(C100="","",VLOOKUP(C100,ETB!$B$10:$C$678,2,0)),IF(C100="","",VLOOKUP(C100,ETB!$B$10:$C$678,2,0))) -> To Cash in hand | F100: ='PDB Expense'!Y1316 -> 68455.03
C101: 727 | D101: =IF(F101<>""," To "&IF(C101="","",VLOOKUP(C101,ETB!$B$10:$C$678,2,0)),IF(C101="","",VLOOKUP(C101,ETB!$B$10:$C$678,2,0))) -> To Director's current account | F101: ='PDB Expense'!X1316 -> 257099.76
D102: =IF(F102<>""," To "&IF(C102="","",VLOOKUP(C102,ETB!$B$10:$C$678,2,0)),IF(C102="","",VLOOKUP(C102,ETB!$B$10:$C$678,2,0)))
D103: (Being : Trade creditors paid through Cash and DCA.)
B105: =+B99+1 -> 16 | C105: 737 | D105: =IF(F105<>""," To "&IF(C105="","",VLOOKUP(C105,ETB!$B$10:$C$678,2,0)),IF(C105="","",VLOOKUP(C105,ETB!$B$10:$C$678,2,0))) -> Trade creditors | E105: ='PDB Purchase'!X253 -> 2200
C106: 586 | D106: =IF(F106<>""," To "&IF(C106="","",VLOOKUP(C106,ETB!$B$10:$C$678,2,0)),IF(C106="","",VLOOKUP(C106,ETB!$B$10:$C$678,2,0))) -> To Trade debtors | F106: =E105 -> 2200
D107: =IF(F107<>""," To "&IF(C107="","",VLOOKUP(C107,ETB!$B$10:$C$678,2,0)),IF(C107="","",VLOOKUP(C107,ETB!$B$10:$C$678,2,0)))
D108: (Being : Sales return shown as purchase.)
B110: =+B105+1 -> 17 | C110: 738 | D110: =IF(F110<>""," To "&IF(C110="","",VLOOKUP(C110,ETB!$B$10:$C$678,2,0)),IF(C110="","",VLOOKUP(C110,ETB!$B$10:$C$678,2,0))) -> Net Wages | E110: =Payroll!O58 -> 630
C111: 668 | D111: =IF(F111<>""," To "&IF(C111="","",VLOOKUP(C111,ETB!$B$10:$C$678,2,0)),IF(C111="","",VLOOKUP(C111,ETB!$B$10:$C$678,2,0))) -> To Cash in hand | F111: =E110 -> 630
D112: =IF(F112<>""," To "&IF(C112="","",VLOOKUP(C112,ETB!$B$10:$C$678,2,0)),IF(C112="","",VLOOKUP(C112,ETB!$B$10:$C$678,2,0)))
D113: (Being : Wages paid through cash.)
B115: =+B110+1 -> 18 | C115: 668 | D115: =IF(F115<>""," To "&IF(C115="","",VLOOKUP(C115,ETB!$B$10:$C$678,2,0)),IF(C115="","",VLOOKUP(C115,ETB!$B$10:$C$678,2,0))) -> Cash in hand | E115: 13784.83
C116: 727 | D116: =IF(F116<>""," To "&IF(C116="","",VLOOKUP(C116,ETB!$B$10:$C$678,2,0)),IF(C116="","",VLOOKUP(C116,ETB!$B$10:$C$678,2,0))) -> To Director's current account | F116: =E115 -> 13784.83
D117: =IF(F117<>""," To "&IF(C117="","",VLOOKUP(C117,ETB!$B$10:$C$678,2,0)),IF(C117="","",VLOOKUP(C117,ETB!$B$10:$C$678,2,0)))
D118: (Being : Cash introduce through DCA.)
B120: =+B115+1 -> 19 | C120: 727 | D120: =IF(F120<>""," To "&IF(C120="","",VLOOKUP(C120,ETB!$B$10:$C$678,2,0)),IF(C120="","",VLOOKUP(C120,ETB!$B$10:$C$678,2,0))) -> Director's current account | E120: =F121+F122 -> 105000
C121: 1 | D121: =IF(F121<>""," To "&IF(C121="","",VLOOKUP(C121,ETB!$B$10:$C$678,2,0)),IF(C121="","",VLOOKUP(C121,ETB!$B$10:$C$678,2,0))) -> To Sales | F121: 70000
C122: 92 | D122: =IF(F122<>""," To "&IF(C122="","",VLOOKUP(C122,ETB!$B$10:$C$678,2,0)),IF(C122="","",VLOOKUP(C122,ETB!$B$10:$C$678,2,0))) -> To Other income | F122: 35000
D124: (Being : Estimate income booked.)
B126: =+B120+1 -> 20 | C126: 442 | D126: =IF(F126<>""," To "&IF(C126="","",VLOOKUP(C126,ETB!$B$10:$C$678,2,0)),IF(C126="","",VLOOKUP(C126,ETB!$B$10:$C$678,2,0))) -> Tax | E126: ='C4-3 - CT'!G47 -> 913.33
C127: 747 | D127: =IF(F127<>""," To "&IF(C127="","",VLOOKUP(C127,ETB!$B$10:$C$678,2,0)),IF(C127="","",VLOOKUP(C127,ETB!$B$10:$C$678,2,0))) -> To Corporation Tax | F127: =E126 -> 913.33
D128: =IF(F128<>""," To "&IF(C128="","",VLOOKUP(C128,ETB!$B$10:$C$678,2,0)),IF(C128="","",VLOOKUP(C128,ETB!$B$10:$C$678,2,0)))
D129: (Being : Corporation tax provision for current year booked.)
B131: =+B126+1 -> 21 | D131: =IF(F131<>""," To "&IF(C131="","",VLOOKUP(C131,ETB!$B$10:$C$678,2,0)),IF(C131="","",VLOOKUP(C131,ETB!$B$10:$C$678,2,0)))
D132: =IF(F132<>""," To "&IF(C132="","",VLOOKUP(C132,ETB!$B$10:$C$678,2,0)),IF(C132="","",VLOOKUP(C132,ETB!$B$10:$C$678,2,0)))
D133: =IF(F133<>""," To "&IF(C133="","",VLOOKUP(C133,ETB!$B$10:$C$678,2,0)),IF(C133="","",VLOOKUP(C133,ETB!$B$10:$C$678,2,0)))
D134: (Being : Internet expenses reallocated from computer expense)
...

Sheet TB
B2: Client : | C2: =Index!C2 -> Forest Car Company Ltd | D2: Prepared by : | E2: =Info!C8 -> Aratee | F2: Date : | G2: =Index!J2 -> 45343
B3: Year end : | C3: =Index!C3 -> 45260 | D3: Reviewed by : | E3: =Info!C11 -> Mitesh | F3: Date : | G3: =Index!J3 -> 45352
B5: Trial Balance
B7: Tax calc | C7: NL Description | D7: Dr | E7: Cr
D122: =SUM(D8:D121) -> 0 | E122: =SUM(E8:E121) -> 0
D124: =E122-D122 -> 0

Sheet Opening TB
B2: Client : | C2: =Index!C2 -> Forest Car Company Ltd | D2: Prepared by : | E2: =Info!C8 -> Aratee | F2: Date : | G2: =Index!J2 -> 45343
B3: Year end : | C3: =Index!C3 -> 45260 | D3: Reviewed by : | E3: =Info!C11 -> Mitesh | F3: Date : | G3: =Index!J3 -> 45352
B5: Trial Balance
B7: N/C | C7: NL Description | D7: Dr | E7: Cr | G7: Check
G8: =VLOOKUP(B:B,ETB!B:B,1,) -> 0
G9: =VLOOKUP(B:B,ETB!B:B,1,) -> 0
G10: =VLOOKUP(B:B,ETB!B:B,1,) -> 0
G11: =VLOOKUP(B:B,ETB!B:B,1,) -> 0
G12: =VLOOKUP(B:B,ETB!B:B,1,) -> 0
G13: =VLOOKUP(B:B,ETB!B:B,1,) -> 0
G14: =VLOOKUP(B:B,ETB!B:B,1,) -> 0
G15: =VLOOKUP(B:B,ETB!B:B,1,) -> 0
G16: =VLOOKUP(B:B,ETB!B:B,1,) -> 0
G17: =VLOOKUP(B:B,ETB!B:B,1,) -> 0
G18: =VLOOKUP(B:B,ETB!B:B,1,) -> 0
G19: =VLOOKUP(B:B,ETB!B:B,1,) -> 0
... G89: =VLOOKUP(B:B,ETB!B:B,1,) -> 0
D92: =SUM(D8:D91) -> 0 | E92: =SUM(E8:E91) -> 0
D94: =E92-D92 -> 0

Sheet ETB
B2: Client : | C2: =Info!C3 -> Forest Car Company Ltd | L2: Prepared by : | M2: =Info!C8 -> Aratee | Q2: Date : | R2: =Info!C9 -> 45343
B3: Year end : | C3: =Info!C6 -> 45260 | L3: Reviewed by : | M3: =Info!C11 -> Mitesh | Q3: Date : | R3: =Info!C12 -> 45352
B5: Extended Trial Balance (ETB)
B6: =+D7 -> Opening Balance
B7: IRIS Code | C7: Name | D7: Opening Balance | F7: Barclays BankA/c. No.: 30470120 | H7: Barclays BankA/c. No.: 50237620 | J7: PDB | L7: Journals | N7: Finalisation Journal | Q7: Closing Balance | S7: IRIS Code
D8: Debit | E8: Credit | F8: Debit | G8: Credit | H8: Debit | I8: Credit | J8: Debit | K8: Credit | L8: Debit | M8: Credit | N8: Debit | O8: Credit | Q8: Debit | R8: Credit
B10: 502 | C10: Goodwill | D10: =SUMIF(TB!$B$9:$E$120,ETB!B10,TB!$D$9:$D$120) -> 0 | E10: =SUMIF(TB!$B$9:$E$120,ETB!B10,TB!$E$9:$E$120) -> 0 | L10: =SUMIF(Journal!$C$10:$C$304,ETB!B10,Journal!$E$10:$E$304) -> 0 | M10: =SUMIF(Journal!$C$10:$C$304,ETB!B10,Journal!$F$10:$F$304) -> 0 | Q10: =MAX((D10-E10+F10-G10+J10-K10+L10-M10+N10-O10),0) -> 0 | R10: =MAX((M10-L10+K10-J10+G10-F10+E10-D10+O10-N10),0) -> 0 | S10: =B10 -> 502 | U10: =+Q10-R10 -> 0
B11: 502/1 | C11: Goodwill Cost/valuation b/f | D11: =SUMIF(TB!$B$9:$E$120,ETB!B11,TB!$D$9:$D$120) -> 0 | E11: =SUMIF(TB!$B$9:$E$120,ETB!B11,TB!$E$9:$E$120) -> 0 | L11: =SUMIF(Journal!$C$10:$C$304,ETB!B11,Journal!$E$10:$E$304) -> 0 | M11: =SUMIF(Journal!$C$10:$C$304,ETB!B11,Journal!$F$10:$F$304) -> 0 | Q11: =MAX((D11-E11+F11-G11+J11-K11+L11-M11+N11-O11),0) -> 0 | R11: =MAX((M11-L11+K11-J11+G11-F11+E11-D11+O11-N11),0) -> 0 | S11: =B11 -> 502/1 | U11: =+Q11-R11 -> 0
B12: 502/2 | C12: Goodwill - Additions | D12: =SUMIF(TB!$B$9:$E$120,ETB!B12,TB!$D$9:$D$120) -> 0 | E12: =SUMIF(TB!$B$9:$E$120,ETB!B12,TB!$E$9:$E$120) -> 0 | L12: =SUMIF(Journal!$C$10:$C$304,ETB!B12,Journal!$E$10:$E$304) -> 0 | M12: =SUMIF(Journal!$C$10:$C$304,ETB!B12,Journal!$F$10:$F$304) -> 0 | Q12: =MAX((D12-E12+F12-G12+J12-K12+L12-M12+N12-O12),0) -> 0 | R12: =MAX((M12-L12+K12-J12+G12-F12+E12-D12+O12-N12),0) -> 0 | S12: =B12 -> 502/2 | U12: =+Q12-R12 -> 0
B13: 502/3 | C13: Goodwill - Disposals | D13: =SUMIF(TB!$B$9:$E$120,ETB!B13,TB!$D$9:$D$120) -> 0 | E13: =SUMIF(TB!$B$9:$E$120,ETB!B13,TB!$E$9:$E$120) -> 0 | L13: =SUMIF(Journal!$C$10:$C$304,ETB!B13,Journal!$E$10:$E$304) -> 0 | M13: =SUMIF(Journal!$C$10:$C$304,ETB!B13,Journal!$F$10:$F$304) -> 0 | Q13: =MAX((D13-E13+F13-G13+J13-K13+L13-M13+N13-O13),0) -> 0 | R13: =MAX((M13-L13+K13-J13+G13-F13+E13-D13+O13-N13),0) -> 0 | S13: =B13 -> 502/3 | U13: =+Q13-R13 -> 0
B14: 502/21 | C14: Goodwill - Amortisation b/fwd | D14: =SUMIF(TB!$B$9:$E$120,ETB!B14,TB!$D$9:$D$120) -> 0 | E14: =SUMIF(TB!$B$9:$E$120,ETB!B14,TB!$E$9:$E$120) -> 0 | L14: =SUMIF(Journal!$C$10:$C$304,ETB!B14,Journal!$E$10:$E$304) -> 0 | M14: =SUMIF(Journal!$C$10:$C$304,ETB!B14,Journal!$F$10:$F$304) -> 0 | Q14: =MAX((D14-E14+F14-G14+J14-K14+L14-M14+N14-O14),0) -> 0 | R14: =MAX((M14-L14+K14-J14+G14-F14+E14-D14+O14-N14),0) -> 0 | S14: =B14 -> 502/21 | U14: =+Q14-R14 -> 0
B15: 502/22 | C15: Goodwill - Charge for year | D15: =SUMIF(TB!$B$9:$E$120,ETB!B15,TB!$D$9:$D$120) -> 0 | E15: =SUMIF(TB!$B$9:$E$120,ETB!B15,TB!$E$9:$E$120) -> 0 | L15: =SUMIF(Journal!$C$10:$C$304,ETB!B15,Journal!$E$10:$E$304) -> 0 | M15: =SUMIF(Journal!$C$10:$C$304,ETB!B15,Journal!$F$10:$F$304) -> 0 | Q15: =MAX((D15-E15+F15-G15+J15-K15+L15-M15+N15-O15),0) -> 0 | R15: =MAX((M15-L15+K15-J15+G15-F15+E15-D15+O15-N15),0) -> 0 | S15: =B15 -> 502/22 | U15: =+Q15-R15 -> 0
B16: 502/23 | C16: Goodwill - Eliminated on disposals | D16: =SUMIF(TB!$B$9:$E$120,ETB!B16,TB!$D$9:$D$120) -> 0 | E16: =SUMIF(TB!$B$9:$E$120,ETB!B16,TB!$E$9:$E$120) -> 0 | L16: =SUMIF(Journal!$C$10:$C$304,ETB!B16,Journal!$E$10:$E$304) -> 0 | M16: =SUMIF(Journal!$C$10:$C$304,ETB!B16,Journal!$F$10:$F$304) -> 0 | Q16: =MAX((D16-E16+F16-G16+J16-K16+L16-M16+N16-O16),0) -> 0 | R16: =MAX((M16-L16+K16-J16+G16-F16+E16-D16+O16-N16),0) -> 0 | S16: =B16 -> 502/23 | U16: =+Q16-R16 -> 0
B17: 503 | C17: Patents & licences | D17: =SUMIF(TB!$B$9:$E$120,ETB!B17,TB!$D$9:$D$120) -> 0 | E17: =SUMIF(TB!$B$9:$E$120,ETB!B17,TB!$E$9:$E$120) -> 0 | L17: =SUMIF(Journal!$C$10:$C$304,ETB!B17,Journal!$E$10:$E$304) -> 0 | M17: =SUMIF(Journal!$C$10:$C$304,ETB!B17,Journal!$F$10:$F$304) -> 0 | Q17: =MAX((D17-E17+F17-G17+J17-K17+L17-M17+N17-O17),0) -> 0 | R17: =MAX((M17-L17+K17-J17+G17-F17+E17-D17+O17-N17),0) -> 0 | S17: =B17 -> 503 | U17: =+Q17-R17 -> 0
B18: 503/1 | C18: Patents & licences Cost/valuation b/f | D18: =SUMIF(TB!$B$9:$E$120,ETB!B18,TB!$D$9:$D$120) -> 0 | E18: =SUMIF(TB!$B$9:$E$120,ETB!B18,TB!$E$9:$E$120) -> 0 | L18: =SUMIF(Journal!$C$10:$C$304,ETB!B18,Journal!$E$10:$E$304) -> 0 | M18: =SUMIF(Journal!$C$10:$C$304,ETB!B18,Journal!$F$10:$F$304) -> 0 | Q18: =MAX((D18-E18+F18-G18+J18-K18+L18-M18+N18-O18),0) -> 0 | R18: =MAX((M18-L18+K18-J18+G18-F18+E18-D18+O18-N18),0) -> 0 | S18: =B18 -> 503/1 | U18: =+Q18-R18 -> 0
B19: 503/2 | C19: Patents & licences - additions | D19: =SUMIF(TB!$B$9:$E$120,ETB!B19,TB!$D$9:$D$120) -> 0 | E19: =SUMIF(TB!$B$9:$E$120,ETB!B19,TB!$E$9:$E$120) -> 0 | L19: =SUMIF(Journal!$C$10:$C$304,ETB!B19,Journal!$E$10:$E$304) -> 0 | M19: =SUMIF(Journal!$C$10:$C$304,ETB!B19,Journal!$F$10:$F$304) -> 0 | Q19: =MAX((D19-E19+F19-G19+J19-K19+L19-M19+N19-O19),0) -> 0 | R19: =MAX((M19-L19+K19-J19+G19-F19+E19-D19+O19-N19),0) -> 0 | S19: =B19 -> 503/2 | U19: =+Q19-R19 -> 0
B20: 503/3 | C20: Patents & licences - disposals | D20: =SUMIF(TB!$B$9:$E$120,ETB!B20,TB!$D$9:$D$120) -> 0 | E20: =SUMIF(TB!$B$9:$E$120,ETB!B20,TB!$E$9:$E$120) -> 0 | L20: =SUMIF(Journal!$C$10:$C$304,ETB!B20,Journal!$E$10:$E$304) -> 0 | M20: =SUMIF(Journal!$C$10:$C$304,ETB!B20,Journal!$F$10:$F$304) -> 0 | Q20: =MAX((D20-E20+F20-G20+J20-K20+L20-M20+N20-O20),0) -> 0 | R20: =MAX((M20-L20+K20-J20+G20-F20+E20-D20+O20-N20),0) -> 0 | S20: =B20 -> 503/3 | U20: =+Q20-R20 -> 0
B21: 503/21 | C21: Patents & licences - amortisation b/fwd | D21: =SUMIF(TB!$B$9:$E$120,ETB!B21,TB!$D$9:$D$120) -> 0 | E21: =SUMIF(TB!$B$9:$E$120,ETB!B21,TB!$E$9:$E$120) -> 0 | L21: =SUMIF(Journal!$C$10:$C$304,ETB!B21,Journal!$E$10:$E$304) -> 0 | M21: =SUMIF(Journal!$C$10:$C$304,ETB!B21,Journal!$F$10:$F$304) -> 0 | Q21: =MAX((D21-E21+F21-G21+J21-K21+L21-M21+N21-O21),0) -> 0 | R21: =MAX((M21-L21+K21-J21+G21-F21+E21-D21+O21-N21),0) -> 0 | S21: =B21 -> 503/21 | U21: =+Q21-R21 -> 0
B22: 503/22 | C22: Patents & licences - amortisation charge in year | D22: =SUMIF(TB!$B$9:$E$120,ETB!B22,TB!$D$9:$D$120) -> 0 | E22: =SUMIF(TB!$B$9:$E$120,ETB!B22,TB!$E$9:$E$120) -> 0 | L22: =SUMIF(Journal!$C$10:$C$304,ETB!B22,Journal!$E$10:$E$304) -> 0 | M22: =SUMIF(Journal!$C$10:$C$304,ETB!B22,Journal!$F$10:$F$304) -> 0 | Q22: =MAX((D22-E22+F22-G22+J22-K22+L22-M22+N22-O22),0) -> 0 | R22: =MAX((M22-L22+K22-J22+G22-F22+E22-D22+O22-N22),0) -> 0 | S22: =B22 -> 503/22 | U22: =+Q22-R22 -> 0
B23: 503/23 | C23: Patents & licences - depreciation on disposals | D23: =SUMIF(TB!$B$9:$E$120,ETB!B23,TB!$D$9:$D$120) -> 0 | E23: =SUMIF(TB!$B$9:$E$120,ETB!B23,TB!$E$9:$E$120) -> 0 | L23: =SUMIF(Journal!$C$10:$C$304,ETB!B23,Journal!$E$10:$E$304) -> 0 | M23: =SUMIF(Journal!$C$10:$C$304,ETB!B23,Journal!$F$10:$F$304) -> 0 | Q23: =MAX((D23-E23+F23-G23+J23-K23+L23-M23+N23-O23),0) -> 0 | R23: =MAX((M23-L23+K23-J23+G23-F23+E23-D23+O23-N23),0) -> 0 | S23: =B23 -> 503/23 | U23: =+Q23-R23 -> 0
B24: 504 | C24: Development Cost | D24: =SUMIF(TB!$B$9:$E$120,ETB!B24,TB!$D$9:$D$120) -> 0 | E24: =SUMIF(TB!$B$9:$E$120,ETB!B24,TB!$E$9:$E$120) -> 0 | L24: =SUMIF(Journal!$C$10:$C$304,ETB!B24,Journal!$E$10:$E$304) -> 0 | M24: =SUMIF(Journal!$C$10:$C$304,ETB!B24,Journal!$F$10:$F$304) -> 0 | Q24: =MAX((D24-E24+F24-G24+J24-K24+L24-M24+N24-O24),0) -> 0 | R24: =MAX((M24-L24+K24-J24+G24-F24+E24-D24+O24-N24),0) -> 0 | S24: =B24 -> 504 | U24: =+Q24-R24 -> 0
B25: 504/1 | C25: Development Cost/valuation b/f | D25: =SUMIF(TB!$B$9:$E$120,ETB!B25,TB!$D$9:$D$120) -> 0 | E25: =SUMIF(TB!$B$9:$E$120,ETB!B25,TB!$E$9:$E$120) -> 0 | L25: =SUMIF(Journal!$C$10:$C$304,ETB!B25,Journal!$E$10:$E$304) -> 0 | M25: =SUMIF(Journal!$C$10:$C$304,ETB!B25,Journal!$F$10:$F$304) -> 0 | Q25: =MAX((D25-E25+F25-G25+J25-K25+L25-M25+N25-O25),0) -> 0 | R25: =MAX((M25-L25+K25-J25+G25-F25+E25-D25+O25-N25),0) -> 0 | S25: =B25 -> 504/1 | U25: =+Q25-R25 -> 0
B26: 504/2 | C26: Development - additions | D26: =SUMIF(TB!$B$9:$E$120,ETB!B26,TB!$D$9:$D$120) -> 0 | E26: =SUMIF(TB!$B$9:$E$120,ETB!B26,TB!$E$9:$E$120) -> 0 | L26: =SUMIF(Journal!$C$10:$C$304,ETB!B26,Journal!$E$10:$E$304) -> 0 | M26: =SUMIF(Journal!$C$10:$C$304,ETB!B26,Journal!$F$10:$F$304) -> 0 | Q26: =MAX((D26-E26+F26-G26+J26-K26+L26-M26+N26-O26),0) -> 0 | R26: =MAX((M26-L26+K26-J26+G26-F26+E26-D26+O26-N26),0) -> 0 | S26: =B26 -> 504/2 | U26: =+Q26-R26 -> 0
B27: 504/3 | C27: Development - disposals | D27: =SUMIF(TB!$B$9:$E$120,ETB!B27,TB!$D$9:$D$120) -> 0 | E27: =SUMIF(TB!$B$9:$E$120,ETB!B27,TB!$E$9:$E$120) -> 0 | L27: =SUMIF(Journal!$C$10:$C$304,ETB!B27,Journal!$E$10:$E$304) -> 0 | M27: =SUMIF(Journal!$C$10:$C$304,ETB!B27,Journal!$F$10:$F$304) -> 0 | Q27: =MAX((D27-E27+F27-G27+J27-K27+L27-M27+N27-O27),0) -> 0 | R27: =MAX((M27-L27+K27-J27+G27-F27+E27-D27+O27-N27),0) -> 0 | S27: =B27 -> 504/3 | U27: =+Q27-R27 -> 0
B28: 504/21 | C28: Development - amortisation b/fwd | D28: =SUMIF(TB!$B$9:$E$120,ETB!B28,TB!$D$9:$D$120) -> 0 | E28: =SUMIF(TB!$B$9:$E$120,ETB!B28,TB!$E$9:$E$120) -> 0 | L28: =SUMIF(Journal!$C$10:$C$304,ETB!B28,Journal!$E$10:$E$304) -> 0 | M28: =SUMIF(Journal!$C$10:$C$304,ETB!B28,Journal!$F$10:$F$304) -> 0 | Q28: =MAX((D28-E28+F28-G28+J28-K28+L28-M28+N28-O28),0) -> 0 | R28: =MAX((M28-L28+K28-J28+G28-F28+E28-D28+O28-N28),0) -> 0 | S28: =B28 -> 504/21 | U28: =+Q28-R28 -> 0
B29: 505 | C29: Computer Software | D29: =SUMIF(TB!$B$9:$E$120,ETB!B29,TB!$D$9:$D$120) -> 0 | E29: =SUMIF(TB!$B$9:$E$120,ETB!B29,TB!$E$9:$E$120) -> 0 | L29: =SUMIF(Journal!$C$10:$C$304,ETB!B29,Journal!$E$10:$E$304) -> 0 | M29: =SUMIF(Journal!$C$10:$C$304,ETB!B29,Journal!$F$10:$F$304) -> 0 | Q29: =MAX((D29-E29+F29-G29+J29-K29+L29-M29+N29-O29),0) -> 0 | R29: =MAX((M29-L29+K29-J29+G29-F29+E29-D29+O29-N29),0) -> 0 | S29: =B29 -> 505 | U29: =+Q29-R29 -> 0
B30: 505/1 | C30: Computer Software Cost/valuation b/f | D30: =SUMIF(TB!$B$9:$E$120,ETB!B30,TB!$D$9:$D$120) -> 0 | E30: =SUMIF(TB!$B$9:$E$120,ETB!B30,TB!$E$9:$E$120) -> 0 | L30: =SUMIF(Journal!$C$10:$C$304,ETB!B30,Journal!$E$10:$E$304) -> 0 | M30: =SUMIF(Journal!$C$10:$C$304,ETB!B30,Journal!$F$10:$F$304) -> 0 | Q30: =MAX((D30-E30+F30-G30+J30-K30+L30-M30+N30-O30),0) -> 0 | R30: =MAX((M30-L30+K30-J30+G30-F30+E30-D30+O30-N30),0) -> 0 | S30: =B30 -> 505/1 | U30: =+Q30-R30 -> 0
B31: 505/2 | C31: Intellectual property - additions | D31: =SUMIF(TB!$B$9:$E$120,ETB!B31,TB!$D$9:$D$120) -> 0 | E31: =SUMIF(TB!$B$9:$E$120,ETB!B31,TB!$E$9:$E$120) -> 0 | L31: =SUMIF(Journal!$C$10:$C$304,ETB!B31,Journal!$E$10:$E$304) -> 0 | M31: =SUMIF(Journal!$C$10:$C$304,ETB!B31,Journal!$F$10:$F$304) -> 0 | Q31: =MAX((D31-E31+F31-G31+J31-K31+L31-M31+N31-O31),0) -> 0 | R31: =MAX((M31-L31+K31-J31+G31-F31+E31-D31+O31-N31),0) -> 0 | S31: =B31 -> 505/2 | U31: =+Q31-R31 -> 0
B32: 505/3 | C32: Intellectual property - disposals | D32: =SUMIF(TB!$B$9:$E$120,ETB!B32,TB!$D$9:$D$120) -> 0 | E32: =SUMIF(TB!$B$9:$E$120,ETB!B32,TB!$E$9:$E$120) -> 0 | L32: =SUMIF(Journal!$C$10:$C$304,ETB!B32,Journal!$E$10:$E$304) -> 0 | M32: =SUMIF(Journal!$C$10:$C$304,ETB!B32,Journal!$F$10:$F$304) -> 0 | Q32: =MAX((D32-E32+F32-G32+J32-K32+L32-M32+N32-O32),0) -> 0 | R32: =MAX((M32-L32+K32-J32+G32-F32+E32-D32+O32-N32),0) -> 0 | S32: =B32 -> 505/3 | U32: =+Q32-R32 -> 0
B33: 505/21 | C33: Intellectual property - amortisation b/fwd | D33: =SUMIF(TB!$B$9:$E$120,ETB!B33,TB!$D$9:$D$120) -> 0 | E33: =SUMIF(TB!$B$9:$E$120,ETB!B33,TB!$E$9:$E$120) -> 0 | L33: =SUMIF(Journal!$C$10:$C$304,ETB!B33,Journal!$E$10:$E$304) -> 0 | M33: =SUMIF(Journal!$C$10:$C$304,ETB!B33,Journal!$F$10:$F$304) -> 0 | Q33: =MAX((D33-E33+F33-G33+J33-K33+L33-M33+N33-O33),0) -> 0 | R33: =MAX((M33-L33+K33-J33+G33-F33+E33-D33+O33-N33),0) -> 0 | S33: =B33 -> 505/21 | U33: =+Q33-R33 -> 0
B34: 505/22 | C34: Intellectual property - amortisation charge in year | D34: =SUMIF(TB!$B$9:$E$120,ETB!B34,TB!$D$9:$D$120) -> 0 | E34: =SUMIF(TB!$B$9:$E$120,ETB!B34,TB!$E$9:$E$120) -> 0 | L34: =SUMIF(Journal!$C$10:$C$304,ETB!B34,Journal!$E$10:$E$304) -> 0 | M34: =SUMIF(Journal!$C$10:$C$304,ETB!B34,Journal!$F$10:$F$304) -> 0 | Q34: =MAX((D34-E34+F34-G34+J34-K34+L34-M34+N34-O34),0) -> 0 | R34: =MAX((M34-L34+K34-J34+G34-F34+E34-D34+O34-N34),0) -> 0 | S34: =B34 -> 505/22 | U34: =+Q34-R34 -> 0
B35: 505/23 | C35: Intellectual property - amortisation on disposals | D35: =SUMIF(TB!$B$9:$E$120,ETB!B35,TB!$D$9:$D$120) -> 0 | E35: =SUMIF(TB!$B$9:$E$120,ETB!B35,TB!$E$9:$E$120) -> 0 | L35: =SUMIF(Journal!$C$10:$C$304,ETB!B35,Journal!$E$10:$E$304) -> 0 | M35: =SUMIF(Journal!$C$10:$C$304,ETB!B35,Journal!$F$10:$F$304) -> 0 | Q35: =MAX((D35-E35+F35-G35+J35-K35+L35-M35+N35-O35),0) -> 0 | R35: =MAX((M35-L35+K35-J35+G35-F35+E35-D35+O35-N35),0) -> 0 | S35: =B35 -> 505/23 | U35: =+Q35-R35 -> 0
B36: 512 | C36: Freehold Property | D36: =SUMIF(TB!$B$9:$E$120,ETB!B36,TB!$D$9:$D$120) -> 0 | E36: =SUMIF(TB!$B$9:$E$120,ETB!B36,TB!$E$9:$E$120) -> 0 | L36: =SUMIF(Journal!$C$10:$C$304,ETB!B36,Journal!$E$10:$E$304) -> 0 | M36: =SUMIF(Journal!$C$10:$C$304,ETB!B36,Journal!$F$10:$F$304) -> 0 | Q36: =MAX((D36-E36+F36-G36+J36-K36+L36-M36+N36-O36),0) -> 0 | R36: =MAX((M36-L36+K36-J36+G36-F36+E36-D36+O36-N36),0) -> 0 | S36: =B36 -> 512 | U36: =+Q36-R36 -> 0
B37: 512/1 | C37: Freehold Property Cost/valuation b/f | D37: =SUMIF(TB!$B$9:$E$120,ETB!B37,TB!$D$9:$D$120) -> 0 | E37: =SUMIF(TB!$B$9:$E$120,ETB!B37,TB!$E$9:$E$120) -> 0 | L37: =SUMIF(Journal!$C$10:$C$304,ETB!B37,Journal!$E$10:$E$304) -> 0 | M37: =SUMIF(Journal!$C$10:$C$304,ETB!B37,Journal!$F$10:$F$304) -> 0 | Q37: =MAX((D37-E37+F37-G37+J37-K37+L37-M37+N37-O37),0) -> 0 | R37: =MAX((M37-L37+K37-J37+G37-F37+E37-D37+O37-N37),0) -> 0 | S37: =B37 -> 512/1 | U37: =+Q37-R37 -> 0
B38: 512/2 | C38: Freehold Property - Additions | D38: =SUMIF(TB!$B$9:$E$120,ETB!B38,TB!$D$9:$D$120) -> 0 | E38: =SUMIF(TB!$B$9:$E$120,ETB!B38,TB!$E$9:$E$120) -> 0 | L38: =SUMIF(Journal!$C$10:$C$304,ETB!B38,Journal!$E$10:$E$304) -> 0 | M38: =SUMIF(Journal!$C$10:$C$304,ETB!B38,Journal!$F$10:$F$304) -> 0 | Q38: =MAX((D38-E38+F38-G38+J38-K38+L38-M38+N38-O38),0) -> 0 | R38: =MAX((M38-L38+K38-J38+G38-F38+E38-D38+O38-N38),0) -> 0 | S38: =B38 -> 512/2 | U38: =+Q38-R38 -> 0
B39: 512/3 | C39: Freehold Property - Disposals | D39: =SUMIF(TB!$B$9:$E$120,ETB!B39,TB!$D$9:$D$120) -> 0 | E39: =SUMIF(TB!$B$9:$E$120,ETB!B39,TB!$E$9:$E$120) -> 0 | L39: =SUMIF(Journal!$C$10:$C$304,ETB!B39,Journal!$E$10:$E$304) -> 0 | M39: =SUMIF(Journal!$C$10:$C$304,ETB!B39,Journal!$F$10:$F$304) -> 0 | Q39: =MAX((D39-E39+F39-G39+J39-K39+L39-M39+N39-O39),0) -> 0 | R39: =MAX((M39-L39+K39-J39+G39-F39+E39-D39+O39-N39),0) -> 0 | S39: =B39 -> 512/3 | U39: =+Q39-R39 -> 0
B40: 512/21 | C40: Freehold Property - Depreciation b/fwd | D40: =SUMIF(TB!$B$9:$E$120,ETB!B40,TB!$D$9:$D$120) -> 0 | E40: =SUMIF(TB!$B$9:$E$120,ETB!B40,TB!$E$9:$E$120) -> 0 | L40: =SUMIF(Journal!$C$10:$C$304,ETB!B40,Journal!$E$10:$E$304) -> 0 | M40: =SUMIF(Journal!$C$10:$C$304,ETB!B40,Journal!$F$10:$F$304) -> 0 | Q40: =MAX((D40-E40+F40-G40+J40-K40+L40-M40+N40-O40),0) -> 0 | R40: =MAX((M40-L40+K40-J40+G40-F40+E40-D40+O40-N40),0) -> 0 | S40: =B40 -> 512/21 | U40: =+Q40-R40 -> 0
B41: 512/22 | C41: Freehold Property - Charge for year | D41: =SUMIF(TB!$B$9:$E$120,ETB!B41,TB!$D$9:$D$120) -> 0 | E41: =SUMIF(TB!$B$9:$E$120,ETB!B41,TB!$E$9:$E$120) -> 0 | L41: =SUMIF(Journal!$C$10:$C$304,ETB!B41,Journal!$E$10:$E$304) -> 0 | M41: =SUMIF(Journal!$C$10:$C$304,ETB!B41,Journal!$F$10:$F$304) -> 0 | Q41: =MAX((D41-E41+F41-G41+J41-K41+L41-M41+N41-O41),0) -> 0 | R41: =MAX((M41-L41+K41-J41+G41-F41+E41-D41+O41-N41),0) -> 0 | S41: =B41 -> 512/22 | U41: =+Q41-R41 -> 0
B42: 512/23 | C42: Freehold Property - Eliminated on disposals | D42: =SUMIF(TB!$B$9:$E$120,ETB!B42,TB!$D$9:$D$120) -> 0 | E42: =SUMIF(TB!$B$9:$E$120,ETB!B42,TB!$E$9:$E$120) -> 0 | L42: =SUMIF(Journal!$C$10:$C$304,ETB!B42,Journal!$E$10:$E$304) -> 0 | M42: =SUMIF(Journal!$C$10:$C$304,ETB!B42,Journal!$F$10:$F$304) -> 0 | Q42: =MAX((D42-E42+F42-G42+J42-K42+L42-M42+N42-O42),0) -> 0 | R42: =MAX((M42-L42+K42-J42+G42-F42+E42-D42+O42-N42),0) -> 0 | S42: =B42 -> 512/23 | U42: =+Q42-R42 -> 0
B43: 513 | C43: Short leasehold | D43: =SUMIF(TB!$B$9:$E$120,ETB!B43,TB!$D$9:$D$120) -> 0 | E43: =SUMIF(TB!$B$9:$E$120,ETB!B43,TB!$E$9:$E$120) -> 0 | L43: =SUMIF(Journal!$C$10:$C$304,ETB!B43,Journal!$E$10:$E$304) -> 0 | M43: =SUMIF(Journal!$C$10:$C$304,ETB!B43,Journal!$F$10:$F$304) -> 0 | Q43: =MAX((D43-E43+F43-G43+J43-K43+L43-M43+N43-O43),0) -> 0 | R43: =MAX((M43-L43+K43-J43+G43-F43+E43-D43+O43-N43),0) -> 0 | S43: =B43 -> 513 | U43: =+Q43-R43 -> 0
B44: 513/1 | C44: Short leasehold Cost/valuation b/f | D44: =SUMIF(TB!$B$9:$E$120,ETB!B44,TB!$D$9:$D$120) -> 0 | E44: =SUMIF(TB!$B$9:$E$120,ETB!B44,TB!$E$9:$E$120) -> 0 | L44: =SUMIF(Journal!$C$10:$C$304,ETB!B44,Journal!$E$10:$E$304) -> 0 | M44: =SUMIF(Journal!$C$10:$C$304,ETB!B44,Journal!$F$10:$F$304) -> 0 | Q44: =MAX((D44-E44+F44-G44+J44-K44+L44-M44+N44-O44),0) -> 0 | R44: =MAX((M44-L44+K44-J44+G44-F44+E44-D44+O44-N44),0) -> 0 | S44: =B44 -> 513/1 | U44: =+Q44-R44 -> 0
B45: 514 | C45: Land and property leasehold - cost | D45: =SUMIF(TB!$B$9:$E$120,ETB!B45,TB!$D$9:$D$120) -> 0 | E45: =SUMIF(TB!$B$9:$E$120,ETB!B45,TB!$E$9:$E$120) -> 0 | L45: =SUMIF(Journal!$C$10:$C$304,ETB!B45,Journal!$E$10:$E$304) -> 0 | M45: =SUMIF(Journal!$C$10:$C$304,ETB!B45,Journal!$F$10:$F$304) -> 0 | Q45: =MAX((D45-E45+F45-G45+J45-K45+L45-M45+N45-O45),0) -> 0 | R45: =MAX((M45-L45+K45-J45+G45-F45+E45-D45+O45-N45),0) -> 0 | S45: =B45 -> 514 | U45: =+Q45-R45 -> 0
B46: 514/1 | C46: Land and property leasehold Cost/valuation b/f | D46: =SUMIF(TB!$B$9:$E$120,ETB!B46,TB!$D$9:$D$120) -> 0 | E46: =SUMIF(TB!$B$9:$E$120,ETB!B46,TB!$E$9:$E$120) -> 0 | L46: =SUMIF(Journal!$C$10:$C$304,ETB!B46,Journal!$E$10:$E$304) -> 0 | M46: =SUMIF(Journal!$C$10:$C$304,ETB!B46,Journal!$F$10:$F$304) -> 0 | Q46: =MAX((D46-E46+F46-G46+J46-K46+L46-M46+N46-O46),0) -> 0 | R46: =MAX((M46-L46+K46-J46+G46-F46+E46-D46+O46-N46),0) -> 0 | S46: =B46 -> 514/1 | U46: =+Q46-R46 -> 0
B47: 514/2 | C47: Land and property leasehold - additions | D47: =SUMIF(TB!$B$9:$E$120,ETB!B47,TB!$D$9:$D$120) -> 0 | E47: =SUMIF(TB!$B$9:$E$120,ETB!B47,TB!$E$9:$E$120) -> 0 | L47: =SUMIF(Journal!$C$10:$C$304,ETB!B47,Journal!$E$10:$E$304) -> 0 | M47: =SUMIF(Journal!$C$10:$C$304,ETB!B47,Journal!$F$10:$F$304) -> 0 | Q47: =MAX((D47-E47+F47-G47+J47-K47+L47-M47+N47-O47),0) -> 0 | R47: =MAX((M47-L47+K47-J47+G47-F47+E47-D47+O47-N47),0) -> 0 | S47: =B47 -> 514/2 | U47: =+Q47-R47 -> 0
B48: 514/3 | C48: Land and property leasehold- disposals | D48: =SUMIF(TB!$B$9:$E$120,ETB!B48,TB!$D$9:$D$120) -> 0 | E48: =SUMIF(TB!$B$9:$E$120,ETB!B48,TB!$E$9:$E$120) -> 0 | L48: =SUMIF(Journal!$C$10:$C$304,ETB!B48,Journal!$E$10:$E$304) -> 0 | M48: =SUMIF(Journal!$C$10:$C$304,ETB!B48,Journal!$F$10:$F$304) -> 0 | Q48: =MAX((D48-E48+F48-G48+J48-K48+L48-M48+N48-O48),0) -> 0 | R48: =MAX((M48-L48+K48-J48+G48-F48+E48-D48+O48-N48),0) -> 0 | S48: =B48 -> 514/3 | U48: =+Q48-R48 -> 0
B49: 514/21 | C49: Land and property leasehold - depreciation b/fwd | D49: =SUMIF(TB!$B$9:$E$120,ETB!B49,TB!$D$9:$D$120) -> 0 | E49: =SUMIF(TB!$B$9:$E$120,ETB!B49,TB!$E$9:$E$120) -> 0 | L49: =SUMIF(Journal!$C$10:$C$304,ETB!B49,Journal!$E$10:$E$304) -> 0 | M49: =SUMIF(Journal!$C$10:$C$304,ETB!B49,Journal!$F$10:$F$304) -> 0 | Q49: =MAX((D49-E49+F49-G49+J49-K49+L49-M49+N49-O49),0) -> 0 | R49: =MAX((M49-L49+K49-J49+G49-F49+E49-D49+O49-N49),0) -> 0 | S49: =B49 -> 514/21 | U49: =+Q49-R49 -> 0
B50: 514/22 | C50: Land and property leasehold - depreciation charge in year | D50: =SUMIF(TB!$B$9:$E$120,ETB!B50,TB!$D$9:$D$120) -> 0 | E50: =SUMIF(TB!$B$9:$E$120,ETB!B50,TB!$E$9:$E$120) -> 0 | L50: =SUMIF(Journal!$C$10:$C$304,ETB!B50,Journal!$E$10:$E$304) -> 0 | M50: =SUMIF(Journal!$C$10:$C$304,ETB!B50,Journal!$F$10:$F$304) -> 0 | Q50: =MAX((D50-E50+F50-G50+J50-K50+L50-M50+N50-O50),0) -> 0 | R50: =MAX((M50-L50+K50-J50+G50-F50+E50-D50+O50-N50),0) -> 0 | S50: =B50 -> 514/22 | U50: =+Q50-R50 -> 0
B51: 514/23 | C51: Land and property leasehold - depreciation on disposals | D51: =SUMIF(TB!$B$9:$E$120,ETB!B51,TB!$D$9:$D$120) -> 0 | E51: =SUMIF(TB!$B$9:$E$120,ETB!B51,TB!$E$9:$E$120) -> 0 | L51: =SUMIF(Journal!$C$10:$C$304,ETB!B51,Journal!$E$10:$E$304) -> 0 | M51: =SUMIF(Journal!$C$10:$C$304,ETB!B51,Journal!$F$10:$F$304) -> 0 | Q51: =MAX((D51-E51+F51-G51+J51-K51+L51-M51+N51-O51),0) -> 0 | R51: =MAX((M51-L51+K51-J51+G51-F51+E51-D51+O51-N51),0) -> 0 | S51: =B51 -> 514/23 | U51: =+Q51-R51 -> 0
B52: 522 | C52: Improvement to properties | D52: =SUMIF(TB!$B$9:$E$120,ETB!B52,TB!$D$9:$D$120) -> 0 | E52: =SUMIF(TB!$B$9:$E$120,ETB!B52,TB!$E$9:$E$120) -> 0 | L52: =SUMIF(Journal!$C$10:$C$304,ETB!B52,Journal!$E$10:$E$304) -> 0 | M52: =SUMIF(Journal!$C$10:$C$304,ETB!B52,Journal!$F$10:$F$304) -> 0 | Q52: =MAX((D52-E52+F52-G52+J52-K52+L52-M52+N52-O52),0) -> 0 | R52: =MAX((M52-L52+K52-J52+G52-F52+E52-D52+O52-N52),0) -> 0 | S52: =B52 -> 522 | U52: =+Q52-R52 -> 0
B53: 522/1 | C53: Improvement to properties Cost/valuation b/f | D53: =SUMIF(TB!$B$9:$E$120,ETB!B53,TB!$D$9:$D$120) -> 0 | E53: =SUMIF(TB!$B$9:$E$120,ETB!B53,TB!$E$9:$E$120) -> 0 | L53: =SUMIF(Journal!$C$10:$C$304,ETB!B53,Journal!$E$10:$E$304) -> 0 | M53: =SUMIF(Journal!$C$10:$C$304,ETB!B53,Journal!$F$10:$F$304) -> 0 | Q53: =MAX((D53-E53+F53-G53+J53-K53+L53-M53+N53-O53),0) -> 0 | R53: =MAX((M53-L53+K53-J53+G53-F53+E53-D53+O53-N53),0) -> 0 | S53: =B53 -> 522/1 | U53: =+Q53-R53 -> 0
B54: 522/2 | C54: Improvement to properties - additions | D54: =SUMIF(TB!$B$9:$E$120,ETB!B54,TB!$D$9:$D$120) -> 0 | E54: =SUMIF(TB!$B$9:$E$120,ETB!B54,TB!$E$9:$E$120) -> 0 | L54: =SUMIF(Journal!$C$10:$C$304,ETB!B54,Journal!$E$10:$E$304) -> 0 | M54: =SUMIF(Journal!$C$10:$C$304,ETB!B54,Journal!$F$10:$F$304) -> 0 | Q54: =MAX((D54-E54+F54-G54+J54-K54+L54-M54+N54-O54),0) -> 0 | R54: =MAX((M54-L54+K54-J54+G54-F54+E54-D54+O54-N54),0) -> 0 | S54: =B54 -> 522/2 | U54: =+Q54-R54 -> 0
B55: 522/3 | C55: Improvement to properties - disposals | D55: =SUMIF(TB!$B$9:$E$120,ETB!B55,TB!$D$9:$D$120) -> 0 | E55: =SUMIF(TB!$B$9:$E$120,ETB!B55,TB!$E$9:$E$120) -> 0 | L55: =SUMIF(Journal!$C$10:$C$304,ETB!B55,Journal!$E$10:$E$304) -> 0 | M55: =SUMIF(Journal!$C$10:$C$304,ETB!B55,Journal!$F$10:$F$304) -> 0 | Q55: =MAX((D55-E55+F55-G55+J55-K55+L55-M55+N55-O55),0) -> 0 | R55: =MAX((M55-L55+K55-J55+G55-F55+E55-D55+O55-N55),0) -> 0 | S55: =B55 -> 522/3 | U55: =+Q55-R55 -> 0
B56: 522/21 | C56: Improvement to properties - depreciation b/fwd | D56: =SUMIF(TB!$B$9:$E$120,ETB!B56,TB!$D$9:$D$120) -> 0 | E56: =SUMIF(TB!$B$9:$E$120,ETB!B56,TB!$E$9:$E$120) -> 0 | L56: =SUMIF(Journal!$C$10:$C$304,ETB!B56,Journal!$E$10:$E$304) -> 0 | M56: =SUMIF(Journal!$C$10:$C$304,ETB!B56,Journal!$F$10:$F$304) -> 0 | Q56: =MAX((D56-E56+F56-G56+J56-K56+L56-M56+N56-O56),0) -> 0 | R56: =MAX((M56-L56+K56-J56+G56-F56+E56-D56+O56-N56),0) -> 0 | S56: =B56 -> 522/21 | U56: =+Q56-R56 -> 0
B57: 522/22 | C57: Improvement to properties - depreciation charge in year | D57: =SUMIF(TB!$B$9:$E$120,ETB!B57,TB!$D$9:$D$120) -> 0 | E57: =SUMIF(TB!$B$9:$E$120,ETB!B57,TB!$E$9:$E$120) -> 0 | L57: =SUMIF(Journal!$C$10:$C$304,ETB!B57,Journal!$E$10:$E$304) -> 0 | M57: =SUMIF(Journal!$C$10:$C$304,ETB!B57,Journal!$F$10:$F$304) -> 0 | Q57: =MAX((D57-E57+F57-G57+J57-K57+L57-M57+N57-O57),0) -> 0 | R57: =MAX((M57-L57+K57-J57+G57-F57+E57-D57+O57-N57),0) -> 0 | S57: =B57 -> 522/22 | U57: =+Q57-R57 -> 0
B58: 522/23 | C58: Improvement to properties - depreciation on disposals | D58: =SUMIF(TB!$B$9:$E$120,ETB!B58,TB!$D$9:$D$120) -> 0 | E58: =SUMIF(TB!$B$9:$E$120,ETB!B58,TB!$E$9:$E$120) -> 0 | L58: =SUMIF(Journal!$C$10:$C$304,ETB!B58,Journal!$E$10:$E$304) -> 0 | M58: =SUMIF(Journal!$C$10:$C$304,ETB!B58,Journal!$F$10:$F$304) -> 0 | Q58: =MAX((D58-E58+F58-G58+J58-K58+L58-M58+N58-O58),0) -> 0 | R58: =MAX((M58-L58+K58-J58+G58-F58+E58-D58+O58-N58),0) -> 0 | S58: =B58 -> 522/23 | U58: =+Q58-R58 -> 0
B59: 523 | C59: Plant & Machin | D59: =SUMIF(TB!$B$9:$E$120,ETB!B59,TB!$D$9:$D$120) -> 0 | E59: =SUMIF(TB!$B$9:$E$120,ETB!B59,TB!$E$9:$E$120) -> 0 | L59: =SUMIF(Journal!$C$10:$C$304,ETB!B59,Journal!$E$10:$E$304) -> 0 | M59: =SUMIF(Journal!$C$10:$C$304,ETB!B59,Journal!$F$10:$F$304) -> 0 | Q59: =MAX((D59-E59+F59-G59+J59-K59+L59-M59+N59-O59),0) -> 0 | R59: =MAX((M59-L59+K59-J59+G59-F59+E59-D59+O59-N59),0) -> 0 | S59: =B59 -> 523 | U59: =+Q59-R59 -> 0
B60: 523/1 | C60: Plant & Machin Cost/valuation b/f | D60: =SUMIF(TB!$B$9:$E$120,ETB!B60,TB!$D$9:$D$120) -> 0 | E60: =SUMIF(TB!$B$9:$E$120,ETB!B60,TB!$E$9:$E$120) -> 0 | L60: =SUMIF(Journal!$C$10:$C$304,ETB!B60,Journal!$E$10:$E$304) -> 0 | M60: =SUMIF(Journal!$C$10:$C$304,ETB!B60,Journal!$F$10:$F$304) -> 0 | Q60: =MAX((D60-E60+F60-G60+J60-K60+L60-M60+N60-O60),0) -> 0 | R60: =MAX((M60-L60+K60-J60+G60-F60+E60-D60+O60-N60),0) -> 0 | S60: =B60 -> 523/1 | U60: =+Q60-R60 -> 0
B61: 523/2 | C61: Plant & Machin - Additions | D61: =SUMIF(TB!$B$9:$E$120,ETB!B61,TB!$D$9:$D$120) -> 0 | E61: =SUMIF(TB!$B$9:$E$120,ETB!B61,TB!$E$9:$E$120) -> 0 | L61: =SUMIF(Journal!$C$10:$C$304,ETB!B61,Journal!$E$10:$E$304) -> 0 | M61: =SUMIF(Journal!$C$10:$C$304,ETB!B61,Journal!$F$10:$F$304) -> 0 | Q61: =MAX((D61-E61+F61-G61+J61-K61+L61-M61+N61-O61),0) -> 0 | R61: =MAX((M61-L61+K61-J61+G61-F61+E61-D61+O61-N61),0) -> 0 | S61: =B61 -> 523/2 | U61: =+Q61-R61 -> 0
B62: 523/3 | C62: Plant & Machin - Disposals | D62: =SUMIF(TB!$B$9:$E$120,ETB!B62,TB!$D$9:$D$120) -> 0 | E62: =SUMIF(TB!$B$9:$E$120,ETB!B62,TB!$E$9:$E$120) -> 0 | L62: =SUMIF(Journal!$C$10:$C$304,ETB!B62,Journal!$E$10:$E$304) -> 0 | M62: =SUMIF(Journal!$C$10:$C$304,ETB!B62,Journal!$F$10:$F$304) -> 0 | Q62: =MAX((D62-E62+F62-G62+J62-K62+L62-M62+N62-O62),0) -> 0 | R62: =MAX((M62-L62+K62-J62+G62-F62+E62-D62+O62-N62),0) -> 0 | S62: =B62 -> 523/3 | U62: =+Q62-R62 -> 0
B63: 523/21 | C63: Plant & Machin - Depreciation b/fwd | D63: =SUMIF(TB!$B$9:$E$120,ETB!B63,TB!$D$9:$D$120) -> 0 | E63: =SUMIF(TB!$B$9:$E$120,ETB!B63,TB!$E$9:$E$120) -> 0 | L63: =SUMIF(Journal!$C$10:$C$304,ETB!B63,Journal!$E$10:$E$304) -> 0 | M63: =SUMIF(Journal!$C$10:$C$304,ETB!B63,Journal!$F$10:$F$304) -> 0 | Q63: =MAX((D63-E63+F63-G63+J63-K63+L63-M63+N63-O63),0) -> 0 | R63: =MAX((M63-L63+K63-J63+G63-F63+E63-D63+O63-N63),0) -> 0 | S63: =B63 -> 523/21 | U63: =+Q63-R63 -> 0
B64: 523/22 | C64: Plant & Machin - Charge for year | D64: =SUMIF(TB!$B$9:$E$120,ETB!B64,TB!$D$9:$D$120) -> 0 | E64: =SUMIF(TB!$B$9:$E$120,ETB!B64,TB!$E$9:$E$120) -> 0 | L64: =SUMIF(Journal!$C$10:$C$304,ETB!B64,Journal!$E$10:$E$304) -> 0 | M64: =SUMIF(Journal!$C$10:$C$304,ETB!B64,Journal!$F$10:$F$304) -> 0 | Q64: =MAX((D64-E64+F64-G64+J64-K64+L64-M64+N64-O64),0) -> 0 | R64: =MAX((M64-L64+K64-J64+G64-F64+E64-D64+O64-N64),0) -> 0 | S64: =B64 -> 523/22 | U64: =+Q64-R64 -> 0
B65: 523/23 | C65: Plant & Machin - Eliminated on disposals | D65: =SUMIF(TB!$B$9:$E$120,ETB!B65,TB!$D$9:$D$120) -> 0 | E65: =SUMIF(TB!$B$9:$E$120,ETB!B65,TB!$E$9:$E$120) -> 0 | L65: =SUMIF(Journal!$C$10:$C$304,ETB!B65,Journal!$E$10:$E$304) -> 0 | M65: =SUMIF(Journal!$C$10:$C$304,ETB!B65,Journal!$F$10:$F$304) -> 0 | Q65: =MAX((D65-E65+F65-G65+J65-K65+L65-M65+N65-O65),0) -> 0 | R65: =MAX((M65-L65+K65-J65+G65-F65+E65-D65+O65-N65),0) -> 0 | S65: =B65 -> 523/23 | U65: =+Q65-R65 -> 0
B66: 524 | C66: Fixtures & fittings | D66: =SUMIF(TB!$B$9:$E$120,ETB!B66,TB!$D$9:$D$120) -> 0 | E66: =SUMIF(TB!$B$9:$E$120,ETB!B66,TB!$E$9:$E$120) -> 0 | L66: =SUMIF(Journal!$C$10:$C$304,ETB!B66,Journal!$E$10:$E$304) -> 0 | M66: =SUMIF(Journal!$C$10:$C$304,ETB!B66,Journal!$F$10:$F$304) -> 0 | Q66: =MAX((D66-E66+F66-G66+J66-K66+L66-M66+N66-O66+H66-I66),0) -> 0 | R66: =MAX((M66-L66+K66-J66+G66-F66+E66-D66+O66-N66-H66+I66),0) -> 0 | S66: =B66 -> 524 | U66: =+Q66-R66 -> 0
B67: 524/1 | C67: Fixtures & fittings Cost/valuation b/f | D67: =SUMIF(TB!$B$9:$E$120,ETB!B67,TB!$D$9:$D$120) -> 0 | E67: =SUMIF(TB!$B$9:$E$120,ETB!B67,TB!$E$9:$E$120) -> 0 | L67: =SUMIF(Journal!$C$10:$C$304,ETB!B67,Journal!$E$10:$E$304) -> 0 | M67: =SUMIF(Journal!$C$10:$C$304,ETB!B67,Journal!$F$10:$F$304) -> 0 | Q67: =MAX((D67-E67+F67-G67+J67-K67+L67-M67+N67-O67+H67-I67),0) -> 0 | R67: =MAX((M67-L67+K67-J67+G67-F67+E67-D67+O67-N67-H67+I67),0) -> 0 | S67: =B67 -> 524/1 | U67: =+Q67-R67 -> 0
B68: 524/2 | C68: Fixtures & fittings - Additions | D68: =SUMIF(TB!$B$9:$E$120,ETB!B68,TB!$D$9:$D$120) -> 0 | E68: =SUMIF(TB!$B$9:$E$120,ETB!B68,TB!$E$9:$E$120) -> 0 | J68: ='PDB Expense'!AQ1312 -> 599 | L68: =SUMIF(Journal!$C$10:$C$304,ETB!B68,Journal!$E$10:$E$304) -> 0 | M68: =SUMIF(Journal!$C$10:$C$304,ETB!B68,Journal!$F$10:$F$304) -> 0 | Q68: =MAX((D68-E68+F68-G68+J68-K68+L68-M68+N68-O68+H68-I68),0) -> 599 | R68: =MAX((M68-L68+K68-J68+G68-F68+E68-D68+O68-N68-H68+I68),0) -> 0 | S68: =B68 -> 524/2 | U68: =+Q68-R68 -> 599
B69: 524/3 | C69: Fixtures & fittings - Disposals | D69: =SUMIF(TB!$B$9:$E$120,ETB!B69,TB!$D$9:$D$120) -> 0 | E69: =SUMIF(TB!$B$9:$E$120,ETB!B69,TB!$E$9:$E$120) -> 0 | L69: =SUMIF(Journal!$C$10:$C$304,ETB!B69,Journal!$E$10:$E$304) -> 0 | M69: =SUMIF(Journal!$C$10:$C$304,ETB!B69,Journal!$F$10:$F$304) -> 0 | Q69: =MAX((D69-E69+F69-G69+J69-K69+L69-M69+N69-O69+H69-I69),0) -> 0 | R69: =MAX((M69-L69+K69-J69+G69-F69+E69-D69+O69-N69-H69+I69),0) -> 0 | S69: =B69 -> 524/3 | U69: =+Q69-R69 -> 0
B70: 524/21 | C70: Fixtures & fittings - Depreciation b/fwd | D70: =SUMIF(TB!$B$9:$E$120,ETB!B70,TB!$D$9:$D$120) -> 0 | E70: =SUMIF(TB!$B$9:$E$120,ETB!B70,TB!$E$9:$E$120) -> 0 | L70: =SUMIF(Journal!$C$10:$C$304,ETB!B70,Journal!$E$10:$E$304) -> 0 | M70: =SUMIF(Journal!$C$10:$C$304,ETB!B70,Journal!$F$10:$F$304) -> 0 | Q70: =MAX((D70-E70+F70-G70+J70-K70+L70-M70+N70-O70+H70-I70),0) -> 0 | R70: =MAX((M70-L70+K70-J70+G70-F70+E70-D70+O70-N70-H70+I70),0) -> 0 | S70: =B70 -> 524/21 | U70: =+Q70-R70 -> 0
B71: 524/22 | C71: Fixtures & fittings - Charge for year | D71: =SUMIF(TB!$B$9:$E$120,ETB!B71,TB!$D$9:$D$120) -> 0 | E71: =SUMIF(TB!$B$9:$E$120,ETB!B71,TB!$E$9:$E$120) -> 0 | L71: =SUMIF(Journal!$C$10:$C$304,ETB!B71,Journal!$E$10:$E$304) -> 0 | M71: =SUMIF(Journal!$C$10:$C$304,ETB!B71,Journal!$F$10:$F$304) -> 89.85 | Q71: =MAX((D71-E71+F71-G71+J71-K71+L71-M71+N71-O71+H71-I71),0) -> 0 | R71: =MAX((M71-L71+K71-J71+G71-F71+E71-D71+O71-N71-H71+I71),0) -> 89.85 | S71: =B71 -> 524/22 | U71: =+Q71-R71 -> -89.85
B72: 524/23 | C72: Fixtures & fittings - Eliminated on disposals | D72: =SUMIF(TB!$B$9:$E$120,ETB!B72,TB!$D$9:$D$120) -> 0 | E72: =SUMIF(TB!$B$9:$E$120,ETB!B72,TB!$E$9:$E$120) -> 0 | L72: =SUMIF(Journal!$C$10:$C$304,ETB!B72,Journal!$E$10:$E$304) -> 0 | M72: =SUMIF(Journal!$C$10:$C$304,ETB!B72,Journal!$F$10:$F$304) -> 0 | Q72: =MAX((D72-E72+F72-G72+J72-K72+L72-M72+N72-O72+H72-I72),0) -> 0 | R72: =MAX((M72-L72+K72-J72+G72-F72+E72-D72+O72-N72-H72+I72),0) -> 0 | S72: =B72 -> 524/23 | U72: =+Q72-R72 -> 0
B73: 525 | C73: Motor vehicles | D73: =SUMIF(TB!$B$9:$E$120,ETB!B73,TB!$D$9:$D$120) -> 0 | E73: =SUMIF(TB!$B$9:$E$120,ETB!B73,TB!$E$9:$E$120) -> 0 | L73: =SUMIF(Journal!$C$10:$C$304,ETB!B73,Journal!$E$10:$E$304) -> 0 | M73: =SUMIF(Journal!$C$10:$C$304,ETB!B73,Journal!$F$10:$F$304) -> 0 | Q73: =MAX((D73-E73+F73-G73+J73-K73+L73-M73+N73-O73+H73-I73),0) -> 0 | R73: =MAX((M73-L73+K73-J73+G73-F73+E73-D73+O73-N73-H73+I73),0) -> 0 | S73: =B73 -> 525 | U73: =+Q73-R73 -> 0
B74: 525/1 | C74: Motor vehicles Cost/valuation b/f | D74: =SUMIF(TB!$B$9:$E$120,ETB!B74,TB!$D$9:$D$120) -> 0 | E74: =SUMIF(TB!$B$9:$E$120,ETB!B74,TB!$E$9:$E$120) -> 0 | L74: =SUMIF(Journal!$C$10:$C$304,ETB!B74,Journal!$E$10:$E$304) -> 0 | M74: =SUMIF(Journal!$C$10:$C$304,ETB!B74,Journal!$F$10:$F$304) -> 0 | Q74: =MAX((D74-E74+F74-G74+J74-K74+L74-M74+N74-O74+H74-I74),0) -> 0 | R74: =MAX((M74-L74+K74-J74+G74-F74+E74-D74+O74-N74-H74+I74),0) -> 0 | S74: =B74 -> 525/1 | U74: =+Q74-R74 -> 0
B75: 525/2 | C75: Motor vehicles - Additions | D75: =SUMIF(TB!$B$9:$E$120,ETB!B75,TB!$D$9:$D$120) -> 0 | E75: =SUMIF(TB!$B$9:$E$120,ETB!B75,TB!$E$9:$E$120) -> 0 | L75: =SUMIF(Journal!$C$10:$C$304,ETB!B75,Journal!$E$10:$E$304) -> 0 | M75: =SUMIF(Journal!$C$10:$C$304,ETB!B75,Journal!$F$10:$F$304) -> 0 | Q75: =MAX((D75-E75+F75-G75+J75-K75+L75-M75+N75-O75+H75-I75),0) -> 0 | R75: =MAX((M75-L75+K75-J75+G75-F75+E75-D75+O75-N75-H75+I75),0) -> 0 | S75: =B75 -> 525/2 | U75: =+Q75-R75 -> 0
B76: 525/3 | C76: Motor vehicles - Disposals | D76: =SUMIF(TB!$B$9:$E$120,ETB!B76,TB!$D$9:$D$120) -> 0 | E76: =SUMIF(TB!$B$9:$E$120,ETB!B76,TB!$E$9:$E$120) -> 0 | L76: =SUMIF(Journal!$C$10:$C$304,ETB!B76,Journal!$E$10:$E$304) -> 0 | M76: =SUMIF(Journal!$C$10:$C$304,ETB!B76,Journal!$F$10:$F$304) -> 0 | Q76: =MAX((D76-E76+F76-G76+J76-K76+L76-M76+N76-O76+H76-I76),0) -> 0 | R76: =MAX((M76-L76+K76-J76+G76-F76+E76-D76+O76-N76-H76+I76),0) -> 0 | S76: =B76 -> 525/3 | U76: =+Q76-R76 -> 0
B77: 525/21 | C77: Motor vehicles - Depreciation b/fwd | D77: =SUMIF(TB!$B$9:$E$120,ETB!B77,TB!$D$9:$D$120) -> 0 | E77: =SUMIF(TB!$B$9:$E$120,ETB!B77,TB!$E$9:$E$120) -> 0 | L77: =SUMIF(Journal!$C$10:$C$304,ETB!B77,Journal!$E$10:$E$304) -> 0 | M77: =SUMIF(Journal!$C$10:$C$304,ETB!B77,Journal!$F$10:$F$304) -> 0 | Q77: =MAX((D77-E77+F77-G77+J77-K77+L77-M77+N77-O77+H77-I77),0) -> 0 | R77: =MAX((M77-L77+K77-J77+G77-F77+E77-D77+O77-N77-H77+I77),0) -> 0 | S77: =B77 -> 525/21 | U77: =+Q77-R77 -> 0
B78: 525/22 | C78: Motor vehicles - Charge for year | D78: =SUMIF(TB!$B$9:$E$120,ETB!B78,TB!$D$9:$D$120) -> 0 | E78: =SUMIF(TB!$B$9:$E$120,ETB!B78,TB!$E$9:$E$120) -> 0 | L78: =SUMIF(Journal!$C$10:$C$304,ETB!B78,Journal!$E$10:$E$304) -> 0 | M78: =SUMIF(Journal!$C$10:$C$304,ETB!B78,Journal!$F$10:$F$304) -> 0 | Q78: =MAX((D78-E78+F78-G78+J78-K78+L78-M78+N78-O78+H78-I78),0) -> 0 | R78: =MAX((M78-L78+K78-J78+G78-F78+E78-D78+O78-N78-H78+I78),0) -> 0 | S78: =B78 -> 525/22 | U78: =+Q78-R78 -> 0
B79: 525/23 | C79: Motor vehicles - Eliminated on disposals | D79: =SUMIF(TB!$B$9:$E$120,ETB!B79,TB!$D$9:$D$120) -> 0 | E79: =SUMIF(TB!$B$9:$E$120,ETB!B79,TB!$E$9:$E$120) -> 0 | L79: =SUMIF(Journal!$C$10:$C$304,ETB!B79,Journal!$E$10:$E$304) -> 0 | M79: =SUMIF(Journal!$C$10:$C$304,ETB!B79,Journal!$F$10:$F$304) -> 0 | Q79: =MAX((D79-E79+F79-G79+J79-K79+L79-M79+N79-O79+H79-I79),0) -> 0 | R79: =MAX((M79-L79+K79-J79+G79-F79+E79-D79+O79-N79-H79+I79),0) -> 0 | S79: =B79 -> 525/23 | U79: =+Q79-R79 -> 0
B80: 526 | C80: Computer equipment | D80: =SUMIF(TB!$B$9:$E$120,ETB!B80,TB!$D$9:$D$120) -> 0 | E80: =SUMIF(TB!$B$9:$E$120,ETB!B80,TB!$E$9:$E$120) -> 0 | L80: =SUMIF(Journal!$C$10:$C$304,ETB!B80,Journal!$E$10:$E$304) -> 0 | M80: =SUMIF(Journal!$C$10:$C$304,ETB!B80,Journal!$F$10:$F$304) -> 0 | Q80: =MAX((D80-E80+F80-G80+J80-K80+L80-M80+N80-O80+H80-I80),0) -> 0 | R80: =MAX((M80-L80+K80-J80+G80-F80+E80-D80+O80-N80-H80+I80),0) -> 0 | S80: =B80 -> 526 | U80: =+Q80-R80 -> 0
B81: 526/1 | C81: Computer equipment Cost/valuation b/f | D81: =SUMIF(TB!$B$9:$E$120,ETB!B81,TB!$D$9:$D$120) -> 0 | E81: =SUMIF(TB!$B$9:$E$120,ETB!B81,TB!$E$9:$E$120) -> 0 | L81: =SUMIF(Journal!$C$10:$C$304,ETB!B81,Journal!$E$10:$E$304) -> 0 | M81: =SUMIF(Journal!$C$10:$C$304,ETB!B81,Journal!$F$10:$F$304) -> 0 | Q81: =MAX((D81-E81+F81-G81+J81-K81+L81-M81+N81-O81+H81-I81),0) -> 0 | R81: =MAX((M81-L81+K81-J81+G81-F81+E81-D81+O81-N81-H81+I81),0) -> 0 | S81: =B81 -> 526/1 | U81: =+Q81-R81 -> 0
B82: 526/2 | C82: Computer equipment - Additions | D82: =SUMIF(TB!$B$9:$E$120,ETB!B82,TB!$D$9:$D$120) -> 0 | E82: =SUMIF(TB!$B$9:$E$120,ETB!B82,TB!$E$9:$E$120) -> 0 | J82: ='PDB Expense'!AR1312 -> 1653.33 | L82: =SUMIF(Journal!$C$10:$C$304,ETB!B82,Journal!$E$10:$E$304) -> 0 | M82: =SUMIF(Journal!$C$10:$C$304,ETB!B82,Journal!$F$10:$F$304) -> 0 | Q82: =MAX((D82-E82+F82-G82+J82-K82+L82-M82+N82-O82+H82-I82),0) -> 1653.33 | R82: =MAX((M82-L82+K82-J82+G82-F82+E82-D82+O82-N82-H82+I82),0) -> 0 | S82: =B82 -> 526/2 | U82: =+Q82-R82 -> 1653.33
B83: 526/3 | C83: Computer equipment - Disposals | D83: =SUMIF(TB!$B$9:$E$120,ETB!B83,TB!$D$9:$D$120) -> 0 | E83: =SUMIF(TB!$B$9:$E$120,ETB!B83,TB!$E$9:$E$120) -> 0 | L83: =SUMIF(Journal!$C$10:$C$304,ETB!B83,Journal!$E$10:$E$304) -> 0 | M83: =SUMIF(Journal!$C$10:$C$304,ETB!B83,Journal!$F$10:$F$304) -> 0 | Q83: =MAX((D83-E83+F83-G83+J83-K83+L83-M83+N83-O83+H83-I83),0) -> 0 | R83: =MAX((M83-L83+K83-J83+G83-F83+E83-D83+O83-N83-H83+I83),0) -> 0 | S83: =B83 -> 526/3 | U83: =+Q83-R83 -> 0
B84: 526/21 | C84: Computer equipment - Depreciation b/fwd | D84: =SUMIF(TB!$B$9:$E$120,ETB!B84,TB!$D$9:$D$120) -> 0 | E84: =SUMIF(TB!$B$9:$E$120,ETB!B84,TB!$E$9:$E$120) -> 0 | L84: =SUMIF(Journal!$C$10:$C$304,ETB!B84,Journal!$E$10:$E$304) -> 0 | M84: =SUMIF(Journal!$C$10:$C$304,ETB!B84,Journal!$F$10:$F$304) -> 0 | Q84: =MAX((D84-E84+F84-G84+J84-K84+L84-M84+N84-O84+H84-I84),0) -> 0 | R84: =MAX((M84-L84+K84-J84+G84-F84+E84-D84+O84-N84-H84+I84),0) -> 0 | S84: =B84 -> 526/21 | U84: =+Q84-R84 -> 0
B85: 526/22 | C85: Computer equipment - Charge for year | D85: =SUMIF(TB!$B$9:$E$120,ETB!B85,TB!$D$9:$D$120) -> 0 | E85: =SUMIF(TB!$B$9:$E$120,ETB!B85,TB!$E$9:$E$120) -> 0 | L85: =SUMIF(Journal!$C$10:$C$304,ETB!B85,Journal!$E$10:$E$304) -> 0 | M85: =SUMIF(Journal!$C$10:$C$304,ETB!B85,Journal!$F$10:$F$304) -> 82.6665 | Q85: =MAX((D85-E85+F85-G85+J85-K85+L85-M85+N85-O85+H85-I85),0) -> 0 | R85: =MAX((M85-L85+K85-J85+G85-F85+E85-D85+O85-N85-H85+I85),0) -> 82.6665 | S85: =B85 -> 526/22 | U85: =+Q85-R85 -> -82.6665
B86: 526/23 | C86: Computer equipment - Eliminated on disposals | D86: =SUMIF(TB!$B$9:$E$120,ETB!B86,TB!$D$9:$D$120) -> 0 | E86: =SUMIF(TB!$B$9:$E$120,ETB!B86,TB!$E$9:$E$120) -> 0 | L86: =SUMIF(Journal!$C$10:$C$304,ETB!B86,Journal!$E$10:$E$304) -> 0 | M86: =SUMIF(Journal!$C$10:$C$304,ETB!B86,Journal!$F$10:$F$304) -> 0 | Q86: =MAX((D86-E86+F86-G86+J86-K86+L86-M86+N86-O86+H86-I86),0) -> 0 | R86: =MAX((M86-L86+K86-J86+G86-F86+E86-D86+O86-N86-H86+I86),0) -> 0 | S86: =B86 -> 526/23 | U86: =+Q86-R86 -> 0
B87: 542 | C87: Share in grp undertaking | D87: =SUMIF(TB!$B$9:$E$120,ETB!B87,TB!$D$9:$D$120) -> 0 | E87: =SUMIF(TB!$B$9:$E$120,ETB!B87,TB!$E$9:$E$120) -> 0 | L87: =SUMIF(Journal!$C$10:$C$304,ETB!B87,Journal!$E$10:$E$304) -> 0 | M87: =SUMIF(Journal!$C$10:$C$304,ETB!B87,Journal!$F$10:$F$304) -> 0 | Q87: =MAX((D87-E87+F87-G87+J87-K87+L87-M87+N87-O87+H87-I87),0) -> 0 | R87: =MAX((M87-L87+K87-J87+G87-F87+E87-D87+O87-N87-H87+I87),0) -> 0 | S87: =B87 -> 542 | U87: =+Q87-R87 -> 0
B88: 543 | C88: Loan to grp undertaking | D88: =SUMIF(TB!$B$9:$E$120,ETB!B88,TB!$D$9:$D$120) -> 0 | E88: =SUMIF(TB!$B$9:$E$120,ETB!B88,TB!$E$9:$E$120) -> 0 | L88: =SUMIF(Journal!$C$10:$C$304,ETB!B88,Journal!$E$10:$E$304) -> 0 | M88: =SUMIF(Journal!$C$10:$C$304,ETB!B88,Journal!$F$10:$F$304) -> 0 | Q88: =MAX((D88-E88+F88-G88+J88-K88+L88-M88+N88-O88+H88-I88),0) -> 0 | R88: =MAX((M88-L88+K88-J88+G88-F88+E88-D88+O88-N88-H88+I88),0) -> 0 | S88: =B88 -> 543 | U88: =+Q88-R88 -> 0
B89: 548 | C89: Interest in associate | D89: =SUMIF(TB!$B$9:$E$120,ETB!B89,TB!$D$9:$D$120) -> 0 | E89: =SUMIF(TB!$B$9:$E$120,ETB!B89,TB!$E$9:$E$120) -> 0 | L89: =SUMIF(Journal!$C$10:$C$304,ETB!B89,Journal!$E$10:$E$304) -> 0 | M89: =SUMIF(Journal!$C$10:$C$304,ETB!B89,Journal!$F$10:$F$304) -> 0 | Q89: =MAX((D89-E89+F89-G89+J89-K89+L89-M89+N89-O89+H89-I89),0) -> 0 | R89: =MAX((M89-L89+K89-J89+G89-F89+E89-D89+O89-N89-H89+I89),0) -> 0 | S89: =B89 -> 548 | U89: =+Q89-R89 -> 0
B90: 549 | C90: Int in joint venture | D90: =SUMIF(TB!$B$9:$E$120,ETB!B90,TB!$D$9:$D$120) -> 0 | E90: =SUMIF(TB!$B$9:$E$120,ETB!B90,TB!$E$9:$E$120) -> 0 | L90: =SUMIF(Journal!$C$10:$C$304,ETB!B90,Journal!$E$10:$E$304) -> 0 | M90: =SUMIF(Journal!$C$10:$C$304,ETB!B90,Journal!$F$10:$F$304) -> 0 | Q90: =MAX((D90-E90+F90-G90+J90-K90+L90-M90+N90-O90+H90-I90),0) -> 0 | R90: =MAX((M90-L90+K90-J90+G90-F90+E90-D90+O90-N90-H90+I90),0) -> 0 | S90: =B90 -> 549 | U90: =+Q90-R90 -> 0
B91: 550 | C91: Int in other participting | D91: =SUMIF(TB!$B$9:$E$120,ETB!B91,TB!$D$9:$D$120) -> 0 | E91: =SUMIF(TB!$B$9:$E$120,ETB!B91,TB!$E$9:$E$120) -> 0 | L91: =SUMIF(Journal!$C$10:$C$304,ETB!B91,Journal!$E$10:$E$304) -> 0 | M91: =SUMIF(Journal!$C$10:$C$304,ETB!B91,Journal!$F$10:$F$304) -> 0 | Q91: =MAX((D91-E91+F91-G91+J91-K91+L91-M91+N91-O91+H91-I91),0) -> 0 | R91: =MAX((M91-L91+K91-J91+G91-F91+E91-D91+O91-N91-H91+I91),0) -> 0 | S91: =B91 -> 550 | U91: =+Q91-R91 -> 0
B92: 551 | C92: Loans to associates | D92: =SUMIF(TB!$B$9:$E$120,ETB!B92,TB!$D$9:$D$120) -> 0 | E92: =SUMIF(TB!$B$9:$E$120,ETB!B92,TB!$E$9:$E$120) -> 0 | L92: =SUMIF(Journal!$C$10:$C$304,ETB!B92,Journal!$E$10:$E$304) -> 0 | M92: =SUMIF(Journal!$C$10:$C$304,ETB!B92,Journal!$F$10:$F$304) -> 0 | Q92: =MAX((D92-E92+F92-G92+J92-K92+L92-M92+N92-O92+H92-I92),0) -> 0 | R92: =MAX((M92-L92+K92-J92+G92-F92+E92-D92+O92-N92-H92+I92),0) -> 0 | S92: =B92 -> 551 | U92: =+Q92-R92 -> 0
B93: 552 | C93: Loan to joint venture | D93: =SUMIF(TB!$B$9:$E$120,ETB!B93,TB!$D$9:$D$120) -> 0 | E93: =SUMIF(TB!$B$9:$E$120,ETB!B93,TB!$E$9:$E$120) -> 0 | L93: =SUMIF(Journal!$C$10:$C$304,ETB!B93,Journal!$E$10:$E$304) -> 0 | M93: =SUMIF(Journal!$C$10:$C$304,ETB!B93,Journal!$F$10:$F$304) -> 0 | Q93: =MAX((D93-E93+F93-G93+J93-K93+L93-M93+N93-O93+H93-I93),0) -> 0 | R93: =MAX((M93-L93+K93-J93+G93-F93+E93-D93+O93-N93-H93+I93),0) -> 0 | S93: =B93 -> 552 | U93: =+Q93-R93 -> 0
B94: 553 | C94: Loans to other part int | D94: =SUMIF(TB!$B$9:$E$120,ETB!B94,TB!$D$9:$D$120) -> 0 | E94: =SUMIF(TB!$B$9:$E$120,ETB!B94,TB!$E$9:$E$120) -> 0 | L94: =SUMIF(Journal!$C$10:$C$304,ETB!B94,Journal!$E$10:$E$304) -> 0 | M94: =SUMIF(Journal!$C$10:$C$304,ETB!B94,Journal!$F$10:$F$304) -> 0 | Q94: =MAX((D94-E94+F94-G94+J94-K94+L94-M94+N94-O94+H94-I94),0) -> 0 | R94: =MAX((M94-L94+K94-J94+G94-F94+E94-D94+O94-N94-H94+I94),0) -> 0 | S94: =B94 -> 553 | U94: =+Q94-R94 -> 0
B95: 556 | C95: Investments - listed | D95: =SUMIF(TB!$B$9:$E$120,ETB!B95,TB!$D$9:$D$120) -> 0 | E95: =SUMIF(TB!$B$9:$E$120,ETB!B95,TB!$E$9:$E$120) -> 0 | L95: =SUMIF(Journal!$C$10:$C$304,ETB!B95,Journal!$E$10:$E$304) -> 0 | M95: =SUMIF(Journal!$C$10:$C$304,ETB!B95,Journal!$F$10:$F$304) -> 0 | Q95: =MAX((D95-E95+F95-G95+J95-K95+L95-M95+N95-O95+H95-I95),0) -> 0 | R95: =MAX((M95-L95+K95-J95+G95-F95+E95-D95+O95-N95-H95+I95),0) -> 0 | S95: =B95 -> 556 | U95: =+Q95-R95 -> 0
B96: 556/1 | C96: Investments - listed b/fwd | D96: =SUMIF(TB!$B$9:$E$120,ETB!B96,TB!$D$9:$D$120) -> 0 | E96: =SUMIF(TB!$B$9:$E$120,ETB!B96,TB!$E$9:$E$120) -> 0 | L96: =SUMIF(Journal!$C$10:$C$304,ETB!B96,Journal!$E$10:$E$304) -> 0 | M96: =SUMIF(Journal!$C$10:$C$304,ETB!B96,Journal!$F$10:$F$304) -> 0 | Q96: =MAX((D96-E96+F96-G96+J96-K96+L96-M96+N96-O96+H96-I96),0) -> 0 | R96: =MAX((M96-L96+K96-J96+G96-F96+E96-D96+O96-N96-H96+I96),0) -> 0 | S96: =B96 -> 556/1 | U96: =+Q96-R96 -> 0
B97: 556/2 | C97: Investments - listed additions | D97: =SUMIF(TB!$B$9:$E$120,ETB!B97,TB!$D$9:$D$120) -> 0 | E97: =SUMIF(TB!$B$9:$E$120,ETB!B97,TB!$E$9:$E$120) -> 0 | L97: =SUMIF(Journal!$C$10:$C$304,ETB!B97,Journal!$E$10:$E$304) -> 0 | M97: =SUMIF(Journal!$C$10:$C$304,ETB!B97,Journal!$F$10:$F$304) -> 0 | Q97: =MAX((D97-E97+F97-G97+J97-K97+L97-M97+N97-O97+H97-I97),0) -> 0 | R97: =MAX((M97-L97+K97-J97+G97-F97+E97-D97+O97-N97-H97+I97),0) -> 0 | S97: =B97 -> 556/2 | U97: =+Q97-R97 -> 0
B98: 556/3 | C98: Investments - listed disposals | D98: =SUMIF(TB!$B$9:$E$120,ETB!B98,TB!$D$9:$D$120) -> 0 | E98: =SUMIF(TB!$B$9:$E$120,ETB!B98,TB!$E$9:$E$120) -> 0 | L98: =SUMIF(Journal!$C$10:$C$304,ETB!B98,Journal!$E$10:$E$304) -> 0 | M98: =SUMIF(Journal!$C$10:$C$304,ETB!B98,Journal!$F$10:$F$304) -> 0 | Q98: =MAX((D98-E98+F98-G98+J98-K98+L98-M98+N98-O98+H98-I98),0) -> 0 | R98: =MAX((M98-L98+K98-J98+G98-F98+E98-D98+O98-N98-H98+I98),0) -> 0 | S98: =B98 -> 556/3 | U98: =+Q98-R98 -> 0
B99: 556/21 | C99: Investments - listed provisions b/fwd | D99: =SUMIF(TB!$B$9:$E$120,ETB!B99,TB!$D$9:$D$120) -> 0 | E99: =SUMIF(TB!$B$9:$E$120,ETB!B99,TB!$E$9:$E$120) -> 0 | L99: =SUMIF(Journal!$C$10:$C$304,ETB!B99,Journal!$E$10:$E$304) -> 0 | M99: =SUMIF(Journal!$C$10:$C$304,ETB!B99,Journal!$F$10:$F$304) -> 0 | Q99: =MAX((D99-E99+F99-G99+J99-K99+L99-M99+N99-O99+H99-I99),0) -> 0 | R99: =MAX((M99-L99+K99-J99+G99-F99+E99-D99+O99-N99-H99+I99),0) -> 0 | S99: =B99 -> 556/21 | U99: =+Q99-R99 -> 0
B100: 556/22 | C100: Investments - listed provisions provided in period | D100: =SUMIF(TB!$B$9:$E$120,ETB!B100,TB!$D$9:$D$120) -> 0 | E100: =SUMIF(TB!$B$9:$E$120,ETB!B100,TB!$E$9:$E$120) -> 0 | L100: =SUMIF(Journal!$C$10:$C$304,ETB!B100,Journal!$E$10:$E$304) -> 0 | M100: =SUMIF(Journal!$C$10:$C$304,ETB!B100,Journal!$F$10:$F$304) -> 0 | Q100: =MAX((D100-E100+F100-G100+J100-K100+L100-M100+N100-O100+H100-I100),0) -> 0 | R100: =MAX((M100-L100+K100-J100+G100-F100+E100-D100+O100-N100-H100+I100),0) -> 0 | S100: =B100 -> 556/22 | U100: =+Q100-R100 -> 0
B101: 556/23 | C101: Investments - listed provisions disposals | D101: =SUMIF(TB!$B$9:$E$120,ETB!B101,TB!$D$9:$D$120) -> 0 | E101: =SUMIF(TB!$B$9:$E$120,ETB!B101,TB!$E$9:$E$120) -> 0 | L101: =SUMIF(Journal!$C$10:$C$304,ETB!B101,Journal!$E$10:$E$304) -> 0 | M101: =SUMIF(Journal!$C$10:$C$304,ETB!B101,Journal!$F$10:$F$304) -> 0 | Q101: =MAX((D101-E101+F101-G101+J101-K101+L101-M101+N101-O101+H101-I101),0) -> 0 | R101: =MAX((M101-L101+K101-J101+G101-F101+E101-D101+O101-N101-H101+I101),0) -> 0 | S101: =B101 -> 556/23 | U101: =+Q101-R101 -> 0
B102: 557 | C102: Investments - unlisted | D102: =SUMIF(TB!$B$9:$E$120,ETB!B102,TB!$D$9:$D$120) -> 0 | E102: =SUMIF(TB!$B$9:$E$120,ETB!B102,TB!$E$9:$E$120) -> 0 | L102: =SUMIF(Journal!$C$10:$C$304,ETB!B102,Journal!$E$10:$E$304) -> 0 | M102: =SUMIF(Journal!$C$10:$C$304,ETB!B102,Journal!$F$10:$F$304) -> 0 | Q102: =MAX((D102-E102+F102-G102+J102-K102+L102-M102+N102-O102+H102-I102),0) -> 0 | R102: =MAX((M102-L102+K102-J102+G102-F102+E102-D102+O102-N102-H102+I102),0) -> 0 | S102: =B102 -> 557 | U102: =+Q102-R102 -> 0
B103: 557/1 | C103: Investments - unlisted b/fwd | D103: =SUMIF(TB!$B$9:$E$120,ETB!B103,TB!$D$9:$D$120) -> 0 | E103: =SUMIF(TB!$B$9:$E$120,ETB!B103,TB!$E$9:$E$120) -> 0 | L103: =SUMIF(Journal!$C$10:$C$304,ETB!B103,Journal!$E$10:$E$304) -> 0 | M103: =SUMIF(Journal!$C$10:$C$304,ETB!B103,Journal!$F$10:$F$304) -> 0 | Q103: =MAX((D103-E103+F103-G103+J103-K103+L103-M103+N103-O103+H103-I103),0) -> 0 | R103: =MAX((M103-L103+K103-J103+G103-F103+E103-D103+O103-N103-H103+I103),0) -> 0 | S103: =B103 -> 557/1 | U103: =+Q103-R103 -> 0
...

Sheet Profit & Loss
B2: Client : | C2: =Index!C2 -> Forest Car Company Ltd | G2: Prepared by : | H2: =Index!H2 -> Aratee | I2: Date : | J2: =Index!J2 -> 45343
B3: Year end : | C3: =Index!C3 -> 45260 | G3: Reviewed by : | H3: =Index!H3 -> Mitesh | I3: Date : | J3: =Index!J3 -> 45352
B5: Profit and loss account
B7: Particulars | D7: =Info!C6 -> 45260 | F7: =Info!E6 -> NA | H7: Variance | J7: Comments/hyperlinks
D8: £ | E8: £ | F8: £ | G8: £ | H8: % | I8: Amount
B10: Turnover
A11: =ETB!B346 -> 1 | B11: =+ETB!C346 -> Sales | E11: =-SUMIF(ETB!$P$344:$R$678,'Profit & Loss'!A11,ETB!$Q$344:$Q$678)+SUMIF(ETB!$P$344:$R$678,'Profit & Loss'!A11,ETB!$R$344:$R$678) -> 673613.23 | G11: =SUMIF('Opening TB'!B:B,'Profit & Loss'!A11,'Opening TB'!E:E)-SUMIF('Opening TB'!B:B,'Profit & Loss'!A11,'Opening TB'!D:D) -> 0 | H11: 1 | I11: =+E11-G11 -> 673613.23 | J11: Increase 70K sales
A12: =ETB!B347 -> 3 | B12: =+ETB!C347 -> Other Income | E12: =-SUMIF(ETB!$P$344:$R$678,'Profit & Loss'!A12,ETB!$Q$344:$Q$678)+SUMIF(ETB!$P$344:$R$678,'Profit & Loss'!A12,ETB!$R$344:$R$678) -> 0 | G12: =SUMIF('Opening TB'!B:B,'Profit & Loss'!A12,'Opening TB'!E:E)-SUMIF('Opening TB'!B:B,'Profit & Loss'!A12,'Opening TB'!D:D) -> 0 | H12: =+(E12/G12)-100% -> #DIV/0! | I12: =+E12-G12 -> 0
A13: =ETB!B348 -> 4 | B13: =+ETB!C348 -> Sales type B | E13: =-SUMIF(ETB!$P$344:$R$678,'Profit & Loss'!A13,ETB!$Q$344:$Q$678)+SUMIF(ETB!$P$344:$R$678,'Profit & Loss'!A13,ETB!$R$344:$R$678) -> 0 | G13: =SUMIF('Opening TB'!B:B,'Profit & Loss'!A13,'Opening TB'!E:E)-SUMIF('Opening TB'!B:B,'Profit & Loss'!A13,'Opening TB'!D:D) -> 0 | H13: =+(E13/G13)-100% -> #DIV/0! | I13: =+E13-G13 -> 0
A14: =ETB!B349 -> 5 | B14: =+ETB!C349 -> Sales type C | E14: =-SUMIF(ETB!$P$344:$R$678,'Profit & Loss'!A14,ETB!$Q$344:$Q$678)+SUMIF(ETB!$P$344:$R$678,'Profit & Loss'!A14,ETB!$R$344:$R$678) -> 0 | G14: =SUMIF('Opening TB'!B:B,'Profit & Loss'!A14,'Opening TB'!E:E)-SUMIF('Opening TB'!B:B,'Profit & Loss'!A14,'Opening TB'!D:D) -> 0 | H14: =+(E14/G14)-100% -> #DIV/0! | I14: =+E14-G14 -> 0
A15: =ETB!B350 -> 2 | B15: =+ETB!C350 -> Contracts | E15: =-SUMIF(ETB!$P$344:$R$678,'Profit & Loss'!A15,ETB!$Q$344:$Q$678)+SUMIF(ETB!$P$344:$R$678,'Profit & Loss'!A15,ETB!$R$344:$R$678) -> 0 | G15: =SUMIF('Opening TB'!B:B,'Profit & Loss'!A15,'Opening TB'!E:E)-SUMIF('Opening TB'!B:B,'Profit & Loss'!A15,'Opening TB'!D:D) -> 0 | H15: =+(E15/G15)-100% -> #DIV/0! | I15: =+E15-G15 -> 0
A16: =ETB!B351 -> 11 | B16: =+ETB!C351 -> Contracts with customers | E16: =-SUMIF(ETB!$P$344:$R$678,'Profit & Loss'!A16,ETB!$Q$344:$Q$678)+SUMIF(ETB!$P$344:$R$678,'Profit & Loss'!A16,ETB!$R$344:$R$678) -> 0 | G16: =SUMIF('Opening TB'!B:B,'Profit & Loss'!A16,'Opening TB'!E:E)-SUMIF('Opening TB'!B:B,'Profit & Loss'!A16,'Opening TB'!D:D) -> 0 | H16: =+(E16/G16)-100% -> #DIV/0! | I16: =+E16-G16 -> 0
A17: =ETB!B352 -> 12 | B17: =+ETB!C352 -> Rental income | E17: =-SUMIF(ETB!$P$344:$R$678,'Profit & Loss'!A17,ETB!$Q$344:$Q$678)+SUMIF(ETB!$P$344:$R$678,'Profit & Loss'!A17,ETB!$R$344:$R$678) -> 0 | G17: =SUMIF('Opening TB'!B:B,'Profit & Loss'!A17,'Opening TB'!E:E)-SUMIF('Opening TB'!B:B,'Profit & Loss'!A17,'Opening TB'!D:D) -> 0 | H17: =+(E17/G17)-100% -> #DIV/0! | I17: =+E17-G17 -> 0
A18: =ETB!B353 -> 13 | B18: =+ETB!C353 -> Commission | E18: =-SUMIF(ETB!$P$344:$R$678,'Profit & Loss'!A18,ETB!$Q$344:$Q$678)+SUMIF(ETB!$P$344:$R$678,'Profit & Loss'!A18,ETB!$R$344:$R$678) -> 0 | G18: =SUMIF('Opening TB'!B:B,'Profit & Loss'!A18,'Opening TB'!E:E)-SUMIF('Opening TB'!B:B,'Profit & Loss'!A18,'Opening TB'!D:D) -> 0 | H18: =+(E18/G18)-100% -> #DIV/0! | I18: =+E18-G18 -> 0
A19: =ETB!B354 -> 14 | B19: =+ETB!C354 -> Grants and subsidies received (Sales) | E19: =-SUMIF(ETB!$P$344:$R$678,'Profit & Loss'!A19,ETB!$Q$344:$Q$678)+SUMIF(ETB!$P$344:$R$678,'Profit & Loss'!A19,ETB!$R$344:$R$678) -> 0 | G19: =SUMIF('Opening TB'!B:B,'Profit & Loss'!A19,'Opening TB'!E:E)-SUMIF('Opening TB'!B:B,'Profit & Loss'!A19,'Opening TB'!D:D) -> 0 | H19: =+(E19/G19)-100% -> #DIV/0! | I19: =+E19-G19 -> 0
A20: =ETB!B355 -> 15 | B20: =+ETB!C355 -> Other trading income | E20: =-SUMIF(ETB!$P$344:$R$678,'Profit & Loss'!A20,ETB!$Q$344:$Q$678)+SUMIF(ETB!$P$344:$R$678,'Profit & Loss'!A20,ETB!$R$344:$R$678) -> 0 | G20: =SUMIF('Opening TB'!B:B,'Profit & Loss'!A20,'Opening TB'!E:E)-SUMIF('Opening TB'!B:B,'Profit & Loss'!A20,'Opening TB'!D:D) -> 0 | H20: =+(E20/G20)-100% -> #DIV/0! | I20: =+E20-G20 -> 0
G21: =SUMIF('Opening TB'!B:B,'Profit & Loss'!A21,'Opening TB'!E:E)-SUMIF('Opening TB'!B:B,'Profit & Loss'!A21,'Opening TB'!D:D) -> 0 | I21: =+E21-G21 -> 0
B22: Cost of Sales
A23: =ETB!B356 -> 17 | B23: =+ETB!C356 -> Opening Valuation | D23: =SUMIF(ETB!$P$345:$R$679,'Profit & Loss'!A23,ETB!$Q$345:$Q$679)-SUMIF(ETB!$P$345:$R$679,'Profit & Loss'!A23,ETB!$R$345:$R$679) -> 0 | F23: =SUMIF('Opening TB'!B:B,'Profit & Loss'!A23,'Opening TB'!D:D)-SUMIF('Opening TB'!B:B,'Profit & Loss'!A23,'Opening TB'!E:E) -> 0 | H23: =+(D23/F23)-100% -> #DIV/0! | I23: =+D23-F23 -> 0
A24: =ETB!B357 -> 18 | B24: =+ETB!C357 -> Opening stock | D24: =SUMIF(ETB!$P$345:$R$679,'Profit & Loss'!A24,ETB!$Q$345:$Q$679)-SUMIF(ETB!$P$345:$R$679,'Profit & Loss'!A24,ETB!$R$345:$R$679) -> 0 | F24: =SUMIF('Opening TB'!B:B,'Profit & Loss'!A24,'Opening TB'!D:D)-SUMIF('Opening TB'!B:B,'Profit & Loss'!A24,'Opening TB'!E:E) -> 0 | H24: =+(D24/F24)-100% -> #DIV/0! | I24: =+D24-F24 -> 0
A25: =ETB!B358 -> 19 | B25: =+ETB!C358 -> Opening raw materials | D25: =SUMIF(ETB!$P$345:$R$679,'Profit & Loss'!A25,ETB!$Q$345:$Q$679)-SUMIF(ETB!$P$345:$R$679,'Profit & Loss'!A25,ETB!$R$345:$R$679) -> 0 | F25: =SUMIF('Opening TB'!B:B,'Profit & Loss'!A25,'Opening TB'!D:D)-SUMIF('Opening TB'!B:B,'Profit & Loss'!A25,'Opening TB'!E:E) -> 0 | H25: =+(D25/F25)-100% -> #DIV/0! | I25: =+D25-F25 -> 0
A26: =ETB!B359 -> 23 | B26: =+ETB!C359 -> Opening work in progress | D26: =SUMIF(ETB!$P$345:$R$679,'Profit & Loss'!A26,ETB!$Q$345:$Q$679)-SUMIF(ETB!$P$345:$R$679,'Profit & Loss'!A26,ETB!$R$345:$R$679) -> 0 | F26: =SUMIF('Opening TB'!B:B,'Profit & Loss'!A26,'Opening TB'!D:D)-SUMIF('Opening TB'!B:B,'Profit & Loss'!A26,'Opening TB'!E:E) -> 0 | H26: =+(D26/F26)-100% -> #DIV/0! | I26: =+D26-F26 -> 0
A27: =ETB!B360 -> 25 | B27: =+ETB!C360 -> Opening Finished goods | D27: =SUMIF(ETB!$P$345:$R$679,'Profit & Loss'!A27,ETB!$Q$345:$Q$679)-SUMIF(ETB!$P$345:$R$679,'Profit & Loss'!A27,ETB!$R$345:$R$679) -> 0 | F27: =SUMIF('Opening TB'!B:B,'Profit & Loss'!A27,'Opening TB'!D:D)-SUMIF('Opening TB'!B:B,'Profit & Loss'!A27,'Opening TB'!E:E) -> 0 | H27: =+(D27/F27)-100% -> #DIV/0! | I27: =+D27-F27 -> 0
A28: =ETB!B361 -> 27 | B28: =+ETB!C361 -> Purchases | D28: =SUMIF(ETB!$P$345:$R$679,'Profit & Loss'!A28,ETB!$Q$345:$Q$679)-SUMIF(ETB!$P$345:$R$679,'Profit & Loss'!A28,ETB!$R$345:$R$679) -> 561254.8 | F28: =SUMIF('Opening TB'!B:B,'Profit & Loss'!A28,'Opening TB'!D:D)-SUMIF('Opening TB'!B:B,'Profit & Loss'!A28,'Opening TB'!E:E) -> 0 | H28: 1 | I28: =+D28-F28 -> 561254.8
A29: =ETB!B362 -> 28 | B29: =+ETB!C362 -> Purchases Type A (Cost of sales) | D29: =SUMIF(ETB!$P$345:$R$679,'Profit & Loss'!A29,ETB!$Q$345:$Q$679)-SUMIF(ETB!$P$345:$R$679,'Profit & Loss'!A29,ETB!$R$345:$R$679) -> 0 | F29: =SUMIF('Opening TB'!B:B,'Profit & Loss'!A29,'Opening TB'!D:D)-SUMIF('Opening TB'!B:B,'Profit & Loss'!A29,'Opening TB'!E:E) -> 0 | H29: 1 | I29: =+D29-F29 -> 0
A30: =ETB!B363 -> 29 | B30: =+ETB!C363 -> Purchases Type B (Cost of sales) | D30: =SUMIF(ETB!$P$345:$R$679,'Profit & Loss'!A30,ETB!$Q$345:$Q$679)-SUMIF(ETB!$P$345:$R$679,'Profit & Loss'!A30,ETB!$R$345:$R$679) -> 0 | F30: =SUMIF('Opening TB'!B:B,'Profit & Loss'!A30,'Opening TB'!D:D)-SUMIF('Opening TB'!B:B,'Profit & Loss'!A30,'Opening TB'!E:E) -> 0 | H30: 1 | I30: =+D30-F30 -> 0
A31: =ETB!B364 -> 30 | B31: =+ETB!C364 -> Purchases Type C (Cost of sales) | D31: =SUMIF(ETB!$P$345:$R$679,'Profit & Loss'!A31,ETB!$Q$345:$Q$679)-SUMIF(ETB!$P$345:$R$679,'Profit & Loss'!A31,ETB!$R$345:$R$679) -> 0 | F31: =SUMIF('Opening TB'!B:B,'Profit & Loss'!A31,'Opening TB'!D:D)-SUMIF('Opening TB'!B:B,'Profit & Loss'!A31,'Opening TB'!E:E) -> 0 | H31: 1 | I31: =+D31-F31 -> 0
A32: =ETB!B365 -> 37 | B32: =+ETB!C365 -> Own work capitalised | D32: =SUMIF(ETB!$P$345:$R$679,'Profit & Loss'!A32,ETB!$Q$345:$Q$679)-SUMIF(ETB!$P$345:$R$679,'Profit & Loss'!A32,ETB!$R$345:$R$679) -> 0 | F32: =SUMIF('Opening TB'!B:B,'Profit & Loss'!A32,'Opening TB'!D:D)-SUMIF('Opening TB'!B:B,'Profit & Loss'!A32,'Opening TB'!E:E) -> 0 | H32: 1 | I32: =+D32-F32 -> 0
A33: =ETB!B366 -> 43 | B33: =+ETB!C366 -> Director's remuneration etc | D33: =SUMIF(ETB!$P$345:$R$679,'Profit & Loss'!A33,ETB!$Q$345:$Q$679)-SUMIF(ETB!$P$345:$R$679,'Profit & Loss'!A33,ETB!$R$345:$R$679) -> 0 | F33: =SUMIF('Opening TB'!B:B,'Profit & Loss'!A33,'Opening TB'!D:D)-SUMIF('Opening TB'!B:B,'Profit & Loss'!A33,'Opening TB'!E:E) -> 0 | H33: 1 | I33: =+D33-F33 -> 0
A34: =ETB!B367 -> 44 | B34: =+ETB!C367 -> Wages | D34: =SUMIF(ETB!$P$345:$R$679,'Profit & Loss'!A34,ETB!$Q$345:$Q$679)-SUMIF(ETB!$P$345:$R$679,'Profit & Loss'!A34,ETB!$R$345:$R$679) -> 0 | F34: =SUMIF('Opening TB'!B:B,'Profit & Loss'!A34,'Opening TB'!D:D)-SUMIF('Opening TB'!B:B,'Profit & Loss'!A34,'Opening TB'!E:E) -> 0 | H34: 1 | I34: =+D34-F34 -> 0
A35: =ETB!B368 -> 45 | B35: =+ETB!C368 -> Social Security | D35: =SUMIF(ETB!$P$345:$R$679,'Profit & Loss'!A35,ETB!$Q$345:$Q$679)-SUMIF(ETB!$P$345:$R$679,'Profit & Loss'!A35,ETB!$R$345:$R$679) -> 0 | F35: =SUMIF('Opening TB'!B:B,'Profit & Loss'!A35,'Opening TB'!D:D)-SUMIF('Opening TB'!B:B,'Profit & Loss'!A35,'Opening TB'!E:E) -> 0 | H35: 1 | I35: =+D35-F35 -> 0
A36: =ETB!B369 -> 46 | B36: =+ETB!C369 -> Pensions | D36: =SUMIF(ETB!$P$345:$R$679,'Profit & Loss'!A36,ETB!$Q$345:$Q$679)-SUMIF(ETB!$P$345:$R$679,'Profit & Loss'!A36,ETB!$R$345:$R$679) -> 0 | F36: =SUMIF('Opening TB'!B:B,'Profit & Loss'!A36,'Opening TB'!D:D)-SUMIF('Opening TB'!B:B,'Profit & Loss'!A36,'Opening TB'!E:E) -> 0 | H36: 1 | I36: =+D36-F36 -> 0
A37: =ETB!B370 -> 49 | B37: =+ETB!C370 -> IFRS 16 Leases | D37: =SUMIF(ETB!$P$345:$R$679,'Profit & Loss'!A37,ETB!$Q$345:$Q$679)-SUMIF(ETB!$P$345:$R$679,'Profit & Loss'!A37,ETB!$R$345:$R$679) -> 0 | F37: =SUMIF('Opening TB'!B:B,'Profit & Loss'!A37,'Opening TB'!D:D)-SUMIF('Opening TB'!B:B,'Profit & Loss'!A37,'Opening TB'!E:E) -> 0 | H37: 1 | I37: =+D37-F37 -> 0
A38: =ETB!B371 -> 50 | B38: =+ETB!C371 -> Hire of plant and machinery | D38: =SUMIF(ETB!$P$345:$R$679,'Profit & Loss'!A38,ETB!$Q$345:$Q$679)-SUMIF(ETB!$P$345:$R$679,'Profit & Loss'!A38,ETB!$R$345:$R$679) -> 0 | F38: =SUMIF('Opening TB'!B:B,'Profit & Loss'!A38,'Opening TB'!D:D)-SUMIF('Opening TB'!B:B,'Profit & Loss'!A38,'Opening TB'!E:E) -> 0 | H38: 1 | I38: =+D38-F38 -> 0
A39: =ETB!B372 -> 51 | B39: =+ETB!C372 -> Other Operating leases | D39: =SUMIF(ETB!$P$345:$R$679,'Profit & Loss'!A39,ETB!$Q$345:$Q$679)-SUMIF(ETB!$P$345:$R$679,'Profit & Loss'!A39,ETB!$R$345:$R$679) -> 0 | F39: =SUMIF('Opening TB'!B:B,'Profit & Loss'!A39,'Opening TB'!D:D)-SUMIF('Opening TB'!B:B,'Profit & Loss'!A39,'Opening TB'!E:E) -> 0 | H39: 1 | I39: =+D39-F39 -> 0
... A42: =ETB!B375 -> 54 | B42: =+ETB!C375 -> Direct cost | D42: =SUMIF(ETB!$P$345:$R$679,'Profit & Loss'!A42,ETB!$Q$345:$Q$679)-SUMIF(ETB!$P$345:$R$679,'Profit & Loss'!A42,ETB!$R$345:$R$679) -> 137771.26 | F42: =SUMIF('Opening TB'!B:B,'Profit & Loss'!A42,'Opening TB'!D:D)-SUMIF('Opening TB'!B:B,'Profit & Loss'!A42,'Opening TB'!E:E) -> 0 | H42: 1 | I42: =+D42-F42 -> 137771.26
A43: =ETB!B376 -> 55 | B43: =+ETB!C376 -> No Descriptions | D43: =SUMIF(ETB!$P$345:$R$679,'Profit & Loss'!A43,ETB!$Q$345:$Q$679)-SUMIF(ETB!$P$345:$R$679,'Profit & Loss'!A43,ETB!$R$345:$R$679) -> 0 | F43: =SUMIF('Opening TB'!B:B,'Profit & Loss'!A43,'Opening TB'!D:D)-SUMIF('Opening TB'!B:B,'Profit & Loss'!A43,'Opening TB'!E:E) -> 0 | H43: =+(D43/F43)-100% -> #DIV/0! | I43: =+D43-F43 -> 0
A44: =ETB!B377 -> 56 | B44: =+ETB!C377 -> No Descriptions | D44: =SUMIF(ETB!$P$345:$R$679,'Profit & Loss'!A44,ETB!$Q$345:$Q$679)-SUMIF(ETB!$P$345:$R$679,'Profit & Loss'!A44,ETB!$R$345:$R$679) -> 0 | F44: =SUMIF('Opening TB'!B:B,'Profit & Loss'!A44,'Opening TB'!D:D)-SUMIF('Opening TB'!B:B,'Profit & Loss'!A44,'Opening TB'!E:E) -> 0 | H44: =+(D44/F44)-100% -> #DIV/0! | I44: =+D44-F44 -> 0
A45: =ETB!B378 -> 65 | B45: =+ETB!C378 -> Amortisation - intang f a | D45: =SUMIF(ETB!$P$345:$R$679,'Profit & Loss'!A45,ETB!$Q$345:$Q$679)-SUMIF(ETB!$P$345:$R$679,'Profit & Loss'!A45,ETB!$R$345:$R$679) -> 0 | F45: =SUMIF('Opening TB'!B:B,'Profit & Loss'!A45,'Opening TB'!D:D)-SUMIF('Opening TB'!B:B,'Profit & Loss'!A45,'Opening TB'!E:E) -> 0 | H45: =+(D45/F45)-100% -> #DIV/0! | I45: =+D45-F45 -> 0
A46: =ETB!B379 -> 66 | B46: =+ETB!C379 -> Depreciation - tang f a | D46: =SUMIF(ETB!$P$345:$R$679,'Profit & Loss'!A46,ETB!$Q$345:$Q$679)-SUMIF(ETB!$P$345:$R$679,'Profit & Loss'!A46,ETB!$R$345:$R$679) -> 0 | F46: =SUMIF('Opening TB'!B:B,'Profit & Loss'!A46,'Opening TB'!D:D)-SUMIF('Opening TB'!B:B,'Profit & Loss'!A46,'Opening TB'!E:E) -> 0 | H46: =+(D46/F46)-100% -> #DIV/0! | I46: =+D46-F46 -> 0
A47: =ETB!B380 -> 67 | B47: =+ETB!C380 -> Profit/loss on sale intang f a | D47: =SUMIF(ETB!$P$345:$R$679,'Profit & Loss'!A47,ETB!$Q$345:$Q$679)-SUMIF(ETB!$P$345:$R$679,'Profit & Loss'!A47,ETB!$R$345:$R$679) -> 0 | F47: =SUMIF('Opening TB'!B:B,'Profit & Loss'!A47,'Opening TB'!D:D)-SUMIF('Opening TB'!B:B,'Profit & Loss'!A47,'Opening TB'!E:E) -> 0 | H47: =+(D47/F47)-100% -> #DIV/0! | I47: =+D47-F47 -> 0
A48: =ETB!B381 -> 68 | B48: =+ETB!C381 -> Profit/loss on sale tang f a | D48: =SUMIF(ETB!$P$345:$R$679,'Profit & Loss'!A48,ETB!$Q$345:$Q$679)-SUMIF(ETB!$P$345:$R$679,'Profit & Loss'!A48,ETB!$R$345:$R$679) -> 0 | F48: =SUMIF('Opening TB'!B:B,'Profit & Loss'!A48,'Opening TB'!D:D)-SUMIF('Opening TB'!B:B,'Profit & Loss'!A48,'Opening TB'!E:E) -> 0 | H48: =+(D48/F48)-100% -> #DIV/0! | I48: =+D48-F48 -> 0
A49: =ETB!B382 -> 69 | B49: =+ETB!C382 -> Profit/loss on sale f a invest | D49: =SUMIF(ETB!$P$345:$R$679,'Profit & Loss'!A49,ETB!$Q$345:$Q$679)-SUMIF(ETB!$P$345:$R$679,'Profit & Loss'!A49,ETB!$R$345:$R$679) -> 0 | F49: =SUMIF('Opening TB'!B:B,'Profit & Loss'!A49,'Opening TB'!D:D)-SUMIF('Opening TB'!B:B,'Profit & Loss'!A49,'Opening TB'!E:E) -> 0 | H49: =+(D49/F49)-100% -> #DIV/0! | I49: =+D49-F49 -> 0
A50: =ETB!B383 -> 70 | B50: =+ETB!C383 -> Impairment loss intang f a | D50: =SUMIF(ETB!$P$345:$R$679,'Profit & Loss'!A50,ETB!$Q$345:$Q$679)-SUMIF(ETB!$P$345:$R$679,'Profit & Loss'!A50,ETB!$R$345:$R$679) -> 0 | F50: =SUMIF('Opening TB'!B:B,'Profit & Loss'!A50,'Opening TB'!D:D)-SUMIF('Opening TB'!B:B,'Profit & Loss'!A50,'Opening TB'!E:E) -> 0 | H50: =+(D50/F50)-100% -> #DIV/0! | I50: =+D50-F50 -> 0
A51: =ETB!B384 -> 71 | B51: =+ETB!C384 -> Impairment loss tang f a | D51: =SUMIF(ETB!$P$345:$R$679,'Profit & Loss'!A51,ETB!$Q$345:$Q$679)-SUMIF(ETB!$P$345:$R$679,'Profit & Loss'!A51,ETB!$R$345:$R$679) -> 0 | F51: =SUMIF('Opening TB'!B:B,'Profit & Loss'!A51,'Opening TB'!D:D)-SUMIF('Opening TB'!B:B,'Profit & Loss'!A51,'Opening TB'!E:E) -> 0 | H51: =+(D51/F51)-100% -> #DIV/0! | I51: =+D51-F51 -> 0
A52: =ETB!B385 -> 72 | B52: =+ETB!C385 -> Exceptional items | D52: =SUMIF(ETB!$P$345:$R$679,'Profit & Loss'!A52,ETB!$Q$345:$Q$679)-SUMIF(ETB!$P$345:$R$679,'Profit & Loss'!A52,ETB!$R$345:$R$679) -> 0 | F52: =SUMIF('Opening TB'!B:B,'Profit & Loss'!A52,'Opening TB'!D:D)-SUMIF('Opening TB'!B:B,'Profit & Loss'!A52,'Opening TB'!E:E) -> 0 | H52: =+(D52/F52)-100% -> #DIV/0! | I52: =+D52-F52 -> 0
B55: Total COS | D55: =SUM(D23:D53) -> 699026.06 | F55: =SUM(F23:F53) -> 0 | I55: =+D55-F55 -> 699026.06
A56: =ETB!B386 -> 73 | B56: =+ETB!C386 -> Closing valuation | D56: =ETB!R386 -> 0 | F56: =SUMIF('Opening TB'!B:B,'Profit & Loss'!A56,'Opening TB'!E:E) -> 0 | H56: =+(D56/F56)-100% -> #DIV/0! | I56: =+D56-F56 -> 0
A57: =ETB!B387 -> 74 | B57: =+ETB!C387 -> Closing stock | D57: =-(SUMIF(ETB!$P$345:$R$679,'Profit & Loss'!A57,ETB!$Q$345:$Q$679)-SUMIF(ETB!$P$345:$R$679,'Profit & Loss'!A57,ETB!$R$345:$R$679)) -> 44938 | F57: =SUMIF('Opening TB'!B:B,'Profit & Loss'!A57,'Opening TB'!E:E) -> 0 | H57: 1 | I57: =+D57-F57 -> 44938
A58: =ETB!B388 -> 75 | B58: =+ETB!C388 -> Closing raw materials | D58: 0 | F58: =SUMIF('Opening TB'!B:B,'Profit & Loss'!A58,'Opening TB'!E:E) -> 0 | H58: =+(D58/F58)-100% -> #DIV/0! | I58: =+D58-F58 -> 0
A59: =ETB!B389 -> 79 | B59: =+ETB!C389 -> Closing work in progress | D59: 0 | F59: =SUMIF('Opening TB'!B:B,'Profit & Loss'!A59,'Opening TB'!E:E) -> 0 | H59: =+(D59/F59)-100% -> #DIV/0! | I59: =+D59-F59 -> 0
A60: =ETB!B390 -> 81 | B60: =+ETB!C390 -> Closing stock - finished goods | D60: =ETB!R389 -> 0 | F60: =SUMIF('Opening TB'!B:B,'Profit & Loss'!A60,'Opening TB'!E:E) -> 0 | H60: =+(D60/F60)-100% -> #DIV/0! | I60: =+D60-F60 -> 0
E61: =+D55-SUM(D56:D60) -> 654088.06 | G61: =+F55-SUM(F56:F60) -> 0
B63: GROSS PROFIT | E63: =SUM(E11:E15)-E61 -> 19525.17 | G63: =SUM(G11:G15)-G61 -> 0
B64: GP Ratio | E64: =E63/SUM(E11:E21)*100% -> 0.028985728 | G64: =G63/SUM(G11:G21)*100% -> #DIV/0!
B66: Other income
A67: =ETB!B391 -> 83 | B67: =ETB!C391 -> Gain/loss on revaln of assets | E67: =-SUMIF(ETB!$P$345:$R$679,'Profit & Loss'!A67,ETB!$Q$345:$Q$679)+SUMIF(ETB!$P$345:$R$679,'Profit & Loss'!A67,ETB!$R$345:$R$679) -> 0 | G67: =SUMIF('Opening TB'!B:B,'Profit & Loss'!A67,'Opening TB'!E:E)-SUMIF('Opening TB'!B:B,'Profit & Loss'!A67,'Opening TB'!D:D) -> 0 | H67: =+(E67/G67)-100% -> #DIV/0! | I67: =+D67-F67 -> 0
A68: =ETB!B392 -> 88 | B68: =ETB!C392 -> Discounts received | E68: =-SUMIF(ETB!$P$345:$R$679,'Profit & Loss'!A68,ETB!$Q$345:$Q$679)+SUMIF(ETB!$P$345:$R$679,'Profit & Loss'!A68,ETB!$R$345:$R$679) -> 0 | G68: =SUMIF('Opening TB'!B:B,'Profit & Loss'!A68,'Opening TB'!E:E)-SUMIF('Opening TB'!B:B,'Profit & Loss'!A68,'Opening TB'!D:D) -> 0 | H68: =+(E68/G68)-100% -> #DIV/0! | I68: =+D68-F68 -> 0
A69: =ETB!B393 -> 89 | B69: =ETB!C393 -> Rents received | E69: =-SUMIF(ETB!$P$345:$R$679,'Profit & Loss'!A69,ETB!$Q$345:$Q$679)+SUMIF(ETB!$P$345:$R$679,'Profit & Loss'!A69,ETB!$R$345:$R$679) -> 0 | G69: =SUMIF('Opening TB'!B:B,'Profit & Loss'!A69,'Opening TB'!E:E)-SUMIF('Opening TB'!B:B,'Profit & Loss'!A69,'Opening TB'!D:D) -> 0 | H69: =+(E69/G69)-100% -> #DIV/0! | I69: =+D69-F69 -> 0
A70: =ETB!B394 -> 90 | B70: =+ETB!C394 -> Sundry Receipts | E70: =-SUMIF(ETB!$P$345:$R$679,'Profit & Loss'!A70,ETB!$Q$345:$Q$679)+SUMIF(ETB!$P$345:$R$679,'Profit & Loss'!A70,ETB!$R$345:$R$679) -> 0 | G70: =SUMIF('Opening TB'!B:B,'Profit & Loss'!A70,'Opening TB'!E:E)-SUMIF('Opening TB'!B:B,'Profit & Loss'!A70,'Opening TB'!D:D) -> 0 | H70: =+(E70/G70)-100% -> #DIV/0! | I70: =+D70-F70 -> 0
A71: =ETB!B395 -> 91 | B71: =+ETB!C395 -> No Descriptions | E71: =-SUMIF(ETB!$P$345:$R$679,'Profit & Loss'!A71,ETB!$Q$345:$Q$679)+SUMIF(ETB!$P$345:$R$679,'Profit & Loss'!A71,ETB!$R$345:$R$679) -> 0 | G71: =SUMIF('Opening TB'!B:B,'Profit & Loss'!A71,'Opening TB'!E:E)-SUMIF('Opening TB'!B:B,'Profit & Loss'!A71,'Opening TB'!D:D) -> 0 | H71: =+(E71/G71)-100% -> #DIV/0! | I71: =+D71-F71 -> 0
A72: =ETB!B396 -> 92 | B72: =+ETB!C396 -> Other income | E72: =-SUMIF(ETB!$P$345:$R$679,'Profit & Loss'!A72,ETB!$Q$345:$Q$679)+SUMIF(ETB!$P$345:$R$679,'Profit & Loss'!A72,ETB!$R$345:$R$679) -> 41159.05 | G72: =SUMIF('Opening TB'!B:B,'Profit & Loss'!A72,'Opening TB'!E:E)-SUMIF('Opening TB'!B:B,'Profit & Loss'!A72,'Opening TB'!D:D) -> 0 | H72: 1 | I72: =+D72-F72 -> 0 | J72: 35K increase
A73: =ETB!B397 -> 93 | B73: =+ETB!C397 -> No Descriptions | E73: =-SUMIF(ETB!$P$345:$R$679,'Profit & Loss'!A73,ETB!$Q$345:$Q$679)+SUMIF(ETB!$P$345:$R$679,'Profit & Loss'!A73,ETB!$R$345:$R$679) -> 0 | G73: =SUMIF('Opening TB'!B:B,'Profit & Loss'!A73,'Opening TB'!E:E)-SUMIF('Opening TB'!B:B,'Profit & Loss'!A73,'Opening TB'!D:D) -> 0 | H73: =+(E73/G73)-100% -> #DIV/0! | I73: =+D73-F73 -> 0
A74: =ETB!B398 -> 96 | B74: =+ETB!C398 -> Government Grants | E74: =-SUMIF(ETB!$P$345:$R$679,'Profit & Loss'!A74,ETB!$Q$345:$Q$679)+SUMIF(ETB!$P$345:$R$679,'Profit & Loss'!A74,ETB!$R$345:$R$679) -> 0 | G74: =SUMIF('Opening TB'!B:B,'Profit & Loss'!A74,'Opening TB'!E:E)-SUMIF('Opening TB'!B:B,'Profit & Loss'!A74,'Opening TB'!D:D) -> 0 | H74: 1 | I74: =+D74-F74 -> 0
A75: =ETB!B399 -> 97 | B75: =+ETB!C399 -> Exchange Gains | E75: =-SUMIF(ETB!$P$345:$R$679,'Profit & Loss'!A75,ETB!$Q$345:$Q$679)+SUMIF(ETB!$P$345:$R$679,'Profit & Loss'!A75,ETB!$R$345:$R$679) -> 0 | G75: =SUMIF('Opening TB'!B:B,'Profit & Loss'!A75,'Opening TB'!E:E)-SUMIF('Opening TB'!B:B,'Profit & Loss'!A75,'Opening TB'!D:D) -> 0 | H75: =+(E75/G75)-100% -> #DIV/0! | I75: =+D75-F75 -> 0
A76: =ETB!B400 -> 98 | B76: =+ETB!C400 -> Profit on sale of intang fa | E76: =-SUMIF(ETB!$P$345:$R$679,'Profit & Loss'!A76,ETB!$Q$345:$Q$679)+SUMIF(ETB!$P$345:$R$679,'Profit & Loss'!A76,ETB!$R$345:$R$679) -> 0 | G76: =SUMIF('Opening TB'!B:B,'Profit & Loss'!A76,'Opening TB'!E:E)-SUMIF('Opening TB'!B:B,'Profit & Loss'!A76,'Opening TB'!D:D) -> 0 | H76: =+(E76/G76)-100% -> #DIV/0! | I76: =+D76-F76 -> 0
A77: =ETB!B401 -> 99 | B77: =+ETB!C401 -> Profit on sale of tang fa | E77: =-SUMIF(ETB!$P$345:$R$679,'Profit & Loss'!A77,ETB!$Q$345:$Q$679)+SUMIF(ETB!$P$345:$R$679,'Profit & Loss'!A77,ETB!$R$345:$R$679) -> 0 | G77: =SUMIF('Opening TB'!B:B,'Profit & Loss'!A77,'Opening TB'!E:E)-SUMIF('Opening TB'!B:B,'Profit & Loss'!A77,'Opening TB'!D:D) -> 0 | H77: =+(E77/G77)-100% -> #DIV/0! | I77: =+D77-F77 -> 0
A78: =ETB!B402 -> 100 | B78: =+ETB!C402 -> Profit on sale f a investment | E78: =-SUMIF(ETB!$P$345:$R$679,'Profit & Loss'!A78,ETB!$Q$345:$Q$679)+SUMIF(ETB!$P$345:$R$679,'Profit & Loss'!A78,ETB!$R$345:$R$679) -> 0 | G78: =SUMIF('Opening TB'!B:B,'Profit & Loss'!A78,'Opening TB'!E:E)-SUMIF('Opening TB'!B:B,'Profit & Loss'!A78,'Opening TB'!D:D) -> 0 | H78: =+(E78/G78)-100% -> #DIV/0! | I78: =+D78-F78 -> 0
A79: =ETB!B403 -> 101 | B79: =+ETB!C403 -> Reversal impairment intang fa | E79: =-SUMIF(ETB!$P$345:$R$679,'Profit & Loss'!A79,ETB!$Q$345:$Q$679)+SUMIF(ETB!$P$345:$R$679,'Profit & Loss'!A79,ETB!$R$345:$R$679) -> 0 | G79: =SUMIF('Opening TB'!B:B,'Profit & Loss'!A79,'Opening TB'!E:E)-SUMIF('Opening TB'!B:B,'Profit & Loss'!A79,'Opening TB'!D:D) -> 0 | H79: =+(E79/G79)-100% -> #DIV/0! | I79: =+D79-F79 -> 0
A80: =ETB!B404 -> 102 | B80: =+ETB!C404 -> Reversal impairment tang fa | E80: =-SUMIF(ETB!$P$345:$R$679,'Profit & Loss'!A80,ETB!$Q$345:$Q$679)+SUMIF(ETB!$P$345:$R$679,'Profit & Loss'!A80,ETB!$R$345:$R$679) -> 0 | G80: =SUMIF('Opening TB'!B:B,'Profit & Loss'!A80,'Opening TB'!E:E)-SUMIF('Opening TB'!B:B,'Profit & Loss'!A80,'Opening TB'!D:D) -> 0 | H80: =+(E80/G80)-100% -> #DIV/0! | I80: =+D80-F80 -> 0
A81: =ETB!B405 -> 103 | B81: =+ETB!C405 -> Exceptional items | E81: =-SUMIF(ETB!$P$345:$R$679,'Profit & Loss'!A81,ETB!$Q$345:$Q$679)+SUMIF(ETB!$P$345:$R$679,'Profit & Loss'!A81,ETB!$R$345:$R$679) -> 0 | G81: =SUMIF('Opening TB'!B:B,'Profit & Loss'!A81,'Opening TB'!E:E)-SUMIF('Opening TB'!B:B,'Profit & Loss'!A81,'Opening TB'!D:D) -> 0 | H81: =+(E81/G81)-100% -> #DIV/0! | I81: =+D81-F81 -> 0
A82: =ETB!B406 -> 104 | B82: =+ETB!C406 -> Gain/loss on revaln of assets | E82: =-SUMIF(ETB!$P$345:$R$679,'Profit & Loss'!A82,ETB!$Q$345:$Q$679)+SUMIF(ETB!$P$345:$R$679,'Profit & Loss'!A82,ETB!$R$345:$R$679) -> 0 | G82: =SUMIF('Opening TB'!B:B,'Profit & Loss'!A82,'Opening TB'!E:E)-SUMIF('Opening TB'!B:B,'Profit & Loss'!A82,'Opening TB'!D:D) -> 0 | H82: =+(E82/G82)-100% -> #DIV/0! | I82: =+D82-F82 -> 0
A83: =ETB!B407 -> 107 | B83: =+ETB!C407 -> Gain/loss on revaln of assets | E83: =-SUMIF(ETB!$P$345:$R$679,'Profit & Loss'!A83,ETB!$Q$345:$Q$679)+SUMIF(ETB!$P$345:$R$679,'Profit & Loss'!A83,ETB!$R$345:$R$679) -> 0 | G83: =SUMIF('Opening TB'!B:B,'Profit & Loss'!A83,'Opening TB'!E:E)-SUMIF('Opening TB'!B:B,'Profit & Loss'!A83,'Opening TB'!D:D) -> 0 | H83: =+(E83/G83)-100% -> #DIV/0! | I83: =+D83-F83 -> 0
A84: =ETB!B408 -> 109 | B84: =+ETB!C408 -> Shares in group indertakings | E84: =-SUMIF(ETB!$P$345:$R$679,'Profit & Loss'!A84,ETB!$Q$345:$Q$679)+SUMIF(ETB!$P$345:$R$679,'Profit & Loss'!A84,ETB!$R$345:$R$679) -> 0 | G84: =SUMIF('Opening TB'!B:B,'Profit & Loss'!A84,'Opening TB'!E:E)-SUMIF('Opening TB'!B:B,'Profit & Loss'!A84,'Opening TB'!D:D) -> 0 | H84: =+(E84/G84)-100% -> #DIV/0! | I84: =+D84-F84 -> 0
A85: =ETB!B409 -> 110 | B85: =+ETB!C409 -> Interest in associate | E85: =-SUMIF(ETB!$P$345:$R$679,'Profit & Loss'!A85,ETB!$Q$345:$Q$679)+SUMIF(ETB!$P$345:$R$679,'Profit & Loss'!A85,ETB!$R$345:$R$679) -> 0 | G85: =SUMIF('Opening TB'!B:B,'Profit & Loss'!A85,'Opening TB'!E:E)-SUMIF('Opening TB'!B:B,'Profit & Loss'!A85,'Opening TB'!D:D) -> 0 | H85: =+(E85/G85)-100% -> #DIV/0! | I85: =+D85-F85 -> 0
A86: =ETB!B410 -> 111 | B86: =+ETB!C410 -> Interest in joint venture | E86: =-SUMIF(ETB!$P$345:$R$679,'Profit & Loss'!A86,ETB!$Q$345:$Q$679)+SUMIF(ETB!$P$345:$R$679,'Profit & Loss'!A86,ETB!$R$345:$R$679) -> 0 | G86: =SUMIF('Opening TB'!B:B,'Profit & Loss'!A86,'Opening TB'!E:E)-SUMIF('Opening TB'!B:B,'Profit & Loss'!A86,'Opening TB'!D:D) -> 0 | H86: =+(E86/G86)-100% -> #DIV/0! | I86: =+D86-F86 -> 0
... A92: =ETB!B416 -> 119 | B92: =+ETB!C416 -> Other fixed asset invert-UnFII | E92: =-SUMIF(ETB!$P$345:$R$679,'Profit & Loss'!A92,ETB!$Q$345:$Q$679)+SUMIF(ETB!$P$345:$R$679,'Profit & Loss'!A92,ETB!$R$345:$R$679) -> 0 | G92: =SUMIF('Opening TB'!B:B,'Profit & Loss'!A92,'Opening TB'!E:E)-SUMIF('Opening TB'!B:B,'Profit & Loss'!A92,'Opening TB'!D:D) -> 0 | H92: =+(E92/G92)-100% -> #DIV/0! | I92: =+D92-F92 -> 0
A93: =ETB!B417 -> 120 | B93: =+ETB!C417 -> No Descriptions | G93: =SUMIF('Opening TB'!B:B,'Profit & Loss'!A93,'Opening TB'!E:E)-SUMIF('Opening TB'!B:B,'Profit & Loss'!A93,'Opening TB'!D:D) -> 0 | H93: =+(E93/G93)-100% -> #DIV/0! | I93: =+D93-F93 -> 0
A94: =ETB!B418 -> 121 | B94: =+ETB!C418 -> No Descriptions | E94: =-SUMIF(ETB!$P$345:$R$679,'Profit & Loss'!A94,ETB!$Q$345:$Q$679)+SUMIF(ETB!$P$345:$R$679,'Profit & Loss'!A94,ETB!$R$345:$R$679) -> 0 | G94: =SUMIF('Opening TB'!B:B,'Profit & Loss'!A94,'Opening TB'!E:E)-SUMIF('Opening TB'!B:B,'Profit & Loss'!A94,'Opening TB'!D:D) -> 0 | H94: =+(E94/G94)-100% -> #DIV/0! | I94: =+D94-F94 -> 0
A95: =ETB!B419 -> 122 | B95: =+ETB!C419 -> No Descriptions | E95: =-SUMIF(ETB!$P$345:$R$679,'Profit & Loss'!A95,ETB!$Q$345:$Q$679)+SUMIF(ETB!$P$345:$R$679,'Profit & Loss'!A95,ETB!$R$345:$R$679) -> 0 | G95: =SUMIF('Opening TB'!B:B,'Profit & Loss'!A95,'Opening TB'!E:E)-SUMIF('Opening TB'!B:B,'Profit & Loss'!A95,'Opening TB'!D:D) -> 0 | H95: =+(E95/G95)-100% -> #DIV/0! | I95: =+D95-F95 -> 0
A96: =ETB!B420 -> 127 | B96: =+ETB!C420 -> Exceptional items | E96: =-SUMIF(ETB!$P$345:$R$679,'Profit & Loss'!A96,ETB!$Q$345:$Q$679)+SUMIF(ETB!$P$345:$R$679,'Profit & Loss'!A96,ETB!$R$345:$R$679) -> 0 | G96: =SUMIF('Opening TB'!B:B,'Profit & Loss'!A96,'Opening TB'!E:E)-SUMIF('Opening TB'!B:B,'Profit & Loss'!A96,'Opening TB'!D:D) -> 0 | H96: =+(E96/G96)-100% -> #DIV/0! | I96: =+D96-F96 -> 0
A97: =ETB!B421 -> 130 | B97: =+ETB!C421 -> Deposit account interest | E97: =-SUMIF(ETB!$P$345:$R$679,'Profit & Loss'!A97,ETB!$Q$345:$Q$679)+SUMIF(ETB!$P$345:$R$679,'Profit & Loss'!A97,ETB!$R$345:$R$679) -> 0 | G97: =SUMIF('Opening TB'!B:B,'Profit & Loss'!A97,'Opening TB'!E:E)-SUMIF('Opening TB'!B:B,'Profit & Loss'!A97,'Opening TB'!D:D) -> 0 | H97: =+(E97/G97)-100% -> #DIV/0! | I97: =+D97-F97 -> 0
A98: =ETB!B422 -> 131 | B98: =+ETB!C422 -> No Descriptions | E98: =-SUMIF(ETB!$P$345:$R$679,'Profit & Loss'!A98,ETB!$Q$345:$Q$679)+SUMIF(ETB!$P$345:$R$679,'Profit & Loss'!A98,ETB!$R$345:$R$679) -> 0 | G98: =SUMIF('Opening TB'!B:B,'Profit & Loss'!A98,'Opening TB'!E:E)-SUMIF('Opening TB'!B:B,'Profit & Loss'!A98,'Opening TB'!D:D) -> 0 | H98: =+(E98/G98)-100% -> #DIV/0! | I98: =+D98-F98 -> 0
A99: =ETB!B423 -> 132 | B99: =+ETB!C423 -> No Descriptions | E99: =-SUMIF(ETB!$P$345:$R$679,'Profit & Loss'!A99,ETB!$Q$345:$Q$679)+SUMIF(ETB!$P$345:$R$679,'Profit & Loss'!A99,ETB!$R$345:$R$679) -> 0 | G99: =SUMIF('Opening TB'!B:B,'Profit & Loss'!A99,'Opening TB'!E:E)-SUMIF('Opening TB'!B:B,'Profit & Loss'!A99,'Opening TB'!D:D) -> 0 | H99: =+(E99/G99)-100% -> #DIV/0! | I99: =+D99-F99 -> 0
A100: =ETB!B424 -> 133 | B100: =+ETB!C424 -> No Descriptions | E100: =-SUMIF(ETB!$P$345:$R$679,'Profit & Loss'!A100,ETB!$Q$345:$Q$679)+SUMIF(ETB!$P$345:$R$679,'Profit & Loss'!A100,ETB!$R$345:$R$679) -> 0 | G100: =SUMIF('Opening TB'!B:B,'Profit & Loss'!A100,'Opening TB'!E:E)-SUMIF('Opening TB'!B:B,'Profit & Loss'!A100,'Opening TB'!D:D) -> 0 | H100: =+(E100/G100)-100% -> #DIV/0! | I100: =+D100-F100 -> 0
A101: =ETB!B425 -> 140 | B101: =+ETB!C425 -> Curr asset inv income | E101: =-SUMIF(ETB!$P$345:$R$679,'Profit & Loss'!A101,ETB!$Q$345:$Q$679)+SUMIF(ETB!$P$345:$R$679,'Profit & Loss'!A101,ETB!$R$345:$R$679) -> 0 | G101: =SUMIF('Opening TB'!B:B,'Profit & Loss'!A101,'Opening TB'!E:E)-SUMIF('Opening TB'!B:B,'Profit & Loss'!A101,'Opening TB'!D:D) -> 0 | H101: =+(E101/G101)-100% -> #DIV/0! | I101: =+D101-F101 -> 0
A102: =ETB!B426 -> 141 | B102: =+ETB!C426 -> No Descriptions | E102: =-SUMIF(ETB!$P$345:$R$679,'Profit & Loss'!A102,ETB!$Q$345:$Q$679)+SUMIF(ETB!$P$345:$R$679,'Profit & Loss'!A102,ETB!$R$345:$R$679) -> 0 | G102: =SUMIF('Opening TB'!B:B,'Profit & Loss'!A102,'Opening TB'!E:E)-SUMIF('Opening TB'!B:B,'Profit & Loss'!A102,'Opening TB'!D:D) -> 0 | H102: =+(E102/G102)-100% -> #DIV/0! | I102: =+D102-F102 -> 0
A103: =ETB!B427 -> 141 | B103: =+ETB!C427 -> No Descriptions | E103: =-SUMIF(ETB!$P$345:$R$679,'Profit & Loss'!A103,ETB!$Q$345:$Q$679)+SUMIF(ETB!$P$345:$R$679,'Profit & Loss'!A103,ETB!$R$345:$R$679) -> 0 | G103: =SUMIF('Opening TB'!B:B,'Profit & Loss'!A103,'Opening TB'!E:E)-SUMIF('Opening TB'!B:B,'Profit & Loss'!A103,'Opening TB'!D:D) -> 0 | H103: =+(E103/G103)-100% -> #DIV/0! | I103: =+D103-F103 -> 0
A104: =ETB!B428 -> 143 | B104: =+ETB!C428 -> No Descriptions | E104: =-SUMIF(ETB!$P$345:$R$679,'Profit & Loss'!A104,ETB!$Q$345:$Q$679)+SUMIF(ETB!$P$345:$R$679,'Profit & Loss'!A104,ETB!$R$345:$R$679) -> 0 | G104: =SUMIF('Opening TB'!B:B,'Profit & Loss'!A104,'Opening TB'!E:E)-SUMIF('Opening TB'!B:B,'Profit & Loss'!A104,'Opening TB'!D:D) -> 0 | H104: =+(E104/G104)-100% -> #DIV/0! | I104: =+D104-F104 -> 0
A105: =ETB!B429 -> 145 | B105: =+ETB!C429 -> Exceptional items | E105: =-SUMIF(ETB!$P$345:$R$679,'Profit & Loss'!A105,ETB!$Q$345:$Q$679)+SUMIF(ETB!$P$345:$R$679,'Profit & Loss'!A105,ETB!$R$345:$R$679) -> 0 | G105: =SUMIF('Opening TB'!B:B,'Profit & Loss'!A105,'Opening TB'!E:E)-SUMIF('Opening TB'!B:B,'Profit & Loss'!A105,'Opening TB'!D:D) -> 0 | H105: =+(E105/G105)-100% -> #DIV/0! | I105: =+D105-F105 -> 0
... A147: =ETB!B471 -> 213 | B147: =+ETB!C471 -> Impairment losses - tang f a | E147: =-SUMIF(ETB!$P$345:$R$679,'Profit & Loss'!A147,ETB!$Q$345:$Q$679)+SUMIF(ETB!$P$345:$R$679,'Profit & Loss'!A147,ETB!$R$345:$R$679) -> 0 | G147: =SUMIF('Opening TB'!B:B,'Profit & Loss'!A147,'Opening TB'!E:E)-SUMIF('Opening TB'!B:B,'Profit & Loss'!A147,'Opening TB'!D:D) -> 0 | H147: =+(E147/G147)-100% -> #DIV/0! | I147: =+D147-F147 -> 0
A148: =ETB!B472 -> 214 | B148: =+ETB!C472 -> Exceptional items | E148: =-SUMIF(ETB!$P$345:$R$679,'Profit & Loss'!A148,ETB!$Q$345:$Q$679)+SUMIF(ETB!$P$345:$R$679,'Profit & Loss'!A148,ETB!$R$345:$R$679) -> 0 | G148: =SUMIF('Opening TB'!B:B,'Profit & Loss'!A148,'Opening TB'!E:E)-SUMIF('Opening TB'!B:B,'Profit & Loss'!A148,'Opening TB'!D:D) -> 0 | H148: =+(D148/F148)-100% -> #DIV/0! | I148: =+D148-F148 -> 0
A149: =ETB!B473 -> 215 | B149: =+ETB!C473 -> Gain/loss on revaln of assets | E149: =-SUMIF(ETB!$P$345:$R$679,'Profit & Loss'!A149,ETB!$Q$345:$Q$679)+SUMIF(ETB!$P$345:$R$679,'Profit & Loss'!A149,ETB!$R$345:$R$679) -> 0 | G149: =SUMIF('Opening TB'!B:B,'Profit & Loss'!A149,'Opening TB'!E:E)-SUMIF('Opening TB'!B:B,'Profit & Loss'!A149,'Opening TB'!D:D) -> 0 | H149: =+(D149/F149)-100% -> #DIV/0! | I149: =+D149-F149 -> 0
A150: =ETB!B474 -> 220 | B150: =+ETB!C474 -> Director's remuneration | E150: =-SUMIF(ETB!$P$345:$R$679,'Profit & Loss'!A150,ETB!$Q$345:$Q$679)+SUMIF(ETB!$P$345:$R$679,'Profit & Loss'!A150,ETB!$R$345:$R$679) -> 0 | G150: =SUMIF('Opening TB'!B:B,'Profit & Loss'!A150,'Opening TB'!E:E)-SUMIF('Opening TB'!B:B,'Profit & Loss'!A150,'Opening TB'!D:D) -> 0 | H150: =+(D150/F150)-100% -> #DIV/0! | I150: =+D150-F150 -> 0
G151: =SUMIF('Opening TB'!B:B,'Profit & Loss'!A151,'Opening TB'!E:E)-SUMIF('Opening TB'!B:B,'Profit & Loss'!A151,'Opening TB'!D:D) -> 0
A152: ` | G152: 0 | H152: 1 | I152: =+D152-F152 -> 0
E153: =SUM(E67:E152) -> 41159.05 | G153: =SUM(G67:G152) -> 0
E154: =+E63+E153 -> 60684.22 | G154: =+G63+G153 -> 0
B155: Expenditure
A156: =ETB!B475 -> 221 | B156: =+ETB!C475 -> Wages | D156: =SUMIF(ETB!$P$345:$R$679,'Profit & Loss'!A156,ETB!$Q$345:$Q$679)-SUMIF(ETB!$P$345:$R$679,'Profit & Loss'!A156,ETB!$R$345:$R$679) -> 0 | F156: =SUMIF('Opening TB'!B:B,'Profit & Loss'!A156,'Opening TB'!D:D)-SUMIF('Opening TB'!B:B,'Profit & Loss'!A156,'Opening TB'!E:E) -> 0 | H156: =+(D156/F156)-100% -> #DIV/0! | I156: =+D156-F156 -> 0
...

Sheet Balance Sheet
B2: Client : | C2: =Index!C2 -> Forest Car Company Ltd | E2: Prepared by : | F2: =Info!C8 -> Aratee | G2: Date : | H2: =Index!J2 -> 45343
B3: Year end : | C3: =Index!C3 -> 45260 | E3: Reviewed by : | F3: =Info!C11 -> Mitesh | G3: Date : | H3: =Index!J3 -> 45352
B5: Balance Sheet
B7: Particulars | D7: =+'Profit & Loss'!D7 -> 45260 | F7: =Info!E6 -> NA | H7: Reference
D8: £ | E8: £ | F8: £ | G8: £
B10: FIXED ASSETS
B11: Intangible assets | E11: =+'F - Fixed Assets'!D9 -> 0 | G11: =+'F - Fixed Assets'!E9 -> 0 | H11: F1
B12: Tangible assets | E12: =+'F - Fixed Assets'!D11 -> 2079.8135 | G12: =+'F - Fixed Assets'!E11 -> 0 | H12: F2
B13: Investments | E13: =+'F - Fixed Assets'!D13 -> 0 | G13: =+'F - Fixed Assets'!E13 -> 0 | H13: F5
B15: CURRENT ASSETS
B16: Stock | D16: =+'C1 - Stock'!G13 -> 44938 | F16: ='C1 - Stock'!H13 -> 0 | H16: C1
B17: Debtors | D17: =+'C2 - Debtors'!G25 -> 5200 | F17: ='C2 - Debtors'!H25 -> 0 | H17: C2
B18: Cash at bank and in hand | D18: =+'C3 - Bank & Cash'!G21 -> 95054.43 | F18: =+'C3 - Bank & Cash'!H21 -> 0 | H18: C3
D20: =SUM(D16:D19) -> 145192.43 | F20: =SUM(F16:F19) -> 0
B22: CREDITORS
B23: Amounts falling due within one year | D23: =+'C4 - Creditors'!G39 -> 141199.37 | F23: =+'C4 - Creditors'!H39 -> 0 | H23: C4
B25: NET CURRENT ASSETS / (LIABILITIES) | E25: =+D20-D23 -> 3993.06 | G25: =+F20-F23 -> 0
B27: TOTAL ASSETS LESS CURRENT LIABILITIES | E27: =SUM(E11:E26) -> 6072.8735 | G27: =SUM(G11:G26) -> 0
B30: CREDITORS
B31: Amount falling due after more than one year | E31: =-+'L - Long Term Loans'!F15 -> 0 | G31: =-+'L - Long Term Loans'!G15 -> 0 | H31: L
B33: PROVISION FOR LIABILITIES
B34: Deferred tax | E34: =-+'D - Deferred tax'!F11 -> 0 | G34: =-+'D - Deferred tax'!G11 -> 0 | H34: D
B36: NET ASSETS | E36: =SUM(E27:E35) -> 6072.8735 | G36: =SUM(G27:G35) -> 0
B39: CAPITAL AND RESERVES
B40: Called up Share capital | E40: ='E - Share capital'!G19 -> 100 | G40: ='E - Share capital'!H19 -> 0 | H40: E
B41: Profit & loss Account | E41: =+'P - Reserves'!F15 -> 5972.8735 | G41: =+'P - Reserves'!G15 -> 0 | H41: P
B43: SHAREHOLDER'S FUND | E43: =SUM(E40:E42) -> 6072.8735 | G43: =SUM(G40:G42) -> 0
E46: =+E43-E36 -> -5.9844751e-10 | G46: =+G43-G36 -> 0
A49: Index Link

Sheet F - Fixed Assets
B2: Client : | C2: =Index!C2 -> Forest Car Company Ltd | D2: Prepared by : | E2: =Info!C8 -> Aratee | F2: Date : | G2: =Index!J2 -> 45343
B3: Year end : | C3: =Index!C3 -> 45260 | D3: Reviewed by : | E3: =Info!C11 -> Mitesh | F3: Date : | G3: =Index!J3 -> 45352
B5: Lead Schedule - Fixed Assets
B7: Particulars | D7: ='Profit & Loss'!D7:E7 -> 45260 | E7: =Info!E6 -> NA
B9: Intangible | D9: =+'F1 - Intangible FA'!G26 -> 0 | E9: ='F1 - Intangible FA'!G28 -> 0 | F9: F1
B11: Tangible | D11: =+'F2 - Tangible FA'!G26 -> 2079.8135 | E11: ='F2 - Tangible FA'!G28 -> 0 | F11: F2
B13: Investments | D13: =+'F5 - Investments'!F15 -> 0 | E13: =+'F5 - Investments'!G15 -> 0
B15: Total | D15: =SUM(D9:D13) -> 2079.8135 | E15: =SUM(E9:E13) -> 0

Sheet F1 - Intangible FA
B2: Client : | C2: =Index!C2 -> Forest Car Company Ltd | I2: Prepared by : | J2: =Index!H2 -> Aratee | K2: Date : | L2: =Index!J2 -> 45343
B3: Year end : | C3: =Index!C3 -> 45260 | I3: Reviewed by : | J3: =Index!H3 -> Mitesh | K3: Date : | L3: =Index!J3 -> 45352
B5: Fixed Assets - Intangible
B7: Particulars | D7: Goodwill | E7: Copyright | F7: Patent | G7: Total
D8: £ | E8: £ | F8: £ | G8: £
B10: COST
B11: Opening | E11: 0 | F11: 0 | G11: =SUM(D11:F11) -> 0
B12: Addition | D12: =ETB!Q12 -> 0 | E12: 0 | F12: 0 | G12: =SUM(D12:F12) -> 0
B13: Disposal | D13: 0 | E13: 0 | F13: 0 | G13: =SUM(D13:F13) -> 0
B15: Closing | D15: =+D11+D12-D13 -> 0 | E15: =+E11+E12-E13 -> 0 | F15: =+F11+F12-F13 -> 0 | G15: =+G11+G12-G13 -> 0
B18: Amortisation
B19: Opening | E19: 0 | F19: 0 | G19: =SUM(D19:F19) -> 0
B20: Charge for the year | D20: =D15/D30 -> 0 | E20: =E15/E30 -> 0 | F20: =F15/F30 -> 0 | G20: =SUM(D20:F20) -> 0
B21: Eliminated on disposal | D21: 0 | E21: 0 | F21: 0 | G21: =SUM(D21:F21) -> 0
B23: Closing | D23: =+D19+D20-D21 -> 0 | E23: =+E19+E20-E21 -> 0 | F23: =+F19+F20-F21 -> 0 | G23: =+G19+G20-G21 -> 0
B25: NET BOOK VALUE
B26: Closing | D26: =+D15-D23 -> 0 | E26: =+E15-E23 -> 0 | F26: =+F15-F23 -> 0 | G26: =+G15-G23 -> 0
B28: Opening | D28: =+D11-D19 -> 0 | E28: =+E11-E19 -> 0 | F28: =+F11-F19 -> 0 | G28: =+G11-G19 -> 0
B30: Amortised over no. of years : | D30: 10 | E30: 10 | F30: 10

Sheet F2 - Tangible FA
B1: =+'Profit & Loss'!#REF! -> #REF!
B2: Client : | D2: =Index!C2 -> Forest Car Company Ltd | G2: Prepared by : | H2: =Index!H2 -> Aratee | I2: Date : | J2: =Index!J2 -> 45343
B3: Year end : | D3: =Index!C3 -> 45260 | G3: Reviewed by : | H3: =Index!H3 -> Mitesh | I3: Date : | J3: =Index!J3 -> 45352
B5: Fixed Assets - Tangible
B7: Particulars | C7: =+'F4 - FAR'!A9 -> Plant and Machinery | D7: =+'F4 - FAR'!A19 -> Fixtures and Fittings | E7: =+'F4 - FAR'!A31 -> Motor Vehicles | F7: Computer Equipment | G7: Total | I7: F4 - FAR
C8: £ | D8: £ | E8: £ | F8: £ | G8: £
B9: Rate of Depreciation | C9: ='F4 - FAR'!D11 -> 0.2 | D9: ='F4 - FAR'!D21 -> 0.2 | E9: ='F4 - FAR'!D33 -> 0.2 | F9: ='F4 - FAR'!D45 -> 0.2 | G9: -
B11: COST
B12: Opening | C12: =+'F4 - FAR'!E18 -> 0 | D12: =+'F4 - FAR'!E30 -> 0 | E12: =+'F4 - FAR'!E42 -> 0 | F12: =+'F4 - FAR'!E54 -> 0 | G12: =SUM(C12:F12) -> 0
B13: Addition | C13: =+'F4 - FAR'!F18 -> 0 | D13: =+'F4 - FAR'!F30 -> 599 | E13: =+'F4 - FAR'!F42 -> 0 | F13: =+'F4 - FAR'!F54 -> 1653.33 | G13: =SUM(C13:F13) -> 2252.33
B14: Disposal | C14: =+'F4 - FAR'!G18 -> 0 | D14: =+'F4 - FAR'!G30 -> 0 | E14: =+'F4 - FAR'!G42 -> 0 | F14: =+'F4 - FAR'!G54 -> 0 | G14: =SUM(C14:F14) -> 0
B16: Closing | C16: =SUM(C12:C15) -> 0 | D16: =SUM(D12:D15) -> 599 | E16: =SUM(E12:E15) -> 0 | F16: =SUM(F12:F15) -> 1653.33 | G16: =SUM(G12:G15) -> 2252.33
B18: DEPRECIATION
B19: Opening | C19: =+'F4 - FAR'!I18 -> 0 | D19: =+'F4 - FAR'!I30 -> 0 | E19: =+'F4 - FAR'!I42 -> 0 | F19: =+'F4 - FAR'!I54 -> 0 | G19: =SUM(C19:F19) -> 0
B20: Charge for the year | C20: =+'F4 - FAR'!J18 -> 0 | D20: =+'F4 - FAR'!J30 -> 89.85 | E20: =+'F4 - FAR'!J42 -> 0 | F20: =+'F4 - FAR'!J54 -> 82.6665 | G20: =SUM(C20:F20) -> 172.5165
B21: Eliminated on disposal | C21: =+'F4 - FAR'!K18 -> 0 | D21: =+'F4 - FAR'!K30 -> 0 | E21: =+'F4 - FAR'!K42 -> 0 | F21: =+'F4 - FAR'!K54 -> 0 | G21: =SUM(C21:F21) -> 0
B23: Closing | C23: =SUM(C19:C22) -> 0 | D23: =SUM(D19:D22) -> 89.85 | E23: =SUM(E19:E22) -> 0 | F23: =SUM(F19:F22) -> 82.6665 | G23: =SUM(G19:G22) -> 172.5165
B25: NET BOOK VALUE
B26: Closing | C26: =+C16-C23 -> 0 | D26: =+D16-D23 -> 509.15 | E26: =+E16-E23 -> 0 | F26: =+F16-F23 -> 1570.6635 | G26: =+G16-G23 -> 2079.8135
B28: Opening | C28: =+C12-C19 -> 0 | D28: =+D12-D19 -> 0 | E28: =+E12-E19 -> 0 | F28: =+F12-F19 -> 0 | G28: =+G12-G19 -> 0
B30: Depreciation Method : | C30: RBM | D30: RBM | E30: RBM | F30: RBM

Sheet F4 - FAR
B2: Client : | C2: =Index!C2 -> Forest Car Company Ltd | F2: Prepared by : | G2: =Index!H2 -> Aratee | H2: Date : | I2: =Index!J2 -> 45343
B3: Year end : | C3: =Index!C3 -> 45260 | F3: Reviewed by : | G3: =Index!H3 -> Mitesh | H3: Date : | I3: =Index!J3 -> 45352
B5: Fixed asset register
B7: Date | C7: Description | D7: Depn. % | E7: Cost | I7: Depreciation | M7: NBV
E8: Opening | F8: Additions | G8: Disposal | H8: Closing | I8: Opening | J8: Charge for year | K8: Eliminated on Disposal | L8: Closing | M8: =Info!C6 -> 45260 | N8: =Info!E6 -> NA
A9: =+B9 -> Plant and Machinery | B9: Plant and Machinery
C11: Opening B/F | D11: 0.2 | H11: =SUM(E11:G11) -> 0 | J11: =(H11-I11)*D11 -> 0 | L11: =SUM(I11:K11) -> 0 | M11: =H11-L11 -> 0 | N11: =E11-I11 -> 0
D12: 0.2 | H12: =SUM(E12:G12) -> 0 | J12: =(H12-I12)*D12 -> 0 | L12: =SUM(I12:K12) -> 0 | M12: =H12-L12 -> 0 | N12: =E12-I12 -> 0
D13: 0.2 | H13: =SUM(E13:G13) -> 0 | J13: =(H13-I13)*D13 -> 0 | L13: =SUM(I13:K13) -> 0 | M13: =H13-L13 -> 0 | N13: =E13-I13 -> 0
D14: 0.2 | H14: =SUM(E14:G14) -> 0 | J14: =(H14-I14)*D14 -> 0 | L14: =SUM(I14:K14) -> 0 | M14: =H14-L14 -> 0 | N14: =E14-I14 -> 0
D15: 0.2 | H15: =SUM(E15:G15) -> 0 | J15: =(H15-I15)*D15 -> 0 | L15: =SUM(I15:K15) -> 0 | M15: =H15-L15 -> 0 | N15: =E15-I15 -> 0
D16: 0.2 | H16: =SUM(E16:G16) -> 0 | J16: =(H16-I16)*D16 -> 0 | L16: =SUM(I16:K16) -> 0 | M16: =H16-L16 -> 0 | N16: =E16-I16 -> 0
C18: Closing C/F | E18: =SUM(E11:E16) -> 0 | F18: =SUM(F11:F16) -> 0 | G18: =SUM(G11:G16) -> 0 | H18: =SUM(H11:H16) -> 0 | I18: =SUM(I11:I16) -> 0 | J18: =SUM(J11:J16) -> 0 | K18: =SUM(K11:K16) -> 0 | L18: =SUM(L11:L16) -> 0 | ... N18: =SUM(N11:N16) -> 0
A19: =+B19 -> Fixtures and Fittings | B19: Fixtures and Fittings
C21: Opening B/F | D21: 0.2 | H21: =SUM(E21:G21) -> 0 | J21: =(H21-I21)*D21 -> 0 | L21: =SUM(I21:K21) -> 0 | M21: =H21-L21 -> 0 | N21: =E21-I21 -> 0
B22: 44990 | C22: Fixtures and Fittings | D22: 0.2 | F22: =F74 -> 599 | H22: =SUM(E22:G22) -> 599 | J22: =(H22-I22)*D22/12*9 -> 89.85 | L22: =SUM(I22:K22) -> 89.85 | M22: =H22-L22 -> 509.15 | N22: =E22-I22 -> 0
D23: 0.2 | H23: =SUM(E23:G23) -> 0 | J23: =(H23-I23)*D23 -> 0 | L23: =SUM(I23:K23) -> 0 | M23: =H23-L23 -> 0 | N23: =E23-I23 -> 0
D24: 0.2 | H24: =SUM(E24:G24) -> 0 | J24: =(H24-I24)*D24 -> 0 | L24: =SUM(I24:K24) -> 0 | M24: =H24-L24 -> 0 | N24: =E24-I24 -> 0
D25: 0.2 | H25: =SUM(E25:G25) -> 0 | J25: =(H25-I25)*D25 -> 0 | L25: =SUM(I25:K25) -> 0 | M25: =H25-L25 -> 0 | N25: =E25-I25 -> 0
D26: 0.2 | H26: =SUM(E26:G26) -> 0 | J26: =(H26-I26)*D26 -> 0 | L26: =SUM(I26:K26) -> 0 | M26: =H26-L26 -> 0 | N26: =E26-I26 -> 0
D27: 0.2 | H27: =SUM(E27:G27) -> 0 | J27: =(H27-I27)*D27 -> 0 | L27: =SUM(I27:K27) -> 0 | M27: =H27-L27 -> 0 | N27: =E27-I27 -> 0
D28: 0.2 | H28: =SUM(E28:G28) -> 0 | J28: =(H28-I28)*D28 -> 0 | L28: =SUM(I28:K28) -> 0 | M28: =H28-L28 -> 0 | N28: =E28-I28 -> 0
C30: Closing C/F | E30: =SUM(E21:E28) -> 0 | F30: =SUM(F21:F28) -> 599 | G30: =SUM(G21:G28) -> 0 | H30: =SUM(H21:H28) -> 599 | I30: =SUM(I21:I28) -> 0 | J30: =SUM(J21:J28) -> 89.85 | K30: =SUM(K21:K28) -> 0 | L30: =SUM(L21:L28) -> 89.85 | ... N30: =SUM(N21:N28) -> 0
A31: =+B31 -> Motor Vehicles | B31: Motor Vehicles
C33: Opening B/F | D33: 0.2 | H33: =SUM(E33:G33) -> 0 | J33: =(H33-I33)*D33 -> 0 | L33: =SUM(I33:K33) -> 0 | M33: =H33-L33 -> 0 | N33: =E33-I33 -> 0
D34: 0.2 | H34: =SUM(E34:G34) -> 0 | J34: =(H34-I34)*D34 -> 0 | L34: =SUM(I34:K34) -> 0 | M34: =H34-L34 -> 0 | N34: =E34-I34 -> 0
D35: 0.2 | H35: =SUM(E35:G35) -> 0 | J35: =(H35-I35)*D35 -> 0 | L35: =SUM(I35:K35) -> 0 | M35: =H35-L35 -> 0 | N35: =E35-I35 -> 0
D36: 0.2 | H36: =SUM(E36:G36) -> 0 | J36: =(H36-I36)*D36 -> 0 | L36: =SUM(I36:K36) -> 0 | M36: =H36-L36 -> 0 | N36: =E36-I36 -> 0
D37: 0.2 | H37: =SUM(E37:G37) -> 0 | J37: =(H37-I37)*D37 -> 0 | L37: =SUM(I37:K37) -> 0 | M37: =H37-L37 -> 0 | N37: =E37-I37 -> 0
D38: 0.2 | H38: =SUM(E38:G38) -> 0 | J38: =(H38-I38)*D38 -> 0 | L38: =SUM(I38:K38) -> 0 | M38: =H38-L38 -> 0 | N38: =E38-I38 -> 0
D39: 0.2 | H39: =SUM(E39:G39) -> 0 | J39: =(H39-I39)*D39 -> 0 | L39: =SUM(I39:K39) -> 0 | M39: =H39-L39 -> 0 | N39: =E39-I39 -> 0
D40: 0.2 | H40: =SUM(E40:G40) -> 0 | J40: =(H40-I40)*D40 -> 0 | L40: =SUM(I40:K40) -> 0 | M40: =H40-L40 -> 0 | N40: =E40-I40 -> 0
C42: Closing C/F | E42: =SUM(E33:E41) -> 0 | F42: =SUM(F33:F41) -> 0 | G42: =SUM(G33:G41) -> 0 | H42: =SUM(H33:H41) -> 0 | I42: =SUM(I33:I41) -> 0 | J42: =SUM(J33:J41) -> 0 | K42: =SUM(K33:K41) -> 0 | L42: =SUM(L33:L41) -> 0 | ... N42: =SUM(N33:N41) -> 0
A43: =+B43 -> Computer Equipment | B43: Computer Equipment
C45: Opening B/F | D45: 0.2 | H45: =SUM(E45:G45) -> 0 | J45: =(H45-I45)*D45 -> 0 | L45: =SUM(I45:K45) -> 0 | M45: =H45-L45 -> 0 | N45: =E45-I45 -> 0
B46: 45174 | C46: Apple MPHE3B/A Laptop in Space Grey | D46: 0.2 | F46: =D65 -> 1653.33 | H46: =SUM(E46:G46) -> 1653.33 | J46: =(H46-I46)*D46/12*3 -> 82.6665 | L46: =SUM(I46:K46) -> 82.6665 | M46: =H46-L46 -> 1570.6635 | N46: =E46-I46 -> 0
D47: 0.2 | H47: =SUM(E47:G47) -> 0 | J47: =(H47-I47)*D47 -> 0 | L47: =SUM(I47:K47) -> 0 | M47: =H47-L47 -> 0 | N47: =E47-I47 -> 0
D48: 0.2 | H48: =SUM(E48:G48) -> 0 | J48: =(H48-I48)*D48 -> 0 | L48: =SUM(I48:K48) -> 0 | M48: =H48-L48 -> 0 | N48: =E48-I48 -> 0
D49: 0.2 | H49: =SUM(E49:G49) -> 0 | J49: =(H49-I49)*D49 -> 0 | L49: =SUM(I49:K49) -> 0 | M49: =H49-L49 -> 0 | N49: =E49-I49 -> 0
D50: 0.2 | H50: =SUM(E50:G50) -> 0 | J50: =(H50-I50)*D50 -> 0 | L50: =SUM(I50:K50) -> 0 | M50: =H50-L50 -> 0 | N50: =E50-I50 -> 0
D51: 0.2 | H51: =SUM(E51:G51) -> 0 | J51: =(H51-I51)*D51 -> 0 | L51: =SUM(I51:K51) -> 0 | M51: =H51-L51 -> 0 | N51: =E51-I51 -> 0
D52: 0.2 | H52: =SUM(E52:G52) -> 0 | J52: =(H52-I52)*D52 -> 0 | L52: =SUM(I52:K52) -> 0 | M52: =H52-L52 -> 0 | N52: =E52-I52 -> 0
C54: Closing C/F | E54: =SUM(E45:E53) -> 0 | F54: =SUM(F45:F53) -> 1653.33 | G54: =SUM(G45:G53) -> 0 | H54: =SUM(H45:H53) -> 1653.33 | I54: =SUM(I45:I53) -> 0 | J54: =SUM(J45:J53) -> 82.6665 | K54: =SUM(K45:K53) -> 0 | L54: =SUM(L45:L53) -> 82.6665 | ... N54: =SUM(N45:N53) -> 0
B56: Total | E56: =E18+E30+E42+E54 -> 0 | F56: =F18+F30+F42+F54 -> 2252.33 | G56: =G18+G30+G42+G54 -> 0 | H56: =H18+H30+H42+H54 -> 2252.33 | I56: =I18+I30+I42+I54 -> 0 | J56: =J18+J30+J42+J54 -> 172.5165 | K56: =K18+K30+K42+K54 -> 0 | L56: =L18+L30+L42+L54 -> 172.5165 | ... N56: =N18+N30+N42+N54 -> 0
M58: =+M56-'F2 - Tangible FA'!G26 -> 0
B60: Computer Equipment - Addition
B62: Date | C62: Supplier | D62: Net Amount | E62: Tax Amount | F62: Gross Amount | G62: Product
B63: 45174 | C63: AO.COM | D63: 1653.33 | E63: 330.67 | F63: 1984 | G63: Apple MPHE3B/A Laptop in Space Grey
D65: =SUM(D63:D64) -> 1653.33 | E65: =SUM(E63:E64) -> 330.67 | F65: =SUM(F63:F64) -> 1984
B69: Fixtures and Fittings - Addition
B71: Date | C71: Supplier | D71: Net Amount | E71: Tax Amount | F71: Gross Amount
B72: 44990 | C72: YOURE FURNISHED LTD | D72: 599 | E72: 0 | F72: 599
F74: =SUM(F72:F73) -> 599

Sheet F5 - Investments
B2: Client : | C2: =Index!C2 -> Forest Car Company Ltd | F2: Prepared by : | G2: =Index!H2 -> Aratee | H2: Date : | I2: =Index!J2 -> 45343
B3: Year end : | C3: =Index!C3 -> 45260 | F3: Reviewed by : | G3: =Index!H3 -> Mitesh | H3: Date : | I3: =Index!J3 -> 45352
B5: Investments
B7: Particulars | F7: =C3 -> 45260 | G7: =Info!E6 -> NA
B15: Total | E15: Total : | F15: =SUM(F8:F14) -> 0 | G15: =SUM(G8:G14) -> 0

Sheet C1 - Stock
B2: Client : | C2: =Index!C2 -> Forest Car Company Ltd | G2: Prepared by : | H2: =Info!C8 -> Aratee | I2: Date : | J2: =Index!J2 -> 45343
B3: Year end : | C3: =Index!C3 -> 45260 | G3: Reviewed by : | H3: =Info!C11 -> Mitesh | I3: Date : | J3: =Index!J3 -> 45352
B5: Lead Schedule - Stock
B7: Particulars | G7: =C3 -> 45260 | H7: =Info!E6 -> NA
B9: Stock | G9: =Journal!E62 -> 44938 | H9: ='Opening TB'!D63 -> 0
B11: Work-in Progress | G11: =H11 -> 0 | H11: ='Opening TB'!D64 -> 0
B13: Total | G13: =SUM(G9:G11) -> 44938 | H13: =SUM(H9:H11) -> 0
B17: Closing balance
B19: Sr No | C19: DATE | D19: SUPPLIER | E19: INV/REF NO | F19: MAKE | G19: REG NO. | H19: BUYING PRICE | I19: NON VAT
B20: 1 | C20: 44936 | D20: REDCORN | E20: STOCK SHEET FEB 23 | F20: MINI | G20: MA08GXO | H20: 800 | I20: 800
B21: 2 | C21: 45162 | D21: REDCORN | E21: VP QE AUG 23/18 | F21: VAUXHALL | G21: FL65RXX | H21: 5405 | I21: 5405
B22: 3 | C22: 45126 | D22: REDCORN | E22: VP QE AUG 23/40 | F22: NISSAN | G22: LR53HHL | H22: 1000 | I22: 1000
B23: 4 | C23: 45167 | D23: REDCORN | E23: VP QE AUG 23/72 | F23: VAUXHALL | G23: BF62KUX | H23: 1525 | I23: 1525
B24: 5 | C24: 45222 | D24: REDCORN | E24: VP QE NOV 23/13 | F24: VOLKSWAGON | G24: FE52KOJ | H24: 640 | I24: 640
B25: 6 | C25: 45238 | D25: REDCORN | E25: VP QE NOV 23/14 | F25: FORD | G25: FE59YBM | H25: 1850 | I25: 1850
B26: 7 | C26: 45217 | D26: REDCORN | E26: VP QE NOV 23/24 | F26: FORD | G26: GK10XCS | H26: 3785 | I26: 3785
B27: 8 | C27: 45222 | D27: REDCORN | E27: VP QE NOV 23/33 | F27: VAUXHALL | G27: HK62CGU | H27: 2665 | I27: 2665
B28: 9 | C28: 45198 | D28: REDCORN | E28: VP QE NOV 23/42 | F28: VAUXHALL | G28: LA56HVX | H28: 1250 | I28: 1250
B29: 10 | C29: 45217 | D29: REDCORN | E29: VP QE NOV 23/47 | F29: JAGUAR | G29: LM59FYV | H29: 710 | I29: 710
B30: 11 | C30: 45229 | D30: REDCORN | E30: VP QE NOV 23/49 | F30: VAUXHALL | G30: LR13RYF | H30: 2600 | I30: 2600
B31: 12 | C31: 45233 | D31: REDCORN | E31: VP QE NOV 23/63 | F31: LANDROVER | G31: RF53NXT | H31: 1225 | I31: 1225
... B36: 17 | C36: 45212 | D36: REDCORN | E36: VP QE NOV 23/86 | F36: RENAULT | G36: AK10MSY | H36: 620 | I36: 620
G38: =SUBTOTAL(3,G20:G36) -> 17 | H38: =SUBTOTAL(9,H20:H36) -> 44938 | I38: =SUBTOTAL(9,I20:I36) -> 44938

Sheet C2 - Debtors
B2: Client : | C2: =Index!C2 -> Forest Car Company Ltd | G2: Prepared by : | H2: =Index!H2 -> Aratee | J2: Date : | K2: =Index!J2 -> 45343
B3: Year end : | C3: =Index!C3 -> 45260 | G3: Reviewed by : | H3: =Index!H3 -> Mitesh | J3: Date : | K3: =Index!J3 -> 45352
B5: Lead Schedule - Debtors
B7: Particulars | F7: IRIS | G7: =C3 -> 45260 | H7: =Info!E6 -> NA
B9: =+'C2-1 - Trade debtors'!B5 -> Trade debtors | F9: =+ETB!B133 -> 586 | G9: =+'C2-1 - Trade debtors'!H28 -> 5200 | H9: ='Opening TB'!D65 -> 0 | I9: C2-1
B11: =+'C2-2-1 - Other Debtors'!B5 -> Other Debtors | F11: =+ETB!B140 -> 594 | G11: =+'C2-2-1 - Other Debtors'!G15 -> 0 | H11: ='Opening TB'!D66 -> 0 | I11: C2-2-1
B13: =+'C4-2 - VAT'!B5 -> VAT Liability | F13: =+ETB!B211 -> 735 | G13: =+'C4-2 - VAT'!G18 -> 0 | H13: ='Opening TB'!D72 -> 0 | I13: C4-2
B15: =+'C2-3 - Prepayments'!B5 -> Prepayments | F15: =+ETB!B150 -> 614 | G15: =+'C2-3 - Prepayments'!F18 -> 0 | H15: ='Opening TB'!D71 -> 0 | I15: C2-3
B17: Other debtors- CIS receivable | F17: =+ETB!B141 -> 595 | G17: ='C2-6 - CIS'!I13 -> 0 | H17: ='Opening TB'!D70 -> 0 | I17: C2-6
B19: Director-1 | G19: ='C4-7 - DCA'!N31 -> 0 | H19: ='Opening TB'!D67 -> 0
B21: Director-2 | G21: ='C4-7 - DCA'!K31 -> 0 | H21: ='Opening TB'!D68 -> 0
B23: Other debtors - inter company | F23: =+ETB!B142 -> 596 | G23: ='C2-5 - Other debtors-Inter co.'!H18 -> 0 | H23: ='Opening TB'!D69 -> 0 | I23: C2-5
B25: Total | G25: =SUM(G8:G24) -> 5200 | H25: =SUM(H8:H24) -> 0

Sheet C2-1 - Trade debtors
B2: Client : | C2: =Index!C2 -> Forest Car Company Ltd | F2: Prepared by : | G2: =Index!H2 -> Aratee | H2: Date: | I2: =Index!J2 -> 45343
B3: Year end : | C3: =Index!C3 -> 45260 | F3: Reviewed by : | G3: =Index!H3 -> Mitesh | H3: Date: | I3: =Index!J3 -> 45352
B5: Trade debtors
B7: Particulars | G7: Debit £ | H7: Credit £
B9: Opening Balance B/F | G9: ='C2 - Debtors'!H9 -> 0
B10: Current year sales booked | G10: =Journal!E16 -> 640214
B12: Trade debtors adjusted / Received
B13: Cash | H13: =Journal!E41 -> 71072.2
B14: DCA | H14: =Journal!E42 -> 1300
B16: Reversal of sales (Sales return)booked | H16: =Journal!F48 -> 12906
B18: Additional income booked which is incurred during sales | G18: =Journal!E52 -> 300
B20: Barclays BankA/c. No.: 30470120
B21: Bank Receipt | H21: ='C3-1-R - BR -1'!P384 -> 558116.8
B22: Bank Receipt on account | H22: ='C3-1-R - BR -1'!Q384 -> 2000
B23: Bank Payment | G23: ='C3-1-P - BP -1'!Z1333 -> 192
B24: Bank Payment - unidentified | G24: ='C3-1-P - BP -1'!AA1333 -> 12089
B26: Sales return shown as purchase | H26: =Journal!F106 -> 2200
B28: Closing Balance C/F | H28: =+G30-SUM(H10:H27) -> 5200 | I28: C2 - Debtors
B30: Total | G30: =SUM(G9:G29) -> 652795 | H30: =SUM(H9:H29) -> 652795
H34: =ETB!Q133-H28 -> -4.3655746e-11
B35: Closing balance
B37: MAKE | C37: REG NO. | D37: DATE SOLD | E37: SELLING AMOUNT | F37: MARGIN | G37: VAT | H37: SOLD TO | I37: INV NO | J37: STOCK | K37: BANK RECEIPT | L37: Closing
B38: VAUXHALL | C38: KV62UZP | D38: 45241 | E38: 2600 | F38: 700 | G38: 116.66667 | H38: ASHLEY BONFILED | I38: VS QE NOV-23-31 | J38: SOLD | L38: =E38 -> 2600
B39: LANDROVER | C39: BK58OHZ | D39: 45260 | E39: 2900 | F39: 1084 | G39: 180.66667 | H39: BEN CHAPMAN | I39: MISSING FOLDER INVOICE | J39: SOLD | K39: 300 | L39: =E39-K39 -> 2600
L41: =SUM(L38:L40) -> 5200
L43: =L41-H28 -> 0

Sheet C2-2-1 - Other Debtors
B2: Client : | C2: =Index!C2 -> Forest Car Company Ltd | F2: Prepared by : | G2: =Index!H2 -> Aratee | H2: Date : | I2: =Index!J2 -> 45343
B3: Year end : | C3: =Index!C3 -> 45260 | F3: Reviewed by : | G3: =Index!H3 -> Mitesh | H3: Date : | I3: =Index!J3 -> 45352
B5: Other Debtors
B7: Particulars | F7: Debit £ | G7: Credit £
B9: =+'C2-1 - Trade debtors'!B9 -> Opening Balance B/F | F9: ='C2 - Debtors'!H11 -> 0
B15: Closing Balance C/F | G15: =+F17-SUM(G9:G14) -> 0 | H15: C2 - Debtors
B17: Total | F17: =SUM(F9:F16) -> 0 | G17: =SUM(G9:G16) -> 0
G21: =+ETB!Q155-G15 -> 0

Sheet C2-3 - Prepayments
B2: Client : | C2: =Index!C2 -> Forest Car Company Ltd | F2: Prepared by : | G2: =Index!H2 -> Aratee | H2: Date : | I2: =Index!J2 -> 45343
B3: Year end : | C3: =Index!C3 -> 45260 | F3: Reviewed by : | G3: =Index!H3 -> Mitesh | H3: Date : | I3: =Index!J3 -> 45352
B5: Prepayments
B7: Particulars | F7: 2022 | G7: 2021
B18: Total | F18: =SUM(F8:F17) -> 0 | G18: =SUM(G8:G17) -> 0 | H18: C2 - Debtors

Sheet C2-4 - Accrued Income
B2: Client : | C2: =Index!C2 -> Forest Car Company Ltd | G2: Prepared by : | H2: =Index!H2 -> Aratee | I2: Date: | J2: =Index!J2 -> 45343
B3: Year end : | C3: =Index!C3 -> 45260 | G3: Reviewed by : | H3: =Index!H3 -> Mitesh | I3: Date: | J3: =Index!J3 -> 45352
B5: Other Debtors
B7: Particulars | G7: Debit £ | H7: Credit £
B9: =+'C2-1 - Trade debtors'!B9 -> Opening Balance B/F
B15: Closing balance | H15: =+G17-SUM(H9:H14) -> 0 | I15: C2 - Debtors
B17: Total | G17: =SUM(G8:G16) -> 0 | H17: =SUM(H8:H16) -> 0
H20: =H15-ETB!Q148-ETB!R148 -> 0

Sheet C2-5 - Other debtors-Inter co.
B2: Client : | C2: =Index!C2 -> Forest Car Company Ltd | G2: Prepared by : | H2: =Index!H2 -> Aratee | I2: Date: | J2: =Index!J2 -> 45343
B3: Year end : | C3: =Index!C3 -> 45260 | G3: Reviewed by : | H3: =Index!H3 -> Mitesh | I3: Date: | J3: =Index!J3 -> 45352
B5: Other Debtors - Inter company
B7: Particulars | G7: Debit £ | H7: Credit £
B9: Opening Balance B/F | G9: ='C2 - Debtors'!H23 -> 0
B18: Closing balance | H18: =+G20-SUM(H9:H17) -> 0 | I18: C2 - Debtors
B20: Total | G20: =SUM(G8:G19) -> 0 | H20: =SUM(H8:H19) -> 0

Sheet C2-6 - CIS
B2: Client : | C2: =Index!C2 -> Forest Car Company Ltd | F2: Prepared by : | G2: =Index!H2 -> Aratee | H2: Date : | I2: =Index!J2 -> 45343
B3: Year end : | C3: =Index!C3 -> 45260 | F3: Reviewed by : | G3: =Index!H3 -> Mitesh | H3: Date : | I3: =Index!J3 -> 45352
B5: Other Debtors - CIS
B7: Particulars | H7: Debit £ | I7: Credit £
B9: Opening Balance B/F | H9: ='C2 - Debtors'!H17 -> 0
B13: Closing Balance C/F | I13: =+H15-SUM(I9:I12) -> 0 | J13: C2 - Debtors
B15: Total | H15: =SUM(H8:H14) -> 0 | I15: =SUM(I8:I14) -> 0

Sheet C2-7 - Other debtors (3)
B2: Client : | C2: =Index!C2 -> Forest Car Company Ltd | F2: Prepared by : | G2: =Index!H2 -> Aratee | H2: Date: | I2: =Index!J2 -> 45343
B3: Year end : | C3: =Index!C3 -> 45260 | F3: Reviewed by : | G3: =Index!H3 -> Mitesh | H3: Date: | I3: =Index!J3 -> 45352
B5: Other Debtors - 3
B7: Particulars | H7: Debit £ | I7: Credit £
B9: =+'C2-1 - Trade debtors'!B9 -> Opening Balance B/F
B16: Closing balance | I16: =+H18-SUM(I9:I15) -> 0 | J16: C2 - Debtors
B18: Total | H18: =SUM(H8:H17) -> 0 | I18: =SUM(I8:I17) -> 0
I21: =+I16-ETB!Q134+ETB!R134 -> 0

Sheet Sales
B2: Client : | C2: =Index!C2 -> Forest Car Company Ltd | F2: Prepared by : | G2: =Info!C8 -> Aratee | H2: Date : | I2: =Index!J2 -> 45343 | AH2: Need to check next year bank
B3: Year end : | C3: =Index!C3 -> 45260 | F3: Reviewed by : | G3: =Info!C11 -> Mitesh | H3: Date : | I3: =Index!J3 -> 45352
B6: Sales summary as per VAT return
AB7: ='C3-1-R - BR -1'!P6 -> 0 | AC7: ='C3-1-R - BR -1'!Q6 -> 0
B8: Sr. No | C8: QE | D8: DATE | E8: SUPPLIER | F8: INV/REF NO | G8: MAKE | H8: REG NO. | I8: BUYING PRICE | J8: NON VAT | K8: STD NET | L8: VAT AMOUNT | M8: DATE SOLD | N8: SELLING AMOUNT | O8: MARGIN | P8: VAT | Q8: WAY OF PAYMENT | R8: SOLD TO | S8: POST CODE / ADDRESS | T8: INV NO | U8: STOCK | V8: Remarks | X8: Bank Payment | Y8: Additional | Z8: Reversal/Sales return | AA8: Duplicate | AB8: Bank receipt | AC8: Bank receipt on account | AD8: DCA | AE8: Cash | AF8: Purchase Return | AG8: Closing
B9: 216 | C9: 45231 | D9: 45170 | E9: CONNOR STROUD | F9: VP QE NOV 23/84 | G9: FORD | H9: AD07KNZ | I9: 1500 | J9: 1500 | K9: 0 | L9: 0 | M9: 45173 | N9: 1989 | O9: =N9-I9 -> 489 | P9: 81.5 | R9: CONNOR STROUD | S9: 211 FOREST GLADE | T9: VS QE NOV-23-65 | U9: SOLD | AB9: =N9 -> 1989 | AG9: =N9-SUM(Z9:AF9)+X9+Y9 -> 0
B10: 1 | C10: 44958 | D10: 44870 | E10: B BROWN | F10: VP FEB 23-11 | G10: CITREON | H10: DG10JCV | I10: 1500 | J10: 1500 | K10: 0 | L10: 0 | M10: 44900 | N10: 1750 | O10: =N10-I10 -> 250 | P10: 41.666667 | Q10: CASH N TRANSFER | R10: D.T.GROOM | S10: CF336ER | T10: VS FEB 23-11 | U10: SOLD | V10: Not found in stock sheet/A | AC10: 250 | AE10: 1500 | AG10: =N10-SUM(Z10:AF10)+X10+Y10 -> 0
B11: 210 | C11: 45231 | D11: 45149 | E11: SALLY GIRDLER | F11: VP QE NOV 23/45 | G11: FORD | H11: LM07FXE | I11: 1400 | J11: 1400 | K11: 0 | L11: 0 | M11: 45205 | N11: 1889 | O11: =N11-I11 -> 489 | P11: 81.5 | R11: ANTHONY CORINGTON | S11: 12 JUBILEE CRESCENT | T11: VS QE NOV-23-34 | U11: SOLD | AB11: =N11 -> 1889 | AG11: =N11-SUM(Z11:AF11)+X11+Y11 -> 0
B12: 2 | C12: 44958 | D12: 44871 | E12: SUNDRY PURCHASE VEHICLE | F12: VP FEB 23-1 | G12: VOLKSWAGON | H12: AJ04ZYS | I12: 1000 | J12: 1000 | K12: 0 | L12: 0 | M12: 44901 | N12: 1500 | O12: =N12-I12 -> 500 | P12: 83.333333 | Q12: TRANSFER | R12: CHLOE RUTTER | T12: VS FEB 23-1 | U12: SOLD | AB12: =N12 -> 1500 | AG12: =N12-SUM(Z12:AF12)+X12+Y12 -> 0
B13: 92 | C13: 45047 | D13: 44986 | E13: REDCORN | F13: VP QE MAY 23/53 | G13: VAUXHALL | H13: AJ11MDX | I13: 1400 | J13: 1400 | K13: 0 | L13: 0 | M13: 45001 | N13: 1989 | O13: =N13-I13 -> 589 | P13: 98.166667 | Q13: BANK TRANSFER | R13: DANNY LEE | S13: CM18 6HL | T13: VS QE MAY 23/55 | U13: SOLD | AB13: =N13 -> 1989 | AG13: =N13-SUM(Z13:AF13)+X13+Y13 -> 0
B14: 107 | C14: 45139 | D14: 45008 | E14: REDCORN | F14: VP QE MAY 23/67 | G14: PEUGEOT | H14: AJ12PUA | I14: 2000 | J14: 2000 | K14: 0 | L14: 0 | M14: 45101 | N14: 3350 | O14: =N14-I14 -> 1350 | P14: 225 | R14: T AGBAJE | T14: VS QE AUG 23-50 | U14: SOLD | AB14: =N14 -> 3350 | AG14: =N14-SUM(Z14:AF14)+X14+Y14 -> 0
B15: 3 | C15: 44958 | D15: 44872 | E15: ABDUL ALI | F15: VP FEB 23-23 | G15: VAUXHALL | H15: LM63RTU | I15: 3500 | J15: 3500 | K15: 0 | L15: 0 | M15: 45263 | N15: 3900 | O15: =N15-I15 -> 400 | P15: 66.666667 | Q15: TRANSFER | R15: MARQUEL EDWARDS | T15: VS FEB 23-23 | U15: SOLD | AB15: =N15 -> 3900 | AG15: =N15-SUM(Z15:AF15)+X15+Y15 -> 0
B16: 28 | C16: 44958 | D16: 44936 | E16: REDCORN | F16: VP FEB 23-29 | G16: VAUXHALL | H16: NC58EOO | I16: 700 | J16: 700 | K16: 0 | L16: 0 | M16: 44958 | N16: 1900 | O16: =N16-I16 -> 1200 | P16: 200 | Q16: TRANSFER | R16: KEIR HEMMANT | S16: CM59BZ | T16: VS FEB 23-29 | U16: SOLD | AB16: =N16 -> 1900 | AG16: =N16-SUM(Z16:AF16)+X16+Y16 -> 0
B17: 6 | C17: 44958 | D17: 44899 | E17: DAN WILLIAMS | F17: VP FEB 23-9 | G17: FORD | H17: CK59KKO | I17: 2500 | J17: 2500 | K17: 0 | L17: 0 | M17: 44937 | N17: 3000 | O17: =N17-I17 -> 500 | P17: 83.333333 | Q17: CASH N TRANSFER | R17: MARK ROWLEY | S17: HP279BQ | T17: VS FEB 23-9 | U17: SOLD | AB17: 250 | AE17: 2750 | AG17: =N17-SUM(Z17:AF17)+X17+Y17 -> 0
B18: 154 | C18: 45139 | D18: 45079 | E18: MISS J M BLADES | F18: VP QE AUG 23/71 | G18: VOLKSWAGON | H18: AU11YRV | I18: 2600 | J18: 2600 | K18: 0 | L18: 0 | M18: 45091 | N18: 3089 | O18: =N18-I18 -> 489 | P18: 81.5 | R18: MARK SAVILLE | T18: VS QE AUG 23-52 | U18: SOLD | AB18: =N18 -> 3089 | AG18: =N18-SUM(Z18:AF18)+X18+Y18 -> 0
B19: 7 | C19: 44958 | D19: 44900 | E19: REDCORN | F19: VP FEB 23-10 | G19: MINI | H19: CX62YSH | I19: 800 | J19: 800 | K19: 0 | L19: 0 | M19: 44915 | N19: 1500 | O19: =N19-I19 -> 700 | P19: 116.66667 | Q19: CASH N TRANSFER | R19: NICOLE SAWDEN | T19: VS FEB 23-10 | U19: SOLD | AB19: 550 | AE19: 950 | AG19: =N19-SUM(Z19:AF19)+X19+Y19 -> 0
B20: 20 | C20: 44958 | D20: 44911 | E20: PHILLIP MANSFIELD | F20: VP FEB 23-14 | G20: VAUXHALL | H20: DY59MME | I20: 250 | J20: 250 | K20: 0 | L20: 0 | M20: 44973 | N20: 589 | O20: =N20-I20 -> 339 | P20: 56.5 | Q20: TRANSFER | R20: BOEDAN GABRIEL TACHE | T20: VS FEB 23-14 | U20: SOLD | AB20: =N20 -> 589 | AG20: =N20-SUM(Z20:AF20)+X20+Y20 -> 0
B21: 11 | C21: 44958 | D21: 44900 | E21: DAVE | F21: VP FEB 23-4 | G21: VOLKSWAGON | H21: AV62LZF | I21: 3800 | J21: 3800 | K21: 0 | L21: 0 | M21: 44970 | N21: 4850 | O21: =N21-I21 -> 1050 | P21: 175 | Q21: TRANSFER | R21: LIAM BENFORD | S21: ME103QY | T21: VS FEB 23-4 | U21: SOLD | AB21: =N21 -> 4850 | AG21: =N21-SUM(Z21:AF21)+X21+Y21 -> 0
B22: 33 | C22: 44958 | D22: 44946 | E22: REDCORN | F22: VP FEB 23-5 | G22: PEUGEOT | H22: BD59PDV | I22: 2000 | J22: 2000 | K22: 0 | L22: 0 | M22: 44947 | N22: 2490 | O22: =N22-I22 -> 490 | P22: 81.666667 | Q22: CASH | R22: BOZHIDAL | T22: VS FEB 23-5 | U22: SOLD | AB22: =N22 -> 2490 | AG22: =N22-SUM(Z22:AF22)+X22+Y22 -> 0
B23: 199 | C23: 45231 | D23: 45170 | E23: DAVID R BROOKS | F23: VP QE NOV 23/88 | G23: FORD | H23: BF07ENX | I23: 600 | J23: 600 | K23: 0 | L23: 0 | M23: 45178 | N23: 989 | O23: =N23-I23 -> 389 | P23: 64.833333 | R23: MICHEAL BROWN | S23: 33 CHELMSFORD | T23: VS QE NOV-23-68 | U23: SOLD | AB23: =N23 -> 989 | AG23: =N23-SUM(Z23:AF23)+X23+Y23 -> 0
B24: 226 | C24: 45231 | D24: 45170 | E24: MAUREEN BALLER | F24: VP QE NOV 23/89 | G24: CITREON | H24: BF59UGE | I24: 2000 | J24: 2000 | K24: 0 | L24: 0 | M24: 45173 | N24: 2489 | O24: =N24-I24 -> 489 | P24: 81.5 | R24: JAY DERREGS | S24: 2 NEW SWINGAM | T24: VS QE NOV-23-69 | U24: SOLD | AB24: =N24 -> 2489 | AG24: =N24-SUM(Z24:AF24)+X24+Y24 -> 0
B25: 9 | C25: 44958 | D25: 44900 | E25: REDCORN | F25: VP FEB 23-24 | G25: TOYOTA | H25: LT60GNU | I25: 1400 | J25: 1400 | K25: 0 | L25: 0 | M25: 44945 | N25: 1989 | O25: =N25-I25 -> 589 | P25: 98.166667 | Q25: TRANSFER | R25: MARIANA VALENTINA DUMITRU | S25: AL100DS | T25: VS FEB 23-24 | U25: SOLD | AB25: =N25 -> 1989 | AG25: =N25-SUM(Z25:AF25)+X25+Y25 -> 0
B26: 10 | C26: 44958 | D26: 44900 | E26: JAMIE MAVALLY | F26: VP FEB 23-37 | G26: CITREON | H26: WU12XEV | I26: 1200 | J26: 1200 | K26: 0 | L26: 0 | M26: 44944 | N26: 1600 | O26: =N26-I26 -> 400 | P26: 66.666667 | Q26: TRANSFER | R26: DORREN VINCENT | T26: VS FEB 23-38 | U26: SOLD | AB26: =N26 -> 1600 | AG26: =N26-SUM(Z26:AF26)+X26+Y26 -> 0
B27: 12 | C27: 44958 | D27: 44901 | E27: REDCORN | F27: VP FEB 23-7 | G27: SUZUKI | H27: CK03TZJ | I27: 3500 | J27: 3500 | K27: 0 | L27: 0 | M27: 44909 | N27: 4109 | O27: =N27-I27 -> 609 | P27: 101.5 | Q27: TRANSFER | R27: HELEN BARNES | S27: DA118DP | T27: VS FEB 23-7 | U27: SOLD | AB27: =N27 -> 4109 | AG27: =N27-SUM(Z27:AF27)+X27+Y27 -> 0
B28: 36 | C28: 44958 | D28: 44969 | E28: REDCORN | F28: VP FEB 23-12 | G28: PEUGEOT | H28: DK55WDD | I28: 800 | J28: 800 | K28: 0 | L28: 0 | M28: 44978 | N28: 1000 | O28: =N28-I28 -> 200 | P28: 33.333333 | Q28: CASH | R28: KHALED ABDALLAH FTIRICH | S28: LU11DL | T28: VS FEB 23-12 | U28: SOLD | AE28: =N28 -> 1000 | AG28: =N28-SUM(Z28:AF28)+X28+Y28 -> 0
B29: 13 | C29: 44958 | D29: 44901 | E29: REDCORN | F29: VP FEB 23-17 | G29: VAUXHALL | H29: FP12ZKK | I29: 800 | J29: 800 | K29: 0 | L29: 0 | M29: 44915 | N29: 1200 | O29: =N29-I29 -> 400 | P29: 66.666667 | Q29: CASH | R29: RIFAT KARAMANOGLU | S29: SE233TJ | T29: VS FEB 23-17 | U29: SOLD | AE29: =N29 -> 1200 | AG29: =N29-SUM(Z29:AF29)+X29+Y29 -> 0
B30: 38 | C30: 44958 | D30: 44961 | E30: MALLARDS FINANCE | F30: VP FEB 23-6 | G30: FORD | H30: BV13RVJ | I30: 450 | J30: 450 | K30: 0 | L30: 0 | M30: 44965 | N30: 3489 | O30: =N30-I30 -> 3039 | P30: 506.5 | Q30: TRANSFER | R30: AMY SAXON | S30: CM16BQ | T30: VS FEB 23-6 | U30: SOLD | AB30: =N30 -> 3489 | AG30: =N30-SUM(Z30:AF30)+X30+Y30 -> 0
B31: 23 | C31: 44958 | D31: 44935 | E31: MALLARDS FINANCE | F31: VP FEB 23-18 | G31: NISSAN | H31: FV11HCX | I31: 500 | J31: 500 | K31: 0 | L31: 0 | M31: 44978 | N31: 1200 | O31: =N31-I31 -> 700 | P31: 116.66667 | Q31: CASH N TRANSFER | R31: EMMA CLARK | S31: CO45ZF | T31: VS FEB 23-18 | U31: SOLD | V31: Payment Assumed | AE31: =N31 -> 1200 | AG31: =N31-SUM(Z31:AF31)+X31+Y31 -> 0
B32: 110 | C32: 45139 | D32: 45104 | E32: MSL WELDON | F32: VP QE AUG 23/03 | G32: RENAULT | H32: CE55ZDW | I32: 2500 | J32: 2500 | K32: 0 | L32: 0 | M32: 45147 | N32: 2700 | O32: =N32-I32 -> 200 | P32: 33.333333 | R32: JORDEN PARKER | T32: VS QE AUG 23-55 | U32: SOLD | AB32: =N32 -> 2700 | AG32: =N32-SUM(Z32:AF32)+X32+Y32 -> 0
B33: 18 | C33: 44958 | D33: 44907 | E33: MR SPENCER | F33: VP FEB 23-26 | G33: RENAULT | H33: MM07FDF | I33: 300 | J33: 300 | K33: 0 | L33: 0 | M33: 44915 | N33: 400 | O33: =N33-I33 -> 100 | P33: 16.666667 | Q33: TRANSFER | R33: TOTAL WASTE MANAGEMENT LTD | S33: CM166LF | T33: VS FEB 23-26 | U33: SOLD | AB33: =N33 -> 400 | AG33: =N33-SUM(Z33:AF33)+X33+Y33 -> 0
B34: 30 | C34: 44958 | D34: 44943 | E34: REDCORN | F34: VP FEB 23-8 | G34: TOYOTA | H34: CK58BSU | I34: 850 | J34: 850 | K34: 0 | L34: 0 | M34: 44968 | N34: 2100 | O34: =N34-I34 -> 1250 | P34: 208.33333 | Q34: TRANSFER | R34: DANAI MAHACHI | S34: CO107EB | T34: VS FEB 23-8 | U34: SOLD | AB34: =N34 -> 2100 | AG34: =N34-SUM(Z34:AF34)+X34+Y34 -> 0
B35: 19 | C35: 44958 | D35: 44910 | E35: REDCORN | F35: VP FEB 23-22 | G35: SEAT | H35: KW59JYD | I35: 800 | J35: 800 | K35: 0 | L35: 0 | M35: 44932 | N35: 800 | O35: =N35-I35 -> 0 | P35: 0 | Q35: CASH N TRANSFER | R35: NAOMI KOJI - PATON | S35: EN93DS | T35: VS FEB 23-22 | U35: SOLD | AB35: 250 | AE35: 550 | AG35: =N35-SUM(Z35:AF35)+X35+Y35 -> 0
B36: 95 | C36: 45047 | D36: 44990 | E36: JIMMY FOXTON | F36: VP QE MAY 23/57 | G36: CITREON | H36: CK61NJV | I36: 1700 | J36: 1700 | K36: 0 | L36: 0 | M36: 45006 | N36: 2189 | O36: =N36-I36 -> 489 | P36: 81.5 | Q36: TRANSFER | R36: AMELIA RIPPIN | S36: MK426EL | T36: VS QE MAY 23/59 | U36: SOLD | AB36: =N36 -> 2189 | AG36: =N36-SUM(Z36:AF36)+X36+Y36 -> 0
B37: 31 | C37: 44958 | D37: 44943 | E37: REDCORN | F37: VP FEB 23-33 | G37: VOLKSWAGON | H37: SY06UMT | I37: 800 | J37: 800 | K37: 0 | L37: 0 | M37: 44981 | N37: 2100 | O37: =N37-I37 -> 1300 | P37: 216.66667 | R37: CHARLIE COME | T37: VS FEB 23-33 | U37: SOLD | AB37: =N37 -> 2100 | AG37: =N37-SUM(Z37:AF37)+X37+Y37 -> 0
B38: 27 | C38: 44958 | D38: 44936 | E38: REDCORN | F38: VP FEB 23-28 | G38: FORD | H38: MV13HXH | I38: 3100 | J38: 3100 | K38: 0 | L38: 0 | M38: 44982 | N38: 2689 | P38: 0 | Q38: CASH N TRANSFER | R38: OZZY CASTWOOD | T38: ADD FEB 23-139 | U38: SOLD | V38: Sale amt diff 250 in stock sheet | AB38: =N38 -> 2689 | AG38: =N38-SUM(Z38:AF38)+X38+Y38 -> 0
B39: 96 | C39: 45047 | D39: 44986 | E39: REDCORN | F39: VP QE MAY 23/58 | G39: FORD | H39: CV59BFJ | I39: 1700 | J39: 1700 | K39: 0 | L39: 0 | M39: 44996 | N39: 2189 | O39: =N39-I39 -> 489 | P39: 81.5 | Q39: TRANSFER | R39: LARA JARVIS | S39: CM19 5RQ | T39: VS QE MAY 23/60 | U39: SOLD | AB39: =N39 -> 2189 | AG39: =N39-SUM(Z39:AF39)+X39+Y39 -> 0
B40: 21 | C40: 44958 | D40: 44915 | E40: MR J HAWKES | F40: VP FEB 23-32 | G40: ROVER | H40: R154NFH | I40: 250 | J40: 250 | K40: 0 | L40: 0 | M40: 44915 | N40: 300 | O40: =N40-I40 -> 50 | P40: 8.3333333 | Q40: TRANSFER | R40: TOTAL WASTE MANAGEMENT LTD | S40: CM166LF | T40: VS FEB 23-32 | U40: SOLD | AB40: =N40 -> 300 | AG40: =N40-SUM(Z40:AF40)+X40+Y40 -> 0
B41: 22 | C41: 44958 | D41: 44927 | E41: UCC | F41: VP FEB 23-35 | G41: PEUGEOT | H41: WG62KWW | I41: 3000 | J41: 3000 | K41: 0 | L41: 0 | M41: 44954 | N41: 3826.8 | O41: =N41-I41 -> 826.8 | P41: 137.8 | Q41: TRANSFER | R41: DANIELLE AUSTIN | T41: VS FEB 23-36 | U41: SOLD | AB41: =N41 -> 3826.8 | AG41: =N41-SUM(Z41:AF41)+X41+Y41 -> 0
B42: 112 | C42: 45139 | D42: 45078 | E42: REDCORN | F42: VP QE AUG 23/06 | G42: FIAT | H42: CY60FET | I42: 800 | J42: 800 | K42: 0 | L42: 0 | M42: 45097 | N42: 1700 | O42: =N42-I42 -> 900 | P42: 150 | R42: SYED HAIDER | T42: VS QE AUG 23-58 | U42: SOLD | AB42: =N42 -> 1700 | AG42: =N42-SUM(Z42:AF42)+X42+Y42 -> 0
B43: 32 | C43: 44958 | D43: 44946 | E43: PETER MAIIETT | F43: VP FEB 23-2 | G43: FORD | H43: AO59ZLK | I43: 1500 | J43: 1500 | K43: 0 | L43: 0 | M43: 44984 | N43: 2100 | O43: =N43-I43 -> 600 | P43: 100 | Q43: TRANSFER | R43: LAMIN JAITEH | S43: PO63RT | T43: VS FEB 23-2 | U43: SOLD | AB43: =N43 -> 2100 | AG43: =N43-SUM(Z43:AF43)+X43+Y43 -> 0
